Workbook

Sheet README
A1: Pipeline and Presence: CRM and marketing-intelligence model
A2: SIMULATED data for a fictional professional-services firm in Nairobi. No real client, firm or staff data is used.
A4: Purpose | B4: Reconstructs the dashboards, data-quality checks and follow-ups that a Clients and Markets support associate would run from Salesforce, with every number a live formula.
A5: Read first | B5: Dashboard_LoS and DQ_Scorecard. Then Priority_Accounts, Dashboard_Industry, Owner_Hygiene, Feedback and Events.
A6: Inputs | B6: Inputs sheet: as-of date, stale threshold, FY27 dates, stage probabilities and simulated targets. Change them and every sheet updates.
A7: Data | B7: Opps, Accounts, Activities and Owners are the simulated Salesforce export. Opps columns O onward are formula flags.
A8: Followups | B8: Static list generated by analysis/audit.py for owner chasing.
A9: Checks | B9: The workbook is reconciled to an independent Python audit.
A10: Colour code | B10: Blue = input or raw data. Black = formula. Green = link to another sheet. Yellow fill = key output.
A11: Tags | B11: [E] = computed in Python (normalised name key, feedback theme tags).

Sheet Dashboard_LoS
A1: Line of Service dashboard (KES millions)
A2: Reconstructs the monthly BD-meeting dashboard: pipeline, FY27 coverage, win rate, cycle time and data quality. Targets are simulated.
A4: Line of service | B4: Open opps | C4: Open pipeline (KES m) | D4: Weighted pipeline (KES m) | E4: FY27-closing weighted (KES m) | F4: FY27 target (KES m) | G4: Won FY27 YTD (KES m) | H4: Remaining to target (KES m) | I4: Coverage (x) | J4: Closed, look-back | K4: Won, look-back | L4: Win rate | M4: Avg cycle, won (days) | N4: Open opps data-clean
A5: =Inputs!A20 -> Assurance | B5: =COUNTIFS(Opps!$D$5:$D$954,A5,Opps!$O$5:$O$954,1) -> 84 | C5: =SUMIFS(Opps!$F$5:$F$954,Opps!$D$5:$D$954,A5,Opps!$O$5:$O$954,1)/1000000 -> 1065.947 | D5: =SUMIFS(Opps!$S$5:$S$954,Opps!$D$5:$D$954,A5,Opps!$O$5:$O$954,1)/1000000 -> 351.31025 | E5: =SUMIFS(Opps!$S$5:$S$954,Opps!$D$5:$D$954,A5,Opps!$AE$5:$AE$954,1)/1000000 -> 347.75445 | F5: =Inputs!B20 -> 1100 | G5: =SUMIFS(Opps!$F$5:$F$954,Opps!$D$5:$D$954,A5,Opps!$AF$5:$AF$954,1)/1000000 -> 124.263 | H5: =MAX(F5-G5,0) -> 975.737 | I5: =IF(H5=0,"",E5/H5) -> 0.35640183 | J5: =COUNTIFS(Opps!$D$5:$D$954,A5,Opps!$AG$5:$AG$954,1) -> 122 | K5: =COUNTIFS(Opps!$D$5:$D$954,A5,Opps!$AG$5:$AG$954,1,Opps!$E$5:$E$954,"Closed Won") -> 40 | L5: =IF(J5=0,"",K5/J5) -> 0.32786885 | M5: =AVERAGEIFS(Opps!$AH$5:$AH$954,Opps!$D$5:$D$954,A5,Opps!$E$5:$E$954,"Closed Won") -> 165.275 | N5: =COUNTIFS(Opps!$D$5:$D$954,A5,Opps!$O$5:$O$954,1,Opps!$AD$5:$AD$954,1)/B5 -> 0.47619048
A6: =Inputs!A21 -> Tax & Legal | B6: =COUNTIFS(Opps!$D$5:$D$954,A6,Opps!$O$5:$O$954,1) -> 101 | C6: =SUMIFS(Opps!$F$5:$F$954,Opps!$D$5:$D$954,A6,Opps!$O$5:$O$954,1)/1000000 -> 942.23 | D6: =SUMIFS(Opps!$S$5:$S$954,Opps!$D$5:$D$954,A6,Opps!$O$5:$O$954,1)/1000000 -> 318.80875 | E6: =SUMIFS(Opps!$S$5:$S$954,Opps!$D$5:$D$954,A6,Opps!$AE$5:$AE$954,1)/1000000 -> 309.4824 | F6: =Inputs!B21 -> 1500 | G6: =SUMIFS(Opps!$F$5:$F$954,Opps!$D$5:$D$954,A6,Opps!$AF$5:$AF$954,1)/1000000 -> 286.747 | H6: =MAX(F6-G6,0) -> 1213.253 | I6: =IF(H6=0,"",E6/H6) -> 0.2550848 | J6: =COUNTIFS(Opps!$D$5:$D$954,A6,Opps!$AG$5:$AG$954,1) -> 167 | K6: =COUNTIFS(Opps!$D$5:$D$954,A6,Opps!$AG$5:$AG$954,1,Opps!$E$5:$E$954,"Closed Won") -> 61 | L6: =IF(J6=0,"",K6/J6) -> 0.36526946 | M6: =AVERAGEIFS(Opps!$AH$5:$AH$954,Opps!$D$5:$D$954,A6,Opps!$E$5:$E$954,"Closed Won") -> 164.44262 | N6: =COUNTIFS(Opps!$D$5:$D$954,A6,Opps!$O$5:$O$954,1,Opps!$AD$5:$AD$954,1)/B6 -> 0.48514851
A7: =Inputs!A22 -> Deals | B7: =COUNTIFS(Opps!$D$5:$D$954,A7,Opps!$O$5:$O$954,1) -> 63 | C7: =SUMIFS(Opps!$F$5:$F$954,Opps!$D$5:$D$954,A7,Opps!$O$5:$O$954,1)/1000000 -> 1979.643 | D7: =SUMIFS(Opps!$S$5:$S$954,Opps!$D$5:$D$954,A7,Opps!$O$5:$O$954,1)/1000000 -> 924.6952 | E7: =SUMIFS(Opps!$S$5:$S$954,Opps!$D$5:$D$954,A7,Opps!$AE$5:$AE$954,1)/1000000 -> 924.6952 | F7: =Inputs!B22 -> 900 | G7: =SUMIFS(Opps!$F$5:$F$954,Opps!$D$5:$D$954,A7,Opps!$AF$5:$AF$954,1)/1000000 -> 726.163 | H7: =MAX(F7-G7,0) -> 173.837 | I7: =IF(H7=0,"",E7/H7) -> 5.3193233 | J7: =COUNTIFS(Opps!$D$5:$D$954,A7,Opps!$AG$5:$AG$954,1) -> 81 | K7: =COUNTIFS(Opps!$D$5:$D$954,A7,Opps!$AG$5:$AG$954,1,Opps!$E$5:$E$954,"Closed Won") -> 38 | L7: =IF(J7=0,"",K7/J7) -> 0.4691358 | M7: =AVERAGEIFS(Opps!$AH$5:$AH$954,Opps!$D$5:$D$954,A7,Opps!$E$5:$E$954,"Closed Won") -> 145 | N7: =COUNTIFS(Opps!$D$5:$D$954,A7,Opps!$O$5:$O$954,1,Opps!$AD$5:$AD$954,1)/B7 -> 0.34920635
A8: =Inputs!A23 -> Consulting | B8: =COUNTIFS(Opps!$D$5:$D$954,A8,Opps!$O$5:$O$954,1) -> 95 | C8: =SUMIFS(Opps!$F$5:$F$954,Opps!$D$5:$D$954,A8,Opps!$O$5:$O$954,1)/1000000 -> 2486.486 | D8: =SUMIFS(Opps!$S$5:$S$954,Opps!$D$5:$D$954,A8,Opps!$O$5:$O$954,1)/1000000 -> 1025.7814 | E8: =SUMIFS(Opps!$S$5:$S$954,Opps!$D$5:$D$954,A8,Opps!$AE$5:$AE$954,1)/1000000 -> 1018.9516 | F8: =Inputs!B23 -> 1900 | G8: =SUMIFS(Opps!$F$5:$F$954,Opps!$D$5:$D$954,A8,Opps!$AF$5:$AF$954,1)/1000000 -> 576.565 | H8: =MAX(F8-G8,0) -> 1323.435 | I8: =IF(H8=0,"",E8/H8) -> 0.7699295 | J8: =COUNTIFS(Opps!$D$5:$D$954,A8,Opps!$AG$5:$AG$954,1) -> 152 | K8: =COUNTIFS(Opps!$D$5:$D$954,A8,Opps!$AG$5:$AG$954,1,Opps!$E$5:$E$954,"Closed Won") -> 53 | L8: =IF(J8=0,"",K8/J8) -> 0.34868421 | M8: =AVERAGEIFS(Opps!$AH$5:$AH$954,Opps!$D$5:$D$954,A8,Opps!$E$5:$E$954,"Closed Won") -> 159.66038 | N8: =COUNTIFS(Opps!$D$5:$D$954,A8,Opps!$O$5:$O$954,1,Opps!$AD$5:$AD$954,1)/B8 -> 0.43157895
A9: =Inputs!A24 -> Risk | B9: =COUNTIFS(Opps!$D$5:$D$954,A9,Opps!$O$5:$O$954,1) -> 30 | C9: =SUMIFS(Opps!$F$5:$F$954,Opps!$D$5:$D$954,A9,Opps!$O$5:$O$954,1)/1000000 -> 341.496 | D9: =SUMIFS(Opps!$S$5:$S$954,Opps!$D$5:$D$954,A9,Opps!$O$5:$O$954,1)/1000000 -> 97.7875 | E9: =SUMIFS(Opps!$S$5:$S$954,Opps!$D$5:$D$954,A9,Opps!$AE$5:$AE$954,1)/1000000 -> 97.7875 | F9: =Inputs!B24 -> 600 | G9: =SUMIFS(Opps!$F$5:$F$954,Opps!$D$5:$D$954,A9,Opps!$AF$5:$AF$954,1)/1000000 -> 186.987 | H9: =MAX(F9-G9,0) -> 413.013 | I9: =IF(H9=0,"",E9/H9) -> 0.23676616 | J9: =COUNTIFS(Opps!$D$5:$D$954,A9,Opps!$AG$5:$AG$954,1) -> 55 | K9: =COUNTIFS(Opps!$D$5:$D$954,A9,Opps!$AG$5:$AG$954,1,Opps!$E$5:$E$954,"Closed Won") -> 24 | L9: =IF(J9=0,"",K9/J9) -> 0.43636364 | M9: =AVERAGEIFS(Opps!$AH$5:$AH$954,Opps!$D$5:$D$954,A9,Opps!$E$5:$E$954,"Closed Won") -> 147.5 | N9: =COUNTIFS(Opps!$D$5:$D$954,A9,Opps!$O$5:$O$954,1,Opps!$AD$5:$AD$954,1)/B9 -> 0.53333333
A10: Total | B10: =SUM(B5:B9) -> 373 | C10: =SUM(C5:C9) -> 6815.802 | D10: =SUM(D5:D9) -> 2718.3831 | E10: =SUM(E5:E9) -> 2698.6712 | F10: =SUM(F5:F9) -> 6000 | G10: =SUM(G5:G9) -> 1900.725 | H10: =SUM(H5:H9) -> 4099.275 | I10: =E10/H10 -> 0.6583289 | J10: =SUM(J5:J9) -> 577 | K10: =SUM(K5:K9) -> 216 | L10: =K10/J10 -> 0.37435009 | M10: =AVERAGEIFS(Opps!$AH$5:$AH$954,Opps!$E$5:$E$954,"Closed Won") -> 158.12037 | N10: =COUNTIFS(Opps!$O$5:$O$954,1,Opps!$AD$5:$AD$954,1)/B10 -> 0.45040214
A12: Coverage = weighted pipeline expected to close in FY27 / (target - won year to date). Below 1.0x means the weighted pipeline alone cannot reach the target.

Sheet Dashboard_Industry
A1: Industry group dashboard (KES millions)
A2: Industry comes from the account record; accounts without an industry fall into 'Unassigned' until fixed.
A4: Industry | B4: Open opps | C4: Open pipeline (KES m) | D4: Weighted pipeline (KES m) | E4: Share of weighted | F4: Closed, look-back | G4: Won, look-back | H4: Win rate | I4: Open opps data-clean
A5: Agribusiness | B5: =COUNTIFS(Opps!$P$5:$P$954,A5,Opps!$O$5:$O$954,1) -> 38 | C5: =SUMIFS(Opps!$F$5:$F$954,Opps!$P$5:$P$954,A5,Opps!$O$5:$O$954,1)/1000000 -> 671.024 | D5: =SUMIFS(Opps!$S$5:$S$954,Opps!$P$5:$P$954,A5,Opps!$O$5:$O$954,1)/1000000 -> 318.40885 | E5: =D5/D$14 -> 0.11713171 | F5: =COUNTIFS(Opps!$P$5:$P$954,A5,Opps!$AG$5:$AG$954,1) -> 50 | G5: =COUNTIFS(Opps!$P$5:$P$954,A5,Opps!$AG$5:$AG$954,1,Opps!$E$5:$E$954,"Closed Won") -> 16 | H5: =IF(F5=0,"",G5/F5) -> 0.32 | I5: =IF(B5=0,"",COUNTIFS(Opps!$P$5:$P$954,A5,Opps!$O$5:$O$954,1,Opps!$AD$5:$AD$954,1)/B5) -> 0.42105263
A6: Consumer & Retail | B6: =COUNTIFS(Opps!$P$5:$P$954,A6,Opps!$O$5:$O$954,1) -> 45 | C6: =SUMIFS(Opps!$F$5:$F$954,Opps!$P$5:$P$954,A6,Opps!$O$5:$O$954,1)/1000000 -> 741.69 | D6: =SUMIFS(Opps!$S$5:$S$954,Opps!$P$5:$P$954,A6,Opps!$O$5:$O$954,1)/1000000 -> 265.83615 | E6: =D6/D$14 -> 0.097792011 | F6: =COUNTIFS(Opps!$P$5:$P$954,A6,Opps!$AG$5:$AG$954,1) -> 63 | G6: =COUNTIFS(Opps!$P$5:$P$954,A6,Opps!$AG$5:$AG$954,1,Opps!$E$5:$E$954,"Closed Won") -> 18 | H6: =IF(F6=0,"",G6/F6) -> 0.28571429 | I6: =IF(B6=0,"",COUNTIFS(Opps!$P$5:$P$954,A6,Opps!$O$5:$O$954,1,Opps!$AD$5:$AD$954,1)/B6) -> 0.42222222
A7: Energy & Resources | B7: =COUNTIFS(Opps!$P$5:$P$954,A7,Opps!$O$5:$O$954,1) -> 44 | C7: =SUMIFS(Opps!$F$5:$F$954,Opps!$P$5:$P$954,A7,Opps!$O$5:$O$954,1)/1000000 -> 936.058 | D7: =SUMIFS(Opps!$S$5:$S$954,Opps!$P$5:$P$954,A7,Opps!$O$5:$O$954,1)/1000000 -> 394.9023 | E7: =D7/D$14 -> 0.14527103 | F7: =COUNTIFS(Opps!$P$5:$P$954,A7,Opps!$AG$5:$AG$954,1) -> 56 | G7: =COUNTIFS(Opps!$P$5:$P$954,A7,Opps!$AG$5:$AG$954,1,Opps!$E$5:$E$954,"Closed Won") -> 31 | H7: =IF(F7=0,"",G7/F7) -> 0.55357143 | I7: =IF(B7=0,"",COUNTIFS(Opps!$P$5:$P$954,A7,Opps!$O$5:$O$954,1,Opps!$AD$5:$AD$954,1)/B7) -> 0.52272727
A8: Financial Services | B8: =COUNTIFS(Opps!$P$5:$P$954,A8,Opps!$O$5:$O$954,1) -> 99 | C8: =SUMIFS(Opps!$F$5:$F$954,Opps!$P$5:$P$954,A8,Opps!$O$5:$O$954,1)/1000000 -> 1758.697 | D8: =SUMIFS(Opps!$S$5:$S$954,Opps!$P$5:$P$954,A8,Opps!$O$5:$O$954,1)/1000000 -> 603.7617 | E8: =D8/D$14 -> 0.22210324 | F8: =COUNTIFS(Opps!$P$5:$P$954,A8,Opps!$AG$5:$AG$954,1) -> 157 | G8: =COUNTIFS(Opps!$P$5:$P$954,A8,Opps!$AG$5:$AG$954,1,Opps!$E$5:$E$954,"Closed Won") -> 59 | H8: =IF(F8=0,"",G8/F8) -> 0.37579618 | I8: =IF(B8=0,"",COUNTIFS(Opps!$P$5:$P$954,A8,Opps!$O$5:$O$954,1,Opps!$AD$5:$AD$954,1)/B8) -> 0.52525253
A9: Health | B9: =COUNTIFS(Opps!$P$5:$P$954,A9,Opps!$O$5:$O$954,1) -> 13 | C9: =SUMIFS(Opps!$F$5:$F$954,Opps!$P$5:$P$954,A9,Opps!$O$5:$O$954,1)/1000000 -> 160.42 | D9: =SUMIFS(Opps!$S$5:$S$954,Opps!$P$5:$P$954,A9,Opps!$O$5:$O$954,1)/1000000 -> 64.63045 | E9: =D9/D$14 -> 0.023775328 | F9: =COUNTIFS(Opps!$P$5:$P$954,A9,Opps!$AG$5:$AG$954,1) -> 28 | G9: =COUNTIFS(Opps!$P$5:$P$954,A9,Opps!$AG$5:$AG$954,1,Opps!$E$5:$E$954,"Closed Won") -> 16 | H9: =IF(F9=0,"",G9/F9) -> 0.57142857 | I9: =IF(B9=0,"",COUNTIFS(Opps!$P$5:$P$954,A9,Opps!$O$5:$O$954,1,Opps!$AD$5:$AD$954,1)/B9) -> 0.46153846
A10: Public Sector & Development | B10: =COUNTIFS(Opps!$P$5:$P$954,A10,Opps!$O$5:$O$954,1) -> 47 | C10: =SUMIFS(Opps!$F$5:$F$954,Opps!$P$5:$P$954,A10,Opps!$O$5:$O$954,1)/1000000 -> 587.049 | D10: =SUMIFS(Opps!$S$5:$S$954,Opps!$P$5:$P$954,A10,Opps!$O$5:$O$954,1)/1000000 -> 220.68835 | E10: =D10/D$14 -> 0.081183682 | F10: =COUNTIFS(Opps!$P$5:$P$954,A10,Opps!$AG$5:$AG$954,1) -> 73 | G10: =COUNTIFS(Opps!$P$5:$P$954,A10,Opps!$AG$5:$AG$954,1,Opps!$E$5:$E$954,"Closed Won") -> 28 | H10: =IF(F10=0,"",G10/F10) -> 0.38356164 | I10: =IF(B10=0,"",COUNTIFS(Opps!$P$5:$P$954,A10,Opps!$O$5:$O$954,1,Opps!$AD$5:$AD$954,1)/B10) -> 0.36170213
A11: Real Estate & Infrastructure | B11: =COUNTIFS(Opps!$P$5:$P$954,A11,Opps!$O$5:$O$954,1) -> 19 | C11: =SUMIFS(Opps!$F$5:$F$954,Opps!$P$5:$P$954,A11,Opps!$O$5:$O$954,1)/1000000 -> 536.621 | D11: =SUMIFS(Opps!$S$5:$S$954,Opps!$P$5:$P$954,A11,Opps!$O$5:$O$954,1)/1000000 -> 311.1257 | E11: =D11/D$14 -> 0.11445248 | F11: =COUNTIFS(Opps!$P$5:$P$954,A11,Opps!$AG$5:$AG$954,1) -> 21 | G11: =COUNTIFS(Opps!$P$5:$P$954,A11,Opps!$AG$5:$AG$954,1,Opps!$E$5:$E$954,"Closed Won") -> 6 | H11: =IF(F11=0,"",G11/F11) -> 0.28571429 | I11: =IF(B11=0,"",COUNTIFS(Opps!$P$5:$P$954,A11,Opps!$O$5:$O$954,1,Opps!$AD$5:$AD$954,1)/B11) -> 0.36842105
A12: Technology, Media & Telecom | B12: =COUNTIFS(Opps!$P$5:$P$954,A12,Opps!$O$5:$O$954,1) -> 56 | C12: =SUMIFS(Opps!$F$5:$F$954,Opps!$P$5:$P$954,A12,Opps!$O$5:$O$954,1)/1000000 -> 1187.057 | D12: =SUMIFS(Opps!$S$5:$S$954,Opps!$P$5:$P$954,A12,Opps!$O$5:$O$954,1)/1000000 -> 443.7796 | E12: =D12/D$14 -> 0.16325131 | F12: =COUNTIFS(Opps!$P$5:$P$954,A12,Opps!$AG$5:$AG$954,1) -> 100 | G12: =COUNTIFS(Opps!$P$5:$P$954,A12,Opps!$AG$5:$AG$954,1,Opps!$E$5:$E$954,"Closed Won") -> 37 | H12: =IF(F12=0,"",G12/F12) -> 0.37 | I12: =IF(B12=0,"",COUNTIFS(Opps!$P$5:$P$954,A12,Opps!$O$5:$O$954,1,Opps!$AD$5:$AD$954,1)/B12) -> 0.42857143
A13: Unassigned | B13: =COUNTIFS(Opps!$P$5:$P$954,A13,Opps!$O$5:$O$954,1) -> 12 | C13: =SUMIFS(Opps!$F$5:$F$954,Opps!$P$5:$P$954,A13,Opps!$O$5:$O$954,1)/1000000 -> 237.186 | D13: =SUMIFS(Opps!$S$5:$S$954,Opps!$P$5:$P$954,A13,Opps!$O$5:$O$954,1)/1000000 -> 95.25 | E13: =D13/D$14 -> 0.035039211 | F13: =COUNTIFS(Opps!$P$5:$P$954,A13,Opps!$AG$5:$AG$954,1) -> 29 | G13: =COUNTIFS(Opps!$P$5:$P$954,A13,Opps!$AG$5:$AG$954,1,Opps!$E$5:$E$954,"Closed Won") -> 5 | H13: =IF(F13=0,"",G13/F13) -> 0.17241379 | I13: =IF(B13=0,"",COUNTIFS(Opps!$P$5:$P$954,A13,Opps!$O$5:$O$954,1,Opps!$AD$5:$AD$954,1)/B13) -> 0.33333333
A14: Total | B14: =SUM(B5:B13) -> 373 | C14: =SUM(C5:C13) -> 6815.802 | D14: =SUM(D5:D13) -> 2718.3831 | E14: =SUM(E5:E13) -> 1 | F14: =SUM(F5:F13) -> 577 | G14: =SUM(G5:G13) -> 216 | H14: =G14/F14 -> 0.37435009

Sheet Priority_Accounts
A1: Priority accounts: pipeline and recency of contact
A2: Priority list is an input. Open opportunities and last touch are live formulas.
A4: Account ID | B4: Account | C4: Industry | D4: Driver | E4: Open opps | F4: Weighted pipeline (KES m) | G4: Last touchpoint | H4: Days since touch | I4: Needs attention?
A5: A0001 | B5: =INDEX(Accounts!$B$5:$B$336,MATCH(A5,Accounts!$A$5:$A$336,0)) -> Jambo Microfinance Limited | C5: =INDEX(Accounts!$K$5:$K$336,MATCH(A5,Accounts!$A$5:$A$336,0)) -> Financial Services | D5: =INDEX(Owners!$B$5:$B$32,MATCH(INDEX(Accounts!$G$5:$G$336,MATCH(A5,Accounts!$A$5:$A$336,0)),Owners!$A$5:$A$32,0)) -> Amina Otieno | E5: =COUNTIFS(Opps!$B$5:$B$954,A5,Opps!$O$5:$O$954,1) -> 4 | F5: =SUMIFS(Opps!$S$5:$S$954,Opps!$B$5:$B$954,A5,Opps!$O$5:$O$954,1)/1000000 -> 68.29475 | G5: =IF(COUNTIFS(Activities!$B$5:$B$1453,A5)=0,"",_xlfn.MAXIFS(Activities!$D$5:$D$1453,Activities!$B$5:$B$1453,A5)) -> 46259 | H5: =IF(G5="","",Inputs!$B$4-G5) -> 55 | I5: =IF(OR(E5=0,H5="",H5>90),"Yes","")
A6: A0002 | B6: =INDEX(Accounts!$B$5:$B$336,MATCH(A6,Accounts!$A$5:$A$336,0)) -> Umoja Capital Limited | C6: =INDEX(Accounts!$K$5:$K$336,MATCH(A6,Accounts!$A$5:$A$336,0)) -> Financial Services | D6: =INDEX(Owners!$B$5:$B$32,MATCH(INDEX(Accounts!$G$5:$G$336,MATCH(A6,Accounts!$A$5:$A$336,0)),Owners!$A$5:$A$32,0)) -> Brian Chebet | E6: =COUNTIFS(Opps!$B$5:$B$954,A6,Opps!$O$5:$O$954,1) -> 2 | F6: =SUMIFS(Opps!$S$5:$S$954,Opps!$B$5:$B$954,A6,Opps!$O$5:$O$954,1)/1000000 -> 7.272 | G6: =IF(COUNTIFS(Activities!$B$5:$B$1453,A6)=0,"",_xlfn.MAXIFS(Activities!$D$5:$D$1453,Activities!$B$5:$B$1453,A6)) -> 46245 | H6: =IF(G6="","",Inputs!$B$4-G6) -> 69 | I6: =IF(OR(E6=0,H6="",H6>90),"Yes","")
A7: A0003 | B7: =INDEX(Accounts!$B$5:$B$336,MATCH(A7,Accounts!$A$5:$A$336,0)) -> Nile Microfinance Limited | C7: =INDEX(Accounts!$K$5:$K$336,MATCH(A7,Accounts!$A$5:$A$336,0)) -> Financial Services | D7: =INDEX(Owners!$B$5:$B$32,MATCH(INDEX(Accounts!$G$5:$G$336,MATCH(A7,Accounts!$A$5:$A$336,0)),Owners!$A$5:$A$32,0)) -> Cynthia Odhiambo | E7: =COUNTIFS(Opps!$B$5:$B$954,A7,Opps!$O$5:$O$954,1) -> 4 | F7: =SUMIFS(Opps!$S$5:$S$954,Opps!$B$5:$B$954,A7,Opps!$O$5:$O$954,1)/1000000 -> 12.8949 | G7: =IF(COUNTIFS(Activities!$B$5:$B$1453,A7)=0,"",_xlfn.MAXIFS(Activities!$D$5:$D$1453,Activities!$B$5:$B$1453,A7)) -> 46261 | H7: =IF(G7="","",Inputs!$B$4-G7) -> 53 | I7: =IF(OR(E7=0,H7="",H7>90),"Yes","")
A8: A0004 | B8: =INDEX(Accounts!$B$5:$B$336,MATCH(A8,Accounts!$A$5:$A$336,0)) -> Pwani Asset Managers Limited | C8: =INDEX(Accounts!$K$5:$K$336,MATCH(A8,Accounts!$A$5:$A$336,0)) -> Financial Services | D8: =INDEX(Owners!$B$5:$B$32,MATCH(INDEX(Accounts!$G$5:$G$336,MATCH(A8,Accounts!$A$5:$A$336,0)),Owners!$A$5:$A$32,0)) -> Daniel Wanjiru | E8: =COUNTIFS(Opps!$B$5:$B$954,A8,Opps!$O$5:$O$954,1) -> 4 | F8: =SUMIFS(Opps!$S$5:$S$954,Opps!$B$5:$B$954,A8,Opps!$O$5:$O$954,1)/1000000 -> 11.1043 | G8: =IF(COUNTIFS(Activities!$B$5:$B$1453,A8)=0,"",_xlfn.MAXIFS(Activities!$D$5:$D$1453,Activities!$B$5:$B$1453,A8)) -> 46292 | H8: =IF(G8="","",Inputs!$B$4-G8) -> 22 | I8: =IF(OR(E8=0,H8="",H8>90),"Yes","")
A9: A0005 | B9: =INDEX(Accounts!$B$5:$B$336,MATCH(A9,Accounts!$A$5:$A$336,0)) -> Twiga Agri Limited | C9: =INDEX(Accounts!$K$5:$K$336,MATCH(A9,Accounts!$A$5:$A$336,0)) -> Agribusiness | D9: =INDEX(Owners!$B$5:$B$32,MATCH(INDEX(Accounts!$G$5:$G$336,MATCH(A9,Accounts!$A$5:$A$336,0)),Owners!$A$5:$A$32,0)) -> Esther Kiprop | E9: =COUNTIFS(Opps!$B$5:$B$954,A9,Opps!$O$5:$O$954,1) -> 5 | F9: =SUMIFS(Opps!$S$5:$S$954,Opps!$B$5:$B$954,A9,Opps!$O$5:$O$954,1)/1000000 -> 8.21025 | G9: =IF(COUNTIFS(Activities!$B$5:$B$1453,A9)=0,"",_xlfn.MAXIFS(Activities!$D$5:$D$1453,Activities!$B$5:$B$1453,A9)) -> 46313 | H9: =IF(G9="","",Inputs!$B$4-G9) -> 1 | I9: =IF(OR(E9=0,H9="",H9>90),"Yes","")
A10: A0006 | B10: =INDEX(Accounts!$B$5:$B$336,MATCH(A10,Accounts!$A$5:$A$336,0)) -> Kibo Microfinance Limited | C10: =INDEX(Accounts!$K$5:$K$336,MATCH(A10,Accounts!$A$5:$A$336,0)) -> Financial Services | D10: =INDEX(Owners!$B$5:$B$32,MATCH(INDEX(Accounts!$G$5:$G$336,MATCH(A10,Accounts!$A$5:$A$336,0)),Owners!$A$5:$A$32,0)) -> Felix Barasa | E10: =COUNTIFS(Opps!$B$5:$B$954,A10,Opps!$O$5:$O$954,1) -> 2 | F10: =SUMIFS(Opps!$S$5:$S$954,Opps!$B$5:$B$954,A10,Opps!$O$5:$O$954,1)/1000000 -> 22.3261 | G10: =IF(COUNTIFS(Activities!$B$5:$B$1453,A10)=0,"",_xlfn.MAXIFS(Activities!$D$5:$D$1453,Activities!$B$5:$B$1453,A10)) -> 46286 | H10: =IF(G10="","",Inputs!$B$4-G10) -> 28 | I10: =IF(OR(E10=0,H10="",H10>90),"Yes","")
A11: A0007 | B11: =INDEX(Accounts!$B$5:$B$336,MATCH(A11,Accounts!$A$5:$A$336,0)) -> Nile County Government | C11: =INDEX(Accounts!$K$5:$K$336,MATCH(A11,Accounts!$A$5:$A$336,0)) -> Public Sector & Development | D11: =INDEX(Owners!$B$5:$B$32,MATCH(INDEX(Accounts!$G$5:$G$336,MATCH(A11,Accounts!$A$5:$A$336,0)),Owners!$A$5:$A$32,0)) -> Grace Mwangi | E11: =COUNTIFS(Opps!$B$5:$B$954,A11,Opps!$O$5:$O$954,1) -> 4 | F11: =SUMIFS(Opps!$S$5:$S$954,Opps!$B$5:$B$954,A11,Opps!$O$5:$O$954,1)/1000000 -> 10.19965 | G11: =IF(COUNTIFS(Activities!$B$5:$B$1453,A11)=0,"",_xlfn.MAXIFS(Activities!$D$5:$D$1453,Activities!$B$5:$B$1453,A11)) -> 46234 | H11: =IF(G11="","",Inputs!$B$4-G11) -> 80 | I11: =IF(OR(E11=0,H11="",H11>90),"Yes","")
A12: A0008 | B12: =INDEX(Accounts!$B$5:$B$336,MATCH(A12,Accounts!$A$5:$A$336,0)) -> Tembo Capital Limited | C12: =INDEX(Accounts!$K$5:$K$336,MATCH(A12,Accounts!$A$5:$A$336,0)) -> Financial Services | D12: =INDEX(Owners!$B$5:$B$32,MATCH(INDEX(Accounts!$G$5:$G$336,MATCH(A12,Accounts!$A$5:$A$336,0)),Owners!$A$5:$A$32,0)) -> Amina Otieno | E12: =COUNTIFS(Opps!$B$5:$B$954,A12,Opps!$O$5:$O$954,1) -> 5 | F12: =SUMIFS(Opps!$S$5:$S$954,Opps!$B$5:$B$954,A12,Opps!$O$5:$O$954,1)/1000000 -> 10.6029 | G12: =IF(COUNTIFS(Activities!$B$5:$B$1453,A12)=0,"",_xlfn.MAXIFS(Activities!$D$5:$D$1453,Activities!$B$5:$B$1453,A12)) -> 46293 | H12: =IF(G12="","",Inputs!$B$4-G12) -> 21 | I12: =IF(OR(E12=0,H12="",H12>90),"Yes","")
A13: A0009 | B13: =INDEX(Accounts!$B$5:$B$336,MATCH(A13,Accounts!$A$5:$A$336,0)) -> Rift Cloud Limited | C13: =INDEX(Accounts!$K$5:$K$336,MATCH(A13,Accounts!$A$5:$A$336,0)) -> Technology, Media & Telecom | D13: =INDEX(Owners!$B$5:$B$32,MATCH(INDEX(Accounts!$G$5:$G$336,MATCH(A13,Accounts!$A$5:$A$336,0)),Owners!$A$5:$A$32,0)) -> Brian Chebet | E13: =COUNTIFS(Opps!$B$5:$B$954,A13,Opps!$O$5:$O$954,1) -> 2 | F13: =SUMIFS(Opps!$S$5:$S$954,Opps!$B$5:$B$954,A13,Opps!$O$5:$O$954,1)/1000000 -> 4.27325 | G13: =IF(COUNTIFS(Activities!$B$5:$B$1453,A13)=0,"",_xlfn.MAXIFS(Activities!$D$5:$D$1453,Activities!$B$5:$B$1453,A13)) -> 46306 | H13: =IF(G13="","",Inputs!$B$4-G13) -> 8 | I13: =IF(OR(E13=0,H13="",H13>90),"Yes","")
A14: A0010 | B14: =INDEX(Accounts!$B$5:$B$336,MATCH(A14,Accounts!$A$5:$A$336,0)) -> Umoja Asset Managers Limited | C14: =INDEX(Accounts!$K$5:$K$336,MATCH(A14,Accounts!$A$5:$A$336,0)) -> Financial Services | D14: =INDEX(Owners!$B$5:$B$32,MATCH(INDEX(Accounts!$G$5:$G$336,MATCH(A14,Accounts!$A$5:$A$336,0)),Owners!$A$5:$A$32,0)) -> Cynthia Odhiambo | E14: =COUNTIFS(Opps!$B$5:$B$954,A14,Opps!$O$5:$O$954,1) -> 4 | F14: =SUMIFS(Opps!$S$5:$S$954,Opps!$B$5:$B$954,A14,Opps!$O$5:$O$954,1)/1000000 -> 77.5095 | G14: =IF(COUNTIFS(Activities!$B$5:$B$1453,A14)=0,"",_xlfn.MAXIFS(Activities!$D$5:$D$1453,Activities!$B$5:$B$1453,A14)) -> 46262 | H14: =IF(G14="","",Inputs!$B$4-G14) -> 52 | I14: =IF(OR(E14=0,H14="",H14>90),"Yes","")
A15: A0011 | B15: =INDEX(Accounts!$B$5:$B$336,MATCH(A15,Accounts!$A$5:$A$336,0)) -> Rift Capital Limited | C15: =INDEX(Accounts!$K$5:$K$336,MATCH(A15,Accounts!$A$5:$A$336,0)) -> Financial Services | D15: =INDEX(Owners!$B$5:$B$32,MATCH(INDEX(Accounts!$G$5:$G$336,MATCH(A15,Accounts!$A$5:$A$336,0)),Owners!$A$5:$A$32,0)) -> Daniel Wanjiru | E15: =COUNTIFS(Opps!$B$5:$B$954,A15,Opps!$O$5:$O$954,1) -> 5 | F15: =SUMIFS(Opps!$S$5:$S$954,Opps!$B$5:$B$954,A15,Opps!$O$5:$O$954,1)/1000000 -> 20.50555 | G15: =IF(COUNTIFS(Activities!$B$5:$B$1453,A15)=0,"",_xlfn.MAXIFS(Activities!$D$5:$D$1453,Activities!$B$5:$B$1453,A15)) -> 46307 | H15: =IF(G15="","",Inputs!$B$4-G15) -> 7 | I15: =IF(OR(E15=0,H15="",H15>90),"Yes","")
A16: A0012 | B16: =INDEX(Accounts!$B$5:$B$336,MATCH(A16,Accounts!$A$5:$A$336,0)) -> Safari Microfinance Limited | C16: =INDEX(Accounts!$K$5:$K$336,MATCH(A16,Accounts!$A$5:$A$336,0)) -> Financial Services | D16: =INDEX(Owners!$B$5:$B$32,MATCH(INDEX(Accounts!$G$5:$G$336,MATCH(A16,Accounts!$A$5:$A$336,0)),Owners!$A$5:$A$32,0)) -> Esther Kiprop | E16: =COUNTIFS(Opps!$B$5:$B$954,A16,Opps!$O$5:$O$954,1) -> 5 | F16: =SUMIFS(Opps!$S$5:$S$954,Opps!$B$5:$B$954,A16,Opps!$O$5:$O$954,1)/1000000 -> 13.684 | G16: =IF(COUNTIFS(Activities!$B$5:$B$1453,A16)=0,"",_xlfn.MAXIFS(Activities!$D$5:$D$1453,Activities!$B$5:$B$1453,A16)) -> 46261 | H16: =IF(G16="","",Inputs!$B$4-G16) -> 53 | I16: =IF(OR(E16=0,H16="",H16>90),"Yes","")
... A44: A0040 | B44: =INDEX(Accounts!$B$5:$B$336,MATCH(A44,Accounts!$A$5:$A$336,0)) -> Amani Insurance Limited | C44: =INDEX(Accounts!$K$5:$K$336,MATCH(A44,Accounts!$A$5:$A$336,0)) -> Financial Services | D44: =INDEX(Owners!$B$5:$B$32,MATCH(INDEX(Accounts!$G$5:$G$336,MATCH(A44,Accounts!$A$5:$A$336,0)),Owners!$A$5:$A$32,0)) -> Esther Kiprop | E44: =COUNTIFS(Opps!$B$5:$B$954,A44,Opps!$O$5:$O$954,1) -> 2 | F44: =SUMIFS(Opps!$S$5:$S$954,Opps!$B$5:$B$954,A44,Opps!$O$5:$O$954,1)/1000000 -> 16.7685 | G44: =IF(COUNTIFS(Activities!$B$5:$B$1453,A44)=0,"",_xlfn.MAXIFS(Activities!$D$5:$D$1453,Activities!$B$5:$B$1453,A44)) -> 46312 | H44: =IF(G44="","",Inputs!$B$4-G44) -> 2 | I44: =IF(OR(E44=0,H44="",H44>90),"Yes","")
A46: Priority accounts | E46: =COUNTA(A5:A44) -> 40
A47: With at least one open opportunity | E47: =COUNTIF(E5:E44,">0") -> 38
A48: Touched in the last 90 days | E48: =COUNTIFS(H5:H44,"<=90") -> 37
A49: Needing attention (no open opp, or no touch in 90 days) | E49: =COUNTIF(I5:I44,"Yes") -> 5

Sheet DQ_Scorecard
A1: Salesforce data-quality scorecard
A2: Eight opportunity rules and two account rules. Open-opportunity clean rate is the headline measure.
A4: Rule | B4: Applies to | C4: Failing | D4: Population | E4: Failure rate | F4: What the owner should do
A5: Amount missing or zero | B5: all opportunities | C5: =SUM(Opps!$U$5:$U$954) -> 66 | D5: =COUNTA(Opps!$A$5:$A$954) -> 950 | E5: =C5/D5 -> 0.069473684 | F5: Add an estimated amount
A6: No owner assigned | B6: all opportunities | C6: =SUM(Opps!$V$5:$V$954) -> 27 | D6: =COUNTA(Opps!$A$5:$A$954) -> 950 | E6: =C6/D6 -> 0.028421053 | F6: Assign an owner
A7: Owner has left or is inactive | B7: open | C7: =SUM(Opps!$W$5:$W$954) -> 40 | D7: =SUM(Opps!$O$5:$O$954) -> 373 | E7: =C7/D7 -> 0.10723861 | F7: Reassign the opportunity
A8: Open with close date in the past | B8: open | C8: =SUM(Opps!$X$5:$X$954) -> 56 | D8: =SUM(Opps!$O$5:$O$954) -> 373 | E8: =C8/D8 -> 0.15013405 | F8: Update the close date or close it
A9: No activity for more than the stale threshold | B9: open | C9: =SUM(Opps!$Y$5:$Y$954) -> 82 | D9: =SUM(Opps!$O$5:$O$954) -> 373 | E9: =C9/D9 -> 0.21983914 | F9: Log an activity or confirm status
A10: Probability does not match stage | B10: open | C10: =SUM(Opps!$Z$5:$Z$954) -> 22 | D10: =SUM(Opps!$O$5:$O$954) -> 373 | E10: =C10/D10 -> 0.058981233 | F10: Correct the probability
A11: No next step recorded | B11: open | C11: =SUM(Opps!$AA$5:$AA$954) -> 29 | D11: =SUM(Opps!$O$5:$O$954) -> 373 | E11: =C11/D11 -> 0.077747989 | F11: Record the next step
A12: Lost without a reason | B12: closed lost | C12: =SUM(Opps!$AB$5:$AB$954) -> 64 | D12: =COUNTIFS(Opps!$E$5:$E$954,"Closed Lost") -> 361 | E12: =C12/D12 -> 0.17728532 | F12: Add the lost reason
A14: Account: missing industry | C14: =SUM(Accounts!$L$5:$L$336) -> 17 | D14: =COUNTA(Accounts!$A$5:$A$336) -> 332 | E14: =C14/D14 -> 0.051204819
A15: Account: part of a duplicate pair | C15: =SUM(Accounts!$I$5:$I$336) -> 24 | D15: =COUNTA(Accounts!$A$5:$A$336) -> 332 | E15: =C15/D15 -> 0.072289157
A17: Open opportunities with no data issue | C17: =COUNTIFS(Opps!$O$5:$O$954,1,Opps!$AD$5:$AD$954,1) -> 168 | D17: =SUM(Opps!$O$5:$O$954) -> 373 | E17: =C17/D17 -> 0.45040214
A18: Open opportunities with at least one issue | C18: =D17-C17 -> 205 | E18: =C18/D17 -> 0.54959786
A19: Issue count to chase (all rules, all opportunities) | C19: =SUM(Opps!$AC$5:$AC$954) -> 386

Sheet Owner_Hygiene
A1: Owner hygiene: who has opportunities to fix
A2: Use this to prepare the follow-up calls and the Salesforce clinics. Open opportunities only.
A4: Owner ID | B4: Name | C4: Grade | D4: Active? | E4: Open opps | F4: Opps with an issue | G4: Clean rate | H4: Issues to fix
A5: =Owners!A5 -> U001 | B5: =Owners!B5 -> Amina Otieno | C5: =Owners!C5 -> Partner | D5: =Owners!E5 -> Yes | E5: =COUNTIFS(Opps!$K$5:$K$954,A5,Opps!$O$5:$O$954,1) -> 23 | F5: =COUNTIFS(Opps!$K$5:$K$954,A5,Opps!$O$5:$O$954,1,Opps!$AD$5:$AD$954,0) -> 10 | G5: =IF(E5=0,"",1-F5/E5) -> 0.56521739 | H5: =SUMIFS(Opps!$AC$5:$AC$954,Opps!$K$5:$K$954,A5,Opps!$O$5:$O$954,1) -> 13
A6: =Owners!A6 -> U002 | B6: =Owners!B6 -> Brian Chebet | C6: =Owners!C6 -> Partner | D6: =Owners!E6 -> Yes | E6: =COUNTIFS(Opps!$K$5:$K$954,A6,Opps!$O$5:$O$954,1) -> 14 | F6: =COUNTIFS(Opps!$K$5:$K$954,A6,Opps!$O$5:$O$954,1,Opps!$AD$5:$AD$954,0) -> 7 | G6: =IF(E6=0,"",1-F6/E6) -> 0.5 | H6: =SUMIFS(Opps!$AC$5:$AC$954,Opps!$K$5:$K$954,A6,Opps!$O$5:$O$954,1) -> 8
A7: =Owners!A7 -> U003 | B7: =Owners!B7 -> Cynthia Odhiambo | C7: =Owners!C7 -> Partner | D7: =Owners!E7 -> Yes | E7: =COUNTIFS(Opps!$K$5:$K$954,A7,Opps!$O$5:$O$954,1) -> 22 | F7: =COUNTIFS(Opps!$K$5:$K$954,A7,Opps!$O$5:$O$954,1,Opps!$AD$5:$AD$954,0) -> 8 | G7: =IF(E7=0,"",1-F7/E7) -> 0.63636364 | H7: =SUMIFS(Opps!$AC$5:$AC$954,Opps!$K$5:$K$954,A7,Opps!$O$5:$O$954,1) -> 8
A8: =Owners!A8 -> U004 | B8: =Owners!B8 -> Daniel Wanjiru | C8: =Owners!C8 -> Partner | D8: =Owners!E8 -> Yes | E8: =COUNTIFS(Opps!$K$5:$K$954,A8,Opps!$O$5:$O$954,1) -> 21 | F8: =COUNTIFS(Opps!$K$5:$K$954,A8,Opps!$O$5:$O$954,1,Opps!$AD$5:$AD$954,0) -> 10 | G8: =IF(E8=0,"",1-F8/E8) -> 0.52380952 | H8: =SUMIFS(Opps!$AC$5:$AC$954,Opps!$K$5:$K$954,A8,Opps!$O$5:$O$954,1) -> 11
A9: =Owners!A9 -> U005 | B9: =Owners!B9 -> Esther Kiprop | C9: =Owners!C9 -> Partner | D9: =Owners!E9 -> Yes | E9: =COUNTIFS(Opps!$K$5:$K$954,A9,Opps!$O$5:$O$954,1) -> 21 | F9: =COUNTIFS(Opps!$K$5:$K$954,A9,Opps!$O$5:$O$954,1,Opps!$AD$5:$AD$954,0) -> 11 | G9: =IF(E9=0,"",1-F9/E9) -> 0.47619048 | H9: =SUMIFS(Opps!$AC$5:$AC$954,Opps!$K$5:$K$954,A9,Opps!$O$5:$O$954,1) -> 12
A10: =Owners!A10 -> U006 | B10: =Owners!B10 -> Felix Barasa | C10: =Owners!C10 -> Partner | D10: =Owners!E10 -> Yes | E10: =COUNTIFS(Opps!$K$5:$K$954,A10,Opps!$O$5:$O$954,1) -> 16 | F10: =COUNTIFS(Opps!$K$5:$K$954,A10,Opps!$O$5:$O$954,1,Opps!$AD$5:$AD$954,0) -> 9 | G10: =IF(E10=0,"",1-F10/E10) -> 0.4375 | H10: =SUMIFS(Opps!$AC$5:$AC$954,Opps!$K$5:$K$954,A10,Opps!$O$5:$O$954,1) -> 13
A11: =Owners!A11 -> U007 | B11: =Owners!B11 -> Grace Mwangi | C11: =Owners!C11 -> Partner | D11: =Owners!E11 -> Yes | E11: =COUNTIFS(Opps!$K$5:$K$954,A11,Opps!$O$5:$O$954,1) -> 16 | F11: =COUNTIFS(Opps!$K$5:$K$954,A11,Opps!$O$5:$O$954,1,Opps!$AD$5:$AD$954,0) -> 10 | G11: =IF(E11=0,"",1-F11/E11) -> 0.375 | H11: =SUMIFS(Opps!$AC$5:$AC$954,Opps!$K$5:$K$954,A11,Opps!$O$5:$O$954,1) -> 14
A12: =Owners!A12 -> U008 | B12: =Owners!B12 -> Hassan Mutua | C12: =Owners!C12 -> Director | D12: =Owners!E12 -> Yes | E12: =COUNTIFS(Opps!$K$5:$K$954,A12,Opps!$O$5:$O$954,1) -> 13 | F12: =COUNTIFS(Opps!$K$5:$K$954,A12,Opps!$O$5:$O$954,1,Opps!$AD$5:$AD$954,0) -> 2 | G12: =IF(E12=0,"",1-F12/E12) -> 0.84615385 | H12: =SUMIFS(Opps!$AC$5:$AC$954,Opps!$K$5:$K$954,A12,Opps!$O$5:$O$954,1) -> 4
A13: =Owners!A13 -> U009 | B13: =Owners!B13 -> Irene Nyambura | C13: =Owners!C13 -> Director | D13: =Owners!E13 -> Yes | E13: =COUNTIFS(Opps!$K$5:$K$954,A13,Opps!$O$5:$O$954,1) -> 11 | F13: =COUNTIFS(Opps!$K$5:$K$954,A13,Opps!$O$5:$O$954,1,Opps!$AD$5:$AD$954,0) -> 4 | G13: =IF(E13=0,"",1-F13/E13) -> 0.63636364 | H13: =SUMIFS(Opps!$AC$5:$AC$954,Opps!$K$5:$K$954,A13,Opps!$O$5:$O$954,1) -> 8
A14: =Owners!A14 -> U010 | B14: =Owners!B14 -> James Kamau | C14: =Owners!C14 -> Director | D14: =Owners!E14 -> Yes | E14: =COUNTIFS(Opps!$K$5:$K$954,A14,Opps!$O$5:$O$954,1) -> 9 | F14: =COUNTIFS(Opps!$K$5:$K$954,A14,Opps!$O$5:$O$954,1,Opps!$AD$5:$AD$954,0) -> 6 | G14: =IF(E14=0,"",1-F14/E14) -> 0.33333333 | H14: =SUMIFS(Opps!$AC$5:$AC$954,Opps!$K$5:$K$954,A14,Opps!$O$5:$O$954,1) -> 8
A15: =Owners!A15 -> U011 | B15: =Owners!B15 -> Kevin Ochieng | C15: =Owners!C15 -> Director | D15: =Owners!E15 -> Yes | E15: =COUNTIFS(Opps!$K$5:$K$954,A15,Opps!$O$5:$O$954,1) -> 9 | F15: =COUNTIFS(Opps!$K$5:$K$954,A15,Opps!$O$5:$O$954,1,Opps!$AD$5:$AD$954,0) -> 6 | G15: =IF(E15=0,"",1-F15/E15) -> 0.33333333 | H15: =SUMIFS(Opps!$AC$5:$AC$954,Opps!$K$5:$K$954,A15,Opps!$O$5:$O$954,1) -> 7
A16: =Owners!A16 -> U012 | B16: =Owners!B16 -> Lucy Kariuki | C16: =Owners!C16 -> Director | D16: =Owners!E16 -> No | E16: =COUNTIFS(Opps!$K$5:$K$954,A16,Opps!$O$5:$O$954,1) -> 24 | F16: =COUNTIFS(Opps!$K$5:$K$954,A16,Opps!$O$5:$O$954,1,Opps!$AD$5:$AD$954,0) -> 24 | G16: =IF(E16=0,"",1-F16/E16) -> 0 | H16: =SUMIFS(Opps!$AC$5:$AC$954,Opps!$K$5:$K$954,A16,Opps!$O$5:$O$954,1) -> 32
... A32: =Owners!A32 -> U028 | B32: =Owners!B32 -> Faith Mutua | C32: =Owners!C32 -> Senior Manager | D32: =Owners!E32 -> Yes | E32: =COUNTIFS(Opps!$K$5:$K$954,A32,Opps!$O$5:$O$954,1) -> 9 | F32: =COUNTIFS(Opps!$K$5:$K$954,A32,Opps!$O$5:$O$954,1,Opps!$AD$5:$AD$954,0) -> 2 | G32: =IF(E32=0,"",1-F32/E32) -> 0.77777778 | H32: =SUMIFS(Opps!$AC$5:$AC$954,Opps!$K$5:$K$954,A32,Opps!$O$5:$O$954,1) -> 2
B33: (no owner) | E33: =COUNTIFS(Opps!$K$5:$K$954,"",Opps!$O$5:$O$954,1) -> 10 | F33: =COUNTIFS(Opps!$K$5:$K$954,"",Opps!$O$5:$O$954,1,Opps!$AD$5:$AD$954,0) -> 10 | H33: =SUMIFS(Opps!$AC$5:$AC$954,Opps!$K$5:$K$954,"",Opps!$O$5:$O$954,1) -> 20
B34: Total | E34: =SUM(E5:E33) -> 373 | F34: =SUM(F5:F33) -> 205 | H34: =SUM(H5:H33) -> 271

Sheet Feedback
A1: Client feedback consolidation (simulated survey)
A2: Theme tags come from keyword matching in Python [E]. Summary tables are live formulas.
A4: Feedback ID | B4: Account ID | C4: Line of service | D4: Survey date | E4: Rating (1-5) | F4: Comment | G4: Follow-up status | H4: Theme [E] | I4: Sentiment | L4: Line of service | M4: Responses | N4: Average rating | O4: % positive | P4: % negative
A5: F0001 | B5: A0307 | C5: Deals | D5: 46287 | E5: 5 | F5: Quick to respond and always available when we need guidance. | G5: Closed | H5: responsiveness | I5: =IF(E5>=4,"Positive",IF(E5<=2,"Negative","Neutral")) -> Positive | L5: Assurance | M5: =COUNTIFS($C$5:$C$184,L5) -> 42 | N5: =AVERAGEIFS($E$5:$E$184,$C$5:$C$184,L5) -> 3.4047619 | O5: =COUNTIFS($C$5:$C$184,L5,$I$5:$I$184,"Positive")/M5 -> 0.47619048 | P5: =COUNTIFS($C$5:$C$184,L5,$I$5:$I$184,"Negative")/M5 -> 0.21428571
A6: F0002 | B6: A0294 | C6: Consulting | D6: 46281 | E6: 5 | F6: Quick to respond and always available when we need guidance. | G6: Responded | H6: responsiveness | I6: =IF(E6>=4,"Positive",IF(E6<=2,"Negative","Neutral")) -> Positive | L6: Tax & Legal | M6: =COUNTIFS($C$5:$C$184,L6) -> 42 | N6: =AVERAGEIFS($E$5:$E$184,$C$5:$C$184,L6) -> 3.6666667 | O6: =COUNTIFS($C$5:$C$184,L6,$I$5:$I$184,"Positive")/M6 -> 0.64285714 | P6: =COUNTIFS($C$5:$C$184,L6,$I$5:$I$184,"Negative")/M6 -> 0.16666667
A7: F0003 | B7: A0028 | C7: Assurance | D7: 46045 | E7: 5 | F7: The client portal made sharing documents simple. | G7: Closed | H7: digital | I7: =IF(E7>=4,"Positive",IF(E7<=2,"Negative","Neutral")) -> Positive | L7: Deals | M7: =COUNTIFS($C$5:$C$184,L7) -> 27 | N7: =AVERAGEIFS($E$5:$E$184,$C$5:$C$184,L7) -> 3.7407407 | O7: =COUNTIFS($C$5:$C$184,L7,$I$5:$I$184,"Positive")/M7 -> 0.66666667 | P7: =COUNTIFS($C$5:$C$184,L7,$I$5:$I$184,"Negative")/M7 -> 0.14814815
A8: F0004 | B8: A0037 | C8: Consulting | D8: 45995 | E8: 1 | F8: We were not told about changes to the timeline early enough. | G8: Closed | H8: communication | I8: =IF(E8>=4,"Positive",IF(E8<=2,"Negative","Neutral")) -> Negative | L8: Consulting | M8: =COUNTIFS($C$5:$C$184,L8) -> 52 | N8: =AVERAGEIFS($E$5:$E$184,$C$5:$C$184,L8) -> 3.8076923 | O8: =COUNTIFS($C$5:$C$184,L8,$I$5:$I$184,"Positive")/M8 -> 0.71153846 | P8: =COUNTIFS($C$5:$C$184,L8,$I$5:$I$184,"Negative")/M8 -> 0.17307692
A9: F0005 | B9: A0167 | C9: Deals | D9: 46306 | E9: 3 | F9: Updates were clear and regular. | G9: Responded | H9: communication | I9: =IF(E9>=4,"Positive",IF(E9<=2,"Negative","Neutral")) -> Neutral | L9: Risk | M9: =COUNTIFS($C$5:$C$184,L9) -> 17 | N9: =AVERAGEIFS($E$5:$E$184,$C$5:$C$184,L9) -> 3.4705882 | O9: =COUNTIFS($C$5:$C$184,L9,$I$5:$I$184,"Positive")/M9 -> 0.58823529 | P9: =COUNTIFS($C$5:$C$184,L9,$I$5:$I$184,"Negative")/M9 -> 0.29411765
A10: F0006 | B10: A0035 | C10: Tax & Legal | D10: 46164 | E10: 3 | F10: Advice felt generic and not tailored to our industry. | G10: Closed | H10: insight | I10: =IF(E10>=4,"Positive",IF(E10<=2,"Negative","Neutral")) -> Neutral
A11: F0007 | B11: A0108 | C11: Tax & Legal | D11: 46197 | E11: 5 | F11: The client portal made sharing documents simple. | G11: Closed | H11: digital | I11: =IF(E11>=4,"Positive",IF(E11<=2,"Negative","Neutral")) -> Positive | L11: All | M11: =COUNTA($A$5:$A$184) -> 180 | N11: =AVERAGE($E$5:$E$184) -> 3.6388889 | O11: =COUNTIF($I$5:$I$184,"Positive")/M11 -> 0.62222222 | P11: =COUNTIF($I$5:$I$184,"Negative")/M11 -> 0.18888889
A12: F0008 | B12: A0216 | C12: Consulting | D12: 46269 | E12: 5 | F12: Event invitations are relevant to our work. | G12: Open | H12: digital | I12: =IF(E12>=4,"Positive",IF(E12<=2,"Negative","Neutral")) -> Positive | L12: Net sentiment (points, % positive - % negative) | P12: =(O11-P11)*100 -> 43.333333
A13: F0009 | B13: A0229 | C13: Assurance | D13: 46091 | E13: 4 | F13: Updates were clear and regular. | G13: Open | H13: communication | I13: =IF(E13>=4,"Positive",IF(E13<=2,"Negative","Neutral")) -> Positive | L13: Open follow-ups | P13: =COUNTIF($G$5:$G$184,"Open") -> 50
A14: F0010 | B14: A0085 | C14: Assurance | D14: 46017 | E14: 2 | F14: Pricing was higher than we expected for the scope. | G14: Closed | H14: value | I14: =IF(E14>=4,"Positive",IF(E14<=2,"Negative","Neutral")) -> Negative
A15: F0011 | B15: A0014 | C15: Assurance | D15: 46016 | E15: 4 | F15: The team brought genuinely useful sector insight. | G15: Open | H15: insight | I15: =IF(E15>=4,"Positive",IF(E15<=2,"Negative","Neutral")) -> Positive
A16: F0012 | B16: A0164 | C16: Tax & Legal | D16: 46132 | E16: 2 | F16: Too many separate emails from different teams. | G16: Responded | H16: digital | I16: =IF(E16>=4,"Positive",IF(E16<=2,"Negative","Neutral")) -> Negative | L16: Theme | M16: Positive | N16: Neutral | O16: Negative | P16: Total
A17: F0013 | B17: A0297 | C17: Risk | D17: 46183 | E17: 4 | F17: Updates were clear and regular. | G17: Open | H17: communication | I17: =IF(E17>=4,"Positive",IF(E17<=2,"Negative","Neutral")) -> Positive | L17: responsiveness | M17: =COUNTIFS($H$5:$H$184,L17,$I$5:$I$184,"Positive") -> 18 | N17: =COUNTIFS($H$5:$H$184,L17,$I$5:$I$184,"Neutral") -> 3 | O17: =COUNTIFS($H$5:$H$184,L17,$I$5:$I$184,"Negative") -> 4 | P17: =SUM(M17:O17) -> 25
A18: F0014 | B18: A0295 | C18: Tax & Legal | D18: 46251 | E18: 2 | F18: Pricing was higher than we expected for the scope. | G18: Responded | H18: value | I18: =IF(E18>=4,"Positive",IF(E18<=2,"Negative","Neutral")) -> Negative | L18: insight | M18: =COUNTIFS($H$5:$H$184,L18,$I$5:$I$184,"Positive") -> 22 | N18: =COUNTIFS($H$5:$H$184,L18,$I$5:$I$184,"Neutral") -> 10 | O18: =COUNTIFS($H$5:$H$184,L18,$I$5:$I$184,"Negative") -> 5 | P18: =SUM(M18:O18) -> 37
A19: F0015 | B19: A0119 | C19: Tax & Legal | D19: 45987 | E19: 4 | F19: Event invitations are relevant to our work. | G19: Open | H19: digital | I19: =IF(E19>=4,"Positive",IF(E19<=2,"Negative","Neutral")) -> Positive | L19: value | M19: =COUNTIFS($H$5:$H$184,L19,$I$5:$I$184,"Positive") -> 24 | N19: =COUNTIFS($H$5:$H$184,L19,$I$5:$I$184,"Neutral") -> 4 | O19: =COUNTIFS($H$5:$H$184,L19,$I$5:$I$184,"Negative") -> 6 | P19: =SUM(M19:O19) -> 34
A20: F0016 | B20: A0297 | C20: Assurance | D20: 46056 | E20: 4 | F20: Fees were fair for the quality delivered. | G20: Responded | H20: value | I20: =IF(E20>=4,"Positive",IF(E20<=2,"Negative","Neutral")) -> Positive | L20: communication | M20: =COUNTIFS($H$5:$H$184,L20,$I$5:$I$184,"Positive") -> 23 | N20: =COUNTIFS($H$5:$H$184,L20,$I$5:$I$184,"Neutral") -> 11 | O20: =COUNTIFS($H$5:$H$184,L20,$I$5:$I$184,"Negative") -> 12 | P20: =SUM(M20:O20) -> 46
A21: F0017 | B21: A0130 | C21: Deals | D21: 46164 | E21: 5 | F21: The client portal made sharing documents simple. | G21: Responded | H21: digital | I21: =IF(E21>=4,"Positive",IF(E21<=2,"Negative","Neutral")) -> Positive | L21: digital | M21: =COUNTIFS($H$5:$H$184,L21,$I$5:$I$184,"Positive") -> 25 | N21: =COUNTIFS($H$5:$H$184,L21,$I$5:$I$184,"Neutral") -> 6 | O21: =COUNTIFS($H$5:$H$184,L21,$I$5:$I$184,"Negative") -> 7 | P21: =SUM(M21:O21) -> 38
A22: F0018 | B22: A0268 | C22: Assurance | D22: 46023 | E22: 2 | F22: Pricing was higher than we expected for the scope. | G22: Open | H22: value | I22: =IF(E22>=4,"Positive",IF(E22<=2,"Negative","Neutral")) -> Negative
A23: F0019 | B23: A0208 | C23: Tax & Legal | D23: 46042 | E23: 3 | F23: Quick to respond and always available when we need guidance. | G23: Responded | H23: responsiveness | I23: =IF(E23>=4,"Positive",IF(E23<=2,"Negative","Neutral")) -> Neutral
A24: F0020 | B24: A0092 | C24: Assurance | D24: 46146 | E24: 5 | F24: The client portal made sharing documents simple. | G24: Responded | H24: digital | I24: =IF(E24>=4,"Positive",IF(E24<=2,"Negative","Neutral")) -> Positive
A25: F0021 | B25: A0045 | C25: Tax & Legal | D25: 46164 | E25: 4 | F25: The team brought genuinely useful sector insight. | G25: Open | H25: insight | I25: =IF(E25>=4,"Positive",IF(E25<=2,"Negative","Neutral")) -> Positive
A26: F0022 | B26: A0220 | C26: Assurance | D26: 46246 | E26: 4 | F26: Clear scoping avoided surprises on cost. | G26: Open | H26: value | I26: =IF(E26>=4,"Positive",IF(E26<=2,"Negative","Neutral")) -> Positive
A27: F0023 | B27: A0277 | C27: Assurance | D27: 46296 | E27: 4 | F27: Event invitations are relevant to our work. | G27: Responded | H27: digital | I27: =IF(E27>=4,"Positive",IF(E27<=2,"Negative","Neutral")) -> Positive
A28: F0024 | B28: A0273 | C28: Assurance | D28: 46042 | E28: 4 | F28: The client portal made sharing documents simple. | G28: Responded | H28: digital | I28: =IF(E28>=4,"Positive",IF(E28<=2,"Negative","Neutral")) -> Positive
A29: F0025 | B29: A0226 | C29: Consulting | D29: 46171 | E29: 3 | F29: One point of contact made everything easier. | G29: Responded | H29: communication | I29: =IF(E29>=4,"Positive",IF(E29<=2,"Negative","Neutral")) -> Neutral
A30: F0026 | B30: A0129 | C30: Risk | D30: 46207 | E30: 2 | F30: Advice felt generic and not tailored to our industry. | G30: Open | H30: insight | I30: =IF(E30>=4,"Positive",IF(E30<=2,"Negative","Neutral")) -> Negative
A31: F0027 | B31: A0244 | C31: Consulting | D31: 46306 | E31: 4 | F31: The team brought genuinely useful sector insight. | G31: Closed | H31: insight | I31: =IF(E31>=4,"Positive",IF(E31<=2,"Negative","Neutral")) -> Positive
A32: F0028 | B32: A0061 | C32: Assurance | D32: 46309 | E32: 3 | F32: We were not told about changes to the timeline early enough. | G32: Open | H32: communication | I32: =IF(E32>=4,"Positive",IF(E32<=2,"Negative","Neutral")) -> Neutral
A33: F0029 | B33: A0162 | C33: Deals | D33: 46132 | E33: 4 | F33: Updates were clear and regular. | G33: Open | H33: communication | I33: =IF(E33>=4,"Positive",IF(E33<=2,"Negative","Neutral")) -> Positive
... A184: F0180 | B184: A0164 | C184: Consulting | D184: 46219 | E184: 5 | F184: Fees were fair for the quality delivered. | G184: Responded | H184: value | I184: =IF(E184>=4,"Positive",IF(E184<=2,"Negative","Neutral")) -> Positive

Sheet Events
A1: Event support: funnel by event (simulated)
A2: Invited to registered to attended to opportunities created.
A4: Event | B4: Industry | C4: Date | D4: Invited | E4: Registered | F4: Attended | G4: Opps created | H4: Registration rate | I4: Attendance rate | J4: Opps per 10 attendees
A5: Banking & Fintech Roundtable | B5: Financial Services | C5: 46226 | D5: 120 | E5: 64 | F5: 47 | G5: 6 | H5: =IF(D5=0,"",E5/D5) -> 0.53333333 | I5: =IF(E5=0,"",F5/E5) -> 0.734375 | J5: =IF(F5=0,"",G5/F5*10) -> 1.2765957
A6: Budget Breakfast: Tax Changes Briefing | B6: All industries | C6: 46240 | D6: 260 | E6: 148 | F6: 109 | G6: 11 | H6: =IF(D6=0,"",E6/D6) -> 0.56923077 | I6: =IF(E6=0,"",F6/E6) -> 0.73648649 | J6: =IF(F6=0,"",G6/F6*10) -> 1.0091743
A7: Energy Transition Forum | B7: Energy & Resources | C7: 46275 | D7: 90 | E7: 51 | F7: 38 | G7: 4 | H7: =IF(D7=0,"",E7/D7) -> 0.56666667 | I7: =IF(E7=0,"",F7/E7) -> 0.74509804 | J7: =IF(F7=0,"",G7/F7*10) -> 1.0526316
A8: Public Sector Finance Clinic | B8: Public Sector & Development | C8: 46289 | D8: 80 | E8: 42 | F8: 33 | G8: 3 | H8: =IF(D8=0,"",E8/D8) -> 0.525 | I8: =IF(E8=0,"",F8/E8) -> 0.78571429 | J8: =IF(F8=0,"",G8/F8*10) -> 0.90909091
A9: Health Leaders Dinner | B9: Health | C9: 46303 | D9: 40 | E9: 27 | F9: 22 | G9: 3 | H9: =IF(D9=0,"",E9/D9) -> 0.675 | I9: =IF(E9=0,"",F9/E9) -> 0.81481481 | J9: =IF(F9=0,"",G9/F9*10) -> 1.3636364
A10: Annual Industry Conference (planned) | B10: All industries | C10: 46345 | D10: 400 | E10: 0 | F10: 0 | G10: 0 | H10: =IF(D10=0,"",E10/D10) -> 0 | I10: =IF(E10=0,"",F10/E10) | J10: =IF(F10=0,"",G10/F10*10)
A11: Held events (excl. planned) | D11: =SUM(D5:D9) -> 590 | E11: =SUM(E5:E9) -> 332 | F11: =SUM(F5:F9) -> 249 | G11: =SUM(G5:G9) -> 27 | H11: =E11/D11 -> 0.56271186 | I11: =F11/E11 -> 0.75 | J11: =G11/F11*10 -> 1.0843373
A13: The last row is the planned annual conference: see comms/event_pack.md for the run-of-show, checklist and success measures.

Sheet Inputs
A1: Inputs
A2: Blue = input. All dashboards read these cells. Data is SIMULATED (see README).
A4: As-of date | B4: 46314
A5: Stale threshold (days without activity) | B5: 60
A6: FY27 start | B6: 46204
A7: FY27 end | B7: 46568
A8: Look-back for win rate (days) | B8: 365
A10: Stage | B10: Default probability %
A11: Prospecting | B11: 10
A12: Qualification | B12: 25
A13: Proposal | B13: 50
A14: Negotiation | B14: 75
A15: Closed Won | B15: 100
A16: Closed Lost | B16: 0
A19: Line of service | B19: FY27 BD target (KES m) [simulated]
A20: Assurance | B20: 1100
A21: Tax & Legal | B21: 1500
A22: Deals | B22: 900
A23: Consulting | B23: 1900
A24: Risk | B24: 600
A26: Targets are simulated planning inputs, not real firm targets.

Sheet Opps
A1: Opportunities: raw export plus live data-quality flags
A2: Columns A-N are the simulated Salesforce export. Columns O onward are formulas.
A4: Opp ID | B4: Account ID | C4: Opportunity | D4: Line of service | E4: Stage | F4: Amount (KES) | G4: Probability % | H4: Created | I4: Close date | J4: Last activity | K4: Owner ID | L4: Lead source | M4: Next step | N4: Lost reason | O4: Open? | P4: Industry | Q4: Tier | R4: Stage probability % | S4: Weighted (KES) | T4: Days since activity | U4: Flag: no amount | V4: Flag: no owner | W4: Flag: owner left | X4: Flag: close date passed | Y4: Flag: stale | Z4: Flag: probability off | AA4: Flag: no next step | AB4: Flag: lost no reason | AC4: Flags | AD4: Clean? | AE4: Closes in FY27 (open) | AF4: Won FY27 YTD | AG4: Closed in look-back | AH4: Cycle days
A5: O00001 | B5: A0002 | C5: Umoja Capital | Assurance | transformation | D5: Assurance | E5: Qualification | F5: 5676000 | G5: 25 | H5: 46199 | I5: 46522 | J5: 46293 | K5: U017 | L5: Cold outreach | M5: Await tender outcome | O5: =IF(OR(E5="Closed Won",E5="Closed Lost"),0,1) -> 1 | P5: =INDEX(Accounts!$K$5:$K$336,MATCH(B5,Accounts!$A$5:$A$336,0)) -> Financial Services | Q5: =INDEX(Accounts!$D$5:$D$336,MATCH(B5,Accounts!$A$5:$A$336,0)) -> Priority | R5: =INDEX(Inputs!$B$11:$B$16,MATCH(E5,Inputs!$A$11:$A$16,0)) -> 25 | S5: =IF(F5="",0,F5)*R5/100 -> 1419000 | T5: =Inputs!$B$4-J5 -> 21 | U5: =IF(OR(F5="",F5=0),1,0) -> 0 | V5: =IF(K5="",1,0) -> 0 | W5: =IF(AND(O5=1,K5<>"",COUNTIFS(Owners!$A$5:$A$32,K5,Owners!$E$5:$E$32,"No")>0),1,0) -> 0 | X5: =IF(AND(O5=1,I5<Inputs!$B$4),1,0) -> 0 | Y5: =IF(AND(O5=1,T5>Inputs!$B$5),1,0) -> 0 | Z5: =IF(AND(O5=1,G5<>R5),1,0) -> 0 | AA5: =IF(AND(O5=1,M5=""),1,0) -> 0 | AB5: =IF(AND(E5="Closed Lost",N5=""),1,0) -> 0 | AC5: =SUM(U5:AB5) -> 0 | AD5: =IF(AC5=0,1,0) -> 1 | AE5: =IF(AND(O5=1,I5>=Inputs!$B$6,I5<=Inputs!$B$7),1,0) -> 1 | AF5: =IF(AND(E5="Closed Won",I5>=Inputs!$B$6,I5<=Inputs!$B$4),1,0) -> 0 | AG5: =IF(AND(O5=0,I5>Inputs!$B$4-Inputs!$B$8,I5<=Inputs!$B$4),1,0) -> 0 | AH5: =I5-H5 -> 323
A6: O00002 | B6: A0102 | C6: Pwani Capital | Assurance | transformation | D6: Assurance | E6: Qualification | F6: 12441000 | G6: 25 | H6: 46179 | I6: 46557 | J6: 46298 | K6: U026 | L6: Digital | M6: Follow-up call | O6: =IF(OR(E6="Closed Won",E6="Closed Lost"),0,1) -> 1 | P6: =INDEX(Accounts!$K$5:$K$336,MATCH(B6,Accounts!$A$5:$A$336,0)) -> Financial Services | Q6: =INDEX(Accounts!$D$5:$D$336,MATCH(B6,Accounts!$A$5:$A$336,0)) -> Key | R6: =INDEX(Inputs!$B$11:$B$16,MATCH(E6,Inputs!$A$11:$A$16,0)) -> 25 | S6: =IF(F6="",0,F6)*R6/100 -> 3110250 | T6: =Inputs!$B$4-J6 -> 16 | U6: =IF(OR(F6="",F6=0),1,0) -> 0 | V6: =IF(K6="",1,0) -> 0 | W6: =IF(AND(O6=1,K6<>"",COUNTIFS(Owners!$A$5:$A$32,K6,Owners!$E$5:$E$32,"No")>0),1,0) -> 0 | X6: =IF(AND(O6=1,I6<Inputs!$B$4),1,0) -> 0 | Y6: =IF(AND(O6=1,T6>Inputs!$B$5),1,0) -> 0 | Z6: =IF(AND(O6=1,G6<>R6),1,0) -> 0 | AA6: =IF(AND(O6=1,M6=""),1,0) -> 0 | AB6: =IF(AND(E6="Closed Lost",N6=""),1,0) -> 0 | AC6: =SUM(U6:AB6) -> 0 | AD6: =IF(AC6=0,1,0) -> 1 | AE6: =IF(AND(O6=1,I6>=Inputs!$B$6,I6<=Inputs!$B$7),1,0) -> 1 | AF6: =IF(AND(E6="Closed Won",I6>=Inputs!$B$6,I6<=Inputs!$B$4),1,0) -> 0 | AG6: =IF(AND(O6=0,I6>Inputs!$B$4-Inputs!$B$8,I6<=Inputs!$B$4),1,0) -> 0 | AH6: =I6-H6 -> 378
A7: O00003 | B7: A0039 | C7: Baobab Power | Consulting | readiness | D7: Consulting | E7: Closed Lost | F7: 133434000 | G7: 0 | H7: 45949 | I7: 46048 | J7: 46048 | K7: U021 | L7: Event | N7: No decision | O7: =IF(OR(E7="Closed Won",E7="Closed Lost"),0,1) -> 0 | P7: =INDEX(Accounts!$K$5:$K$336,MATCH(B7,Accounts!$A$5:$A$336,0)) -> Energy & Resources | Q7: =INDEX(Accounts!$D$5:$D$336,MATCH(B7,Accounts!$A$5:$A$336,0)) -> Priority | R7: =INDEX(Inputs!$B$11:$B$16,MATCH(E7,Inputs!$A$11:$A$16,0)) -> 0 | S7: =IF(F7="",0,F7)*R7/100 -> 0 | T7: =Inputs!$B$4-J7 -> 266 | U7: =IF(OR(F7="",F7=0),1,0) -> 0 | V7: =IF(K7="",1,0) -> 0 | W7: =IF(AND(O7=1,K7<>"",COUNTIFS(Owners!$A$5:$A$32,K7,Owners!$E$5:$E$32,"No")>0),1,0) -> 0 | X7: =IF(AND(O7=1,I7<Inputs!$B$4),1,0) -> 0 | Y7: =IF(AND(O7=1,T7>Inputs!$B$5),1,0) -> 0 | Z7: =IF(AND(O7=1,G7<>R7),1,0) -> 0 | AA7: =IF(AND(O7=1,M7=""),1,0) -> 0 | AB7: =IF(AND(E7="Closed Lost",N7=""),1,0) -> 0 | AC7: =SUM(U7:AB7) -> 0 | AD7: =IF(AC7=0,1,0) -> 1 | AE7: =IF(AND(O7=1,I7>=Inputs!$B$6,I7<=Inputs!$B$7),1,0) -> 0 | AF7: =IF(AND(E7="Closed Won",I7>=Inputs!$B$6,I7<=Inputs!$B$4),1,0) -> 0 | AG7: =IF(AND(O7=0,I7>Inputs!$B$4-Inputs!$B$8,I7<=Inputs!$B$4),1,0) -> 1 | AH7: =I7-H7 -> 99
A8: O00004 | B8: A0152 | C8: Lakeview Sacco | Deals | transformation | D8: Deals | E8: Closed Won | F8: 18415000 | G8: 100 | H8: 45923 | I8: 46004 | J8: 46004 | K8: U024 | L8: Existing client | O8: =IF(OR(E8="Closed Won",E8="Closed Lost"),0,1) -> 0 | P8: =INDEX(Accounts!$K$5:$K$336,MATCH(B8,Accounts!$A$5:$A$336,0)) -> Financial Services | Q8: =INDEX(Accounts!$D$5:$D$336,MATCH(B8,Accounts!$A$5:$A$336,0)) -> Standard | R8: =INDEX(Inputs!$B$11:$B$16,MATCH(E8,Inputs!$A$11:$A$16,0)) -> 100 | S8: =IF(F8="",0,F8)*R8/100 -> 18415000 | T8: =Inputs!$B$4-J8 -> 310 | U8: =IF(OR(F8="",F8=0),1,0) -> 0 | V8: =IF(K8="",1,0) -> 0 | W8: =IF(AND(O8=1,K8<>"",COUNTIFS(Owners!$A$5:$A$32,K8,Owners!$E$5:$E$32,"No")>0),1,0) -> 0 | X8: =IF(AND(O8=1,I8<Inputs!$B$4),1,0) -> 0 | Y8: =IF(AND(O8=1,T8>Inputs!$B$5),1,0) -> 0 | Z8: =IF(AND(O8=1,G8<>R8),1,0) -> 0 | AA8: =IF(AND(O8=1,M8=""),1,0) -> 0 | AB8: =IF(AND(E8="Closed Lost",N8=""),1,0) -> 0 | AC8: =SUM(U8:AB8) -> 0 | AD8: =IF(AC8=0,1,0) -> 1 | AE8: =IF(AND(O8=1,I8>=Inputs!$B$6,I8<=Inputs!$B$7),1,0) -> 0 | AF8: =IF(AND(E8="Closed Won",I8>=Inputs!$B$6,I8<=Inputs!$B$4),1,0) -> 0 | AG8: =IF(AND(O8=0,I8>Inputs!$B$4-Inputs!$B$8,I8<=Inputs!$B$4),1,0) -> 1 | AH8: =I8-H8 -> 81
A9: O00005 | B9: A0137 | C9: Amani Networks | Tax & Legal | review | D9: Tax & Legal | E9: Qualification | F9: 17645000 | G9: 25 | H9: 46304 | I9: 46560 | J9: 46289 | K9: U025 | L9: Existing client | M9: Await tender outcome | O9: =IF(OR(E9="Closed Won",E9="Closed Lost"),0,1) -> 1 | P9: =INDEX(Accounts!$K$5:$K$336,MATCH(B9,Accounts!$A$5:$A$336,0)) -> Technology, Media & Telecom | Q9: =INDEX(Accounts!$D$5:$D$336,MATCH(B9,Accounts!$A$5:$A$336,0)) -> Standard | R9: =INDEX(Inputs!$B$11:$B$16,MATCH(E9,Inputs!$A$11:$A$16,0)) -> 25 | S9: =IF(F9="",0,F9)*R9/100 -> 4411250 | T9: =Inputs!$B$4-J9 -> 25 | U9: =IF(OR(F9="",F9=0),1,0) -> 0 | V9: =IF(K9="",1,0) -> 0 | W9: =IF(AND(O9=1,K9<>"",COUNTIFS(Owners!$A$5:$A$32,K9,Owners!$E$5:$E$32,"No")>0),1,0) -> 0 | X9: =IF(AND(O9=1,I9<Inputs!$B$4),1,0) -> 0 | Y9: =IF(AND(O9=1,T9>Inputs!$B$5),1,0) -> 0 | Z9: =IF(AND(O9=1,G9<>R9),1,0) -> 0 | AA9: =IF(AND(O9=1,M9=""),1,0) -> 0 | AB9: =IF(AND(E9="Closed Lost",N9=""),1,0) -> 0 | AC9: =SUM(U9:AB9) -> 0 | AD9: =IF(AC9=0,1,0) -> 1 | AE9: =IF(AND(O9=1,I9>=Inputs!$B$6,I9<=Inputs!$B$7),1,0) -> 1 | AF9: =IF(AND(E9="Closed Won",I9>=Inputs!$B$6,I9<=Inputs!$B$4),1,0) -> 0 | AG9: =IF(AND(O9=0,I9>Inputs!$B$4-Inputs!$B$8,I9<=Inputs!$B$4),1,0) -> 0 | AH9: =I9-H9 -> 256
A10: O00006 | B10: A0176 | C10: Baobab Capital | Deals | annual | D10: Deals | E10: Qualification | F10: 198924000 | G10: 25 | H10: 46281 | I10: 46533 | J10: 46290 | K10: U014 | L10: Thought leadership | M10: Partner meeting | O10: =IF(OR(E10="Closed Won",E10="Closed Lost"),0,1) -> 1 | P10: =INDEX(Accounts!$K$5:$K$336,MATCH(B10,Accounts!$A$5:$A$336,0)) -> Financial Services | Q10: =INDEX(Accounts!$D$5:$D$336,MATCH(B10,Accounts!$A$5:$A$336,0)) -> Standard | R10: =INDEX(Inputs!$B$11:$B$16,MATCH(E10,Inputs!$A$11:$A$16,0)) -> 25 | S10: =IF(F10="",0,F10)*R10/100 -> 49731000 | T10: =Inputs!$B$4-J10 -> 24 | U10: =IF(OR(F10="",F10=0),1,0) -> 0 | V10: =IF(K10="",1,0) -> 0 | W10: =IF(AND(O10=1,K10<>"",COUNTIFS(Owners!$A$5:$A$32,K10,Owners!$E$5:$E$32,"No")>0),1,0) -> 0 | X10: =IF(AND(O10=1,I10<Inputs!$B$4),1,0) -> 0 | Y10: =IF(AND(O10=1,T10>Inputs!$B$5),1,0) -> 0 | Z10: =IF(AND(O10=1,G10<>R10),1,0) -> 0 | AA10: =IF(AND(O10=1,M10=""),1,0) -> 0 | AB10: =IF(AND(E10="Closed Lost",N10=""),1,0) -> 0 | AC10: =SUM(U10:AB10) -> 0 | AD10: =IF(AC10=0,1,0) -> 1 | AE10: =IF(AND(O10=1,I10>=Inputs!$B$6,I10<=Inputs!$B$7),1,0) -> 1 | AF10: =IF(AND(E10="Closed Won",I10>=Inputs!$B$6,I10<=Inputs!$B$4),1,0) -> 0 | AG10: =IF(AND(O10=0,I10>Inputs!$B$4-Inputs!$B$8,I10<=Inputs!$B$4),1,0) -> 0 | AH10: =I10-H10 -> 252
A11: O00007 | B11: A0016 | C11: Mara Foods | Assurance | review | D11: Assurance | E11: Closed Lost | F11: 4008000 | G11: 0 | H11: 45896 | I11: 46156 | J11: 46156 | K11: U004 | L11: Event | N11: Price | O11: =IF(OR(E11="Closed Won",E11="Closed Lost"),0,1) -> 0 | P11: =INDEX(Accounts!$K$5:$K$336,MATCH(B11,Accounts!$A$5:$A$336,0)) -> Consumer & Retail | Q11: =INDEX(Accounts!$D$5:$D$336,MATCH(B11,Accounts!$A$5:$A$336,0)) -> Priority | R11: =INDEX(Inputs!$B$11:$B$16,MATCH(E11,Inputs!$A$11:$A$16,0)) -> 0 | S11: =IF(F11="",0,F11)*R11/100 -> 0 | T11: =Inputs!$B$4-J11 -> 158 | U11: =IF(OR(F11="",F11=0),1,0) -> 0 | V11: =IF(K11="",1,0) -> 0 | W11: =IF(AND(O11=1,K11<>"",COUNTIFS(Owners!$A$5:$A$32,K11,Owners!$E$5:$E$32,"No")>0),1,0) -> 0 | X11: =IF(AND(O11=1,I11<Inputs!$B$4),1,0) -> 0 | Y11: =IF(AND(O11=1,T11>Inputs!$B$5),1,0) -> 0 | Z11: =IF(AND(O11=1,G11<>R11),1,0) -> 0 | AA11: =IF(AND(O11=1,M11=""),1,0) -> 0 | AB11: =IF(AND(E11="Closed Lost",N11=""),1,0) -> 0 | AC11: =SUM(U11:AB11) -> 0 | AD11: =IF(AC11=0,1,0) -> 1 | AE11: =IF(AND(O11=1,I11>=Inputs!$B$6,I11<=Inputs!$B$7),1,0) -> 0 | AF11: =IF(AND(E11="Closed Won",I11>=Inputs!$B$6,I11<=Inputs!$B$4),1,0) -> 0 | AG11: =IF(AND(O11=0,I11>Inputs!$B$4-Inputs!$B$8,I11<=Inputs!$B$4),1,0) -> 1 | AH11: =I11-H11 -> 260
A12: O00008 | B12: A0149 | C12: Savanna Construction | Consulting | due diligence | D12: Consulting | E12: Qualification | F12: 25200000 | G12: 25 | H12: 46292 | I12: 46532 | J12: 46312 | K12: U019 | L12: Existing client | M12: Send proposal | O12: =IF(OR(E12="Closed Won",E12="Closed Lost"),0,1) -> 1 | P12: =INDEX(Accounts!$K$5:$K$336,MATCH(B12,Accounts!$A$5:$A$336,0)) -> Real Estate & Infrastructure | Q12: =INDEX(Accounts!$D$5:$D$336,MATCH(B12,Accounts!$A$5:$A$336,0)) -> Standard | R12: =INDEX(Inputs!$B$11:$B$16,MATCH(E12,Inputs!$A$11:$A$16,0)) -> 25 | S12: =IF(F12="",0,F12)*R12/100 -> 6300000 | T12: =Inputs!$B$4-J12 -> 2 | U12: =IF(OR(F12="",F12=0),1,0) -> 0 | V12: =IF(K12="",1,0) -> 0 | W12: =IF(AND(O12=1,K12<>"",COUNTIFS(Owners!$A$5:$A$32,K12,Owners!$E$5:$E$32,"No")>0),1,0) -> 0 | X12: =IF(AND(O12=1,I12<Inputs!$B$4),1,0) -> 0 | Y12: =IF(AND(O12=1,T12>Inputs!$B$5),1,0) -> 0 | Z12: =IF(AND(O12=1,G12<>R12),1,0) -> 0 | AA12: =IF(AND(O12=1,M12=""),1,0) -> 0 | AB12: =IF(AND(E12="Closed Lost",N12=""),1,0) -> 0 | AC12: =SUM(U12:AB12) -> 0 | AD12: =IF(AC12=0,1,0) -> 1 | AE12: =IF(AND(O12=1,I12>=Inputs!$B$6,I12<=Inputs!$B$7),1,0) -> 1 | AF12: =IF(AND(E12="Closed Won",I12>=Inputs!$B$6,I12<=Inputs!$B$4),1,0) -> 0 | AG12: =IF(AND(O12=0,I12>Inputs!$B$4-Inputs!$B$8,I12<=Inputs!$B$4),1,0) -> 0 | AH12: =I12-H12 -> 240
A13: O00009 | B13: A0051 | C13: Kibo Sacco | Consulting | readiness | D13: Consulting | E13: Closed Lost | F13: 2821000 | G13: 0 | H13: 45932 | I13: 46223 | J13: 46223 | K13: U006 | L13: Existing client | N13: Price | O13: =IF(OR(E13="Closed Won",E13="Closed Lost"),0,1) -> 0 | P13: =INDEX(Accounts!$K$5:$K$336,MATCH(B13,Accounts!$A$5:$A$336,0)) -> Financial Services | Q13: =INDEX(Accounts!$D$5:$D$336,MATCH(B13,Accounts!$A$5:$A$336,0)) -> Key | R13: =INDEX(Inputs!$B$11:$B$16,MATCH(E13,Inputs!$A$11:$A$16,0)) -> 0 | S13: =IF(F13="",0,F13)*R13/100 -> 0 | T13: =Inputs!$B$4-J13 -> 91 | U13: =IF(OR(F13="",F13=0),1,0) -> 0 | V13: =IF(K13="",1,0) -> 0 | W13: =IF(AND(O13=1,K13<>"",COUNTIFS(Owners!$A$5:$A$32,K13,Owners!$E$5:$E$32,"No")>0),1,0) -> 0 | X13: =IF(AND(O13=1,I13<Inputs!$B$4),1,0) -> 0 | Y13: =IF(AND(O13=1,T13>Inputs!$B$5),1,0) -> 0 | Z13: =IF(AND(O13=1,G13<>R13),1,0) -> 0 | AA13: =IF(AND(O13=1,M13=""),1,0) -> 0 | AB13: =IF(AND(E13="Closed Lost",N13=""),1,0) -> 0 | AC13: =SUM(U13:AB13) -> 0 | AD13: =IF(AC13=0,1,0) -> 1 | AE13: =IF(AND(O13=1,I13>=Inputs!$B$6,I13<=Inputs!$B$7),1,0) -> 0 | AF13: =IF(AND(E13="Closed Won",I13>=Inputs!$B$6,I13<=Inputs!$B$4),1,0) -> 0 | AG13: =IF(AND(O13=0,I13>Inputs!$B$4-Inputs!$B$8,I13<=Inputs!$B$4),1,0) -> 1 | AH13: =I13-H13 -> 291
A14: O00010 | B14: A0032 | C14: Jambo Tea Estates | Risk | advisory | D14: Risk | E14: Qualification | F14: 6036000 | G14: 100 | H14: 46263 | I14: 46557 | J14: 46208 | K14: U004 | L14: Cold outreach | M14: Partner meeting | O14: =IF(OR(E14="Closed Won",E14="Closed Lost"),0,1) -> 1 | P14: =INDEX(Accounts!$K$5:$K$336,MATCH(B14,Accounts!$A$5:$A$336,0)) -> Agribusiness | Q14: =INDEX(Accounts!$D$5:$D$336,MATCH(B14,Accounts!$A$5:$A$336,0)) -> Priority | R14: =INDEX(Inputs!$B$11:$B$16,MATCH(E14,Inputs!$A$11:$A$16,0)) -> 25 | S14: =IF(F14="",0,F14)*R14/100 -> 1509000 | T14: =Inputs!$B$4-J14 -> 106 | U14: =IF(OR(F14="",F14=0),1,0) -> 0 | V14: =IF(K14="",1,0) -> 0 | W14: =IF(AND(O14=1,K14<>"",COUNTIFS(Owners!$A$5:$A$32,K14,Owners!$E$5:$E$32,"No")>0),1,0) -> 0 | X14: =IF(AND(O14=1,I14<Inputs!$B$4),1,0) -> 0 | Y14: =IF(AND(O14=1,T14>Inputs!$B$5),1,0) -> 1 | Z14: =IF(AND(O14=1,G14<>R14),1,0) -> 1 | AA14: =IF(AND(O14=1,M14=""),1,0) -> 0 | AB14: =IF(AND(E14="Closed Lost",N14=""),1,0) -> 0 | AC14: =SUM(U14:AB14) -> 2 | AD14: =IF(AC14=0,1,0) -> 0 | AE14: =IF(AND(O14=1,I14>=Inputs!$B$6,I14<=Inputs!$B$7),1,0) -> 1 | AF14: =IF(AND(E14="Closed Won",I14>=Inputs!$B$6,I14<=Inputs!$B$4),1,0) -> 0 | AG14: =IF(AND(O14=0,I14>Inputs!$B$4-Inputs!$B$8,I14<=Inputs!$B$4),1,0) -> 0 | AH14: =I14-H14 -> 294
A15: O00011 | B15: A0199 | C15: Amani Commission | Tax & Legal | due diligence | D15: Tax & Legal | E15: Closed Lost | F15: 4076000 | G15: 0 | H15: 46058 | I15: 46134 | J15: 46134 | K15: U006 | L15: Referral | N15: Incumbent retained | O15: =IF(OR(E15="Closed Won",E15="Closed Lost"),0,1) -> 0 | P15: =INDEX(Accounts!$K$5:$K$336,MATCH(B15,Accounts!$A$5:$A$336,0)) -> Public Sector & Development | Q15: =INDEX(Accounts!$D$5:$D$336,MATCH(B15,Accounts!$A$5:$A$336,0)) -> Standard | R15: =INDEX(Inputs!$B$11:$B$16,MATCH(E15,Inputs!$A$11:$A$16,0)) -> 0 | S15: =IF(F15="",0,F15)*R15/100 -> 0 | T15: =Inputs!$B$4-J15 -> 180 | U15: =IF(OR(F15="",F15=0),1,0) -> 0 | V15: =IF(K15="",1,0) -> 0 | W15: =IF(AND(O15=1,K15<>"",COUNTIFS(Owners!$A$5:$A$32,K15,Owners!$E$5:$E$32,"No")>0),1,0) -> 0 | X15: =IF(AND(O15=1,I15<Inputs!$B$4),1,0) -> 0 | Y15: =IF(AND(O15=1,T15>Inputs!$B$5),1,0) -> 0 | Z15: =IF(AND(O15=1,G15<>R15),1,0) -> 0 | AA15: =IF(AND(O15=1,M15=""),1,0) -> 0 | AB15: =IF(AND(E15="Closed Lost",N15=""),1,0) -> 0 | AC15: =SUM(U15:AB15) -> 0 | AD15: =IF(AC15=0,1,0) -> 1 | AE15: =IF(AND(O15=1,I15>=Inputs!$B$6,I15<=Inputs!$B$7),1,0) -> 0 | AF15: =IF(AND(E15="Closed Won",I15>=Inputs!$B$6,I15<=Inputs!$B$4),1,0) -> 0 | AG15: =IF(AND(O15=0,I15>Inputs!$B$4-Inputs!$B$8,I15<=Inputs!$B$4),1,0) -> 1 | AH15: =I15-H15 -> 76
A16: O00012 | B16: A0027 | C16: Safari Growers | Tax & Legal | compliance | D16: Tax & Legal | E16: Proposal | F16: 2608000 | G16: 50 | H16: 46223 | I16: 46370 | J16: 46281 | K16: U006 | L16: Referral | M16: Scope workshop | O16: =IF(OR(E16="Closed Won",E16="Closed Lost"),0,1) -> 1 | P16: =INDEX(Accounts!$K$5:$K$336,MATCH(B16,Accounts!$A$5:$A$336,0)) -> Agribusiness | Q16: =INDEX(Accounts!$D$5:$D$336,MATCH(B16,Accounts!$A$5:$A$336,0)) -> Priority | R16: =INDEX(Inputs!$B$11:$B$16,MATCH(E16,Inputs!$A$11:$A$16,0)) -> 50 | S16: =IF(F16="",0,F16)*R16/100 -> 1304000 | T16: =Inputs!$B$4-J16 -> 33 | U16: =IF(OR(F16="",F16=0),1,0) -> 0 | V16: =IF(K16="",1,0) -> 0 | W16: =IF(AND(O16=1,K16<>"",COUNTIFS(Owners!$A$5:$A$32,K16,Owners!$E$5:$E$32,"No")>0),1,0) -> 0 | X16: =IF(AND(O16=1,I16<Inputs!$B$4),1,0) -> 0 | Y16: =IF(AND(O16=1,T16>Inputs!$B$5),1,0) -> 0 | Z16: =IF(AND(O16=1,G16<>R16),1,0) -> 0 | AA16: =IF(AND(O16=1,M16=""),1,0) -> 0 | AB16: =IF(AND(E16="Closed Lost",N16=""),1,0) -> 0 | AC16: =SUM(U16:AB16) -> 0 | AD16: =IF(AC16=0,1,0) -> 1 | AE16: =IF(AND(O16=1,I16>=Inputs!$B$6,I16<=Inputs!$B$7),1,0) -> 1 | AF16: =IF(AND(E16="Closed Won",I16>=Inputs!$B$6,I16<=Inputs!$B$4),1,0) -> 0 | AG16: =IF(AND(O16=0,I16>Inputs!$B$4-Inputs!$B$8,I16<=Inputs!$B$4),1,0) -> 0 | AH16: =I16-H16 -> 147
A17: O00013 | B17: A0249 | C17: Nyota Petroleum | Consulting | compliance | D17: Consulting | E17: Closed Lost | F17: 34156000 | G17: 0 | H17: 46235 | I17: 46307 | J17: 46307 | L17: Existing client | N17: Incumbent retained | O17: =IF(OR(E17="Closed Won",E17="Closed Lost"),0,1) -> 0 | P17: =INDEX(Accounts!$K$5:$K$336,MATCH(B17,Accounts!$A$5:$A$336,0)) -> Energy & Resources | Q17: =INDEX(Accounts!$D$5:$D$336,MATCH(B17,Accounts!$A$5:$A$336,0)) -> Standard | R17: =INDEX(Inputs!$B$11:$B$16,MATCH(E17,Inputs!$A$11:$A$16,0)) -> 0 | S17: =IF(F17="",0,F17)*R17/100 -> 0 | T17: =Inputs!$B$4-J17 -> 7 | U17: =IF(OR(F17="",F17=0),1,0) -> 0 | V17: =IF(K17="",1,0) -> 1 | W17: =IF(AND(O17=1,K17<>"",COUNTIFS(Owners!$A$5:$A$32,K17,Owners!$E$5:$E$32,"No")>0),1,0) -> 0 | X17: =IF(AND(O17=1,I17<Inputs!$B$4),1,0) -> 0 | Y17: =IF(AND(O17=1,T17>Inputs!$B$5),1,0) -> 0 | Z17: =IF(AND(O17=1,G17<>R17),1,0) -> 0 | AA17: =IF(AND(O17=1,M17=""),1,0) -> 0 | AB17: =IF(AND(E17="Closed Lost",N17=""),1,0) -> 0 | AC17: =SUM(U17:AB17) -> 1 | AD17: =IF(AC17=0,1,0) -> 0 | AE17: =IF(AND(O17=1,I17>=Inputs!$B$6,I17<=Inputs!$B$7),1,0) -> 0 | AF17: =IF(AND(E17="Closed Won",I17>=Inputs!$B$6,I17<=Inputs!$B$4),1,0) -> 0 | AG17: =IF(AND(O17=0,I17>Inputs!$B$4-Inputs!$B$8,I17<=Inputs!$B$4),1,0) -> 1 | AH17: =I17-H17 -> 72
A18: O00014 | B18: A0025 | C18: Lakeview Bank | Risk | transformation | D18: Risk | E18: Prospecting | F18: 6960000 | G18: 10 | H18: 46306 | I18: 46374 | J18: 46305 | K18: U004 | L18: Cold outreach | M18: Pricing review | O18: =IF(OR(E18="Closed Won",E18="Closed Lost"),0,1) -> 1 | P18: =INDEX(Accounts!$K$5:$K$336,MATCH(B18,Accounts!$A$5:$A$336,0)) -> Financial Services | Q18: =INDEX(Accounts!$D$5:$D$336,MATCH(B18,Accounts!$A$5:$A$336,0)) -> Priority | R18: =INDEX(Inputs!$B$11:$B$16,MATCH(E18,Inputs!$A$11:$A$16,0)) -> 10 | S18: =IF(F18="",0,F18)*R18/100 -> 696000 | T18: =Inputs!$B$4-J18 -> 9 | U18: =IF(OR(F18="",F18=0),1,0) -> 0 | V18: =IF(K18="",1,0) -> 0 | W18: =IF(AND(O18=1,K18<>"",COUNTIFS(Owners!$A$5:$A$32,K18,Owners!$E$5:$E$32,"No")>0),1,0) -> 0 | X18: =IF(AND(O18=1,I18<Inputs!$B$4),1,0) -> 0 | Y18: =IF(AND(O18=1,T18>Inputs!$B$5),1,0) -> 0 | Z18: =IF(AND(O18=1,G18<>R18),1,0) -> 0 | AA18: =IF(AND(O18=1,M18=""),1,0) -> 0 | AB18: =IF(AND(E18="Closed Lost",N18=""),1,0) -> 0 | AC18: =SUM(U18:AB18) -> 0 | AD18: =IF(AC18=0,1,0) -> 1 | AE18: =IF(AND(O18=1,I18>=Inputs!$B$6,I18<=Inputs!$B$7),1,0) -> 1 | AF18: =IF(AND(E18="Closed Won",I18>=Inputs!$B$6,I18<=Inputs!$B$4),1,0) -> 0 | AG18: =IF(AND(O18=0,I18>Inputs!$B$4-Inputs!$B$8,I18<=Inputs!$B$4),1,0) -> 0 | AH18: =I18-H18 -> 68
A19: O00015 | B19: A0038 | C19: Pwani Media | Consulting | due diligence | D19: Consulting | E19: Proposal | F19: 10433000 | G19: 50 | H19: 46165 | I19: 46281 | J19: 46284 | K19: U011 | L19: Existing client | M19: Scope workshop | O19: =IF(OR(E19="Closed Won",E19="Closed Lost"),0,1) -> 1 | P19: =INDEX(Accounts!$K$5:$K$336,MATCH(B19,Accounts!$A$5:$A$336,0)) -> Technology, Media & Telecom | Q19: =INDEX(Accounts!$D$5:$D$336,MATCH(B19,Accounts!$A$5:$A$336,0)) -> Priority | R19: =INDEX(Inputs!$B$11:$B$16,MATCH(E19,Inputs!$A$11:$A$16,0)) -> 50 | S19: =IF(F19="",0,F19)*R19/100 -> 5216500 | T19: =Inputs!$B$4-J19 -> 30 | U19: =IF(OR(F19="",F19=0),1,0) -> 0 | V19: =IF(K19="",1,0) -> 0 | W19: =IF(AND(O19=1,K19<>"",COUNTIFS(Owners!$A$5:$A$32,K19,Owners!$E$5:$E$32,"No")>0),1,0) -> 0 | X19: =IF(AND(O19=1,I19<Inputs!$B$4),1,0) -> 1 | Y19: =IF(AND(O19=1,T19>Inputs!$B$5),1,0) -> 0 | Z19: =IF(AND(O19=1,G19<>R19),1,0) -> 0 | AA19: =IF(AND(O19=1,M19=""),1,0) -> 0 | AB19: =IF(AND(E19="Closed Lost",N19=""),1,0) -> 0 | AC19: =SUM(U19:AB19) -> 1 | AD19: =IF(AC19=0,1,0) -> 0 | AE19: =IF(AND(O19=1,I19>=Inputs!$B$6,I19<=Inputs!$B$7),1,0) -> 1 | AF19: =IF(AND(E19="Closed Won",I19>=Inputs!$B$6,I19<=Inputs!$B$4),1,0) -> 0 | AG19: =IF(AND(O19=0,I19>Inputs!$B$4-Inputs!$B$8,I19<=Inputs!$B$4),1,0) -> 0 | AH19: =I19-H19 -> 116
A20: O00016 | B20: A0280 | C20: Simba Diagnostics | Tax & Legal | review | D20: Tax & Legal | E20: Closed Won | F20: 3840000 | G20: 100 | H20: 45989 | I20: 46096 | J20: 46096 | K20: U025 | L20: Existing client | O20: =IF(OR(E20="Closed Won",E20="Closed Lost"),0,1) -> 0 | P20: =INDEX(Accounts!$K$5:$K$336,MATCH(B20,Accounts!$A$5:$A$336,0)) -> Health | Q20: =INDEX(Accounts!$D$5:$D$336,MATCH(B20,Accounts!$A$5:$A$336,0)) -> Standard | R20: =INDEX(Inputs!$B$11:$B$16,MATCH(E20,Inputs!$A$11:$A$16,0)) -> 100 | S20: =IF(F20="",0,F20)*R20/100 -> 3840000 | T20: =Inputs!$B$4-J20 -> 218 | U20: =IF(OR(F20="",F20=0),1,0) -> 0 | V20: =IF(K20="",1,0) -> 0 | W20: =IF(AND(O20=1,K20<>"",COUNTIFS(Owners!$A$5:$A$32,K20,Owners!$E$5:$E$32,"No")>0),1,0) -> 0 | X20: =IF(AND(O20=1,I20<Inputs!$B$4),1,0) -> 0 | Y20: =IF(AND(O20=1,T20>Inputs!$B$5),1,0) -> 0 | Z20: =IF(AND(O20=1,G20<>R20),1,0) -> 0 | AA20: =IF(AND(O20=1,M20=""),1,0) -> 0 | AB20: =IF(AND(E20="Closed Lost",N20=""),1,0) -> 0 | AC20: =SUM(U20:AB20) -> 0 | AD20: =IF(AC20=0,1,0) -> 1 | AE20: =IF(AND(O20=1,I20>=Inputs!$B$6,I20<=Inputs!$B$7),1,0) -> 0 | AF20: =IF(AND(E20="Closed Won",I20>=Inputs!$B$6,I20<=Inputs!$B$4),1,0) -> 0 | AG20: =IF(AND(O20=0,I20>Inputs!$B$4-Inputs!$B$8,I20<=Inputs!$B$4),1,0) -> 1 | AH20: =I20-H20 -> 107
A21: O00017 | B21: A0013 | C21: Kilimanjaro Capital | Tax & Legal | review | D21: Tax & Legal | E21: Closed Won | F21: 6278000 | G21: 100 | H21: 46153 | I21: 46238 | J21: 46238 | K21: U006 | L21: Existing client | O21: =IF(OR(E21="Closed Won",E21="Closed Lost"),0,1) -> 0 | P21: =INDEX(Accounts!$K$5:$K$336,MATCH(B21,Accounts!$A$5:$A$336,0)) -> Financial Services | Q21: =INDEX(Accounts!$D$5:$D$336,MATCH(B21,Accounts!$A$5:$A$336,0)) -> Priority | R21: =INDEX(Inputs!$B$11:$B$16,MATCH(E21,Inputs!$A$11:$A$16,0)) -> 100 | S21: =IF(F21="",0,F21)*R21/100 -> 6278000 | T21: =Inputs!$B$4-J21 -> 76 | U21: =IF(OR(F21="",F21=0),1,0) -> 0 | V21: =IF(K21="",1,0) -> 0 | W21: =IF(AND(O21=1,K21<>"",COUNTIFS(Owners!$A$5:$A$32,K21,Owners!$E$5:$E$32,"No")>0),1,0) -> 0 | X21: =IF(AND(O21=1,I21<Inputs!$B$4),1,0) -> 0 | Y21: =IF(AND(O21=1,T21>Inputs!$B$5),1,0) -> 0 | Z21: =IF(AND(O21=1,G21<>R21),1,0) -> 0 | AA21: =IF(AND(O21=1,M21=""),1,0) -> 0 | AB21: =IF(AND(E21="Closed Lost",N21=""),1,0) -> 0 | AC21: =SUM(U21:AB21) -> 0 | AD21: =IF(AC21=0,1,0) -> 1 | AE21: =IF(AND(O21=1,I21>=Inputs!$B$6,I21<=Inputs!$B$7),1,0) -> 0 | AF21: =IF(AND(E21="Closed Won",I21>=Inputs!$B$6,I21<=Inputs!$B$4),1,0) -> 1 | AG21: =IF(AND(O21=0,I21>Inputs!$B$4-Inputs!$B$8,I21<=Inputs!$B$4),1,0) -> 1 | AH21: =I21-H21 -> 85
A22: O00018 | B22: A0068 | C22: Nyota Asset Managers | Tax & Legal | support | D22: Tax & Legal | E22: Closed Won | F22: 14738000 | G22: 100 | H22: 45990 | I22: 46050 | J22: 46050 | K22: U011 | L22: Event | O22: =IF(OR(E22="Closed Won",E22="Closed Lost"),0,1) -> 0 | P22: =INDEX(Accounts!$K$5:$K$336,MATCH(B22,Accounts!$A$5:$A$336,0)) -> Financial Services | Q22: =INDEX(Accounts!$D$5:$D$336,MATCH(B22,Accounts!$A$5:$A$336,0)) -> Key | R22: =INDEX(Inputs!$B$11:$B$16,MATCH(E22,Inputs!$A$11:$A$16,0)) -> 100 | S22: =IF(F22="",0,F22)*R22/100 -> 14738000 | T22: =Inputs!$B$4-J22 -> 264 | U22: =IF(OR(F22="",F22=0),1,0) -> 0 | V22: =IF(K22="",1,0) -> 0 | W22: =IF(AND(O22=1,K22<>"",COUNTIFS(Owners!$A$5:$A$32,K22,Owners!$E$5:$E$32,"No")>0),1,0) -> 0 | X22: =IF(AND(O22=1,I22<Inputs!$B$4),1,0) -> 0 | Y22: =IF(AND(O22=1,T22>Inputs!$B$5),1,0) -> 0 | Z22: =IF(AND(O22=1,G22<>R22),1,0) -> 0 | AA22: =IF(AND(O22=1,M22=""),1,0) -> 0 | AB22: =IF(AND(E22="Closed Lost",N22=""),1,0) -> 0 | AC22: =SUM(U22:AB22) -> 0 | AD22: =IF(AC22=0,1,0) -> 1 | AE22: =IF(AND(O22=1,I22>=Inputs!$B$6,I22<=Inputs!$B$7),1,0) -> 0 | AF22: =IF(AND(E22="Closed Won",I22>=Inputs!$B$6,I22<=Inputs!$B$4),1,0) -> 0 | AG22: =IF(AND(O22=0,I22>Inputs!$B$4-Inputs!$B$8,I22<=Inputs!$B$4),1,0) -> 1 | AH22: =I22-H22 -> 60
A23: O00019 | B23: A0015 | C23: Baobab Energy | Assurance | transformation | D23: Assurance | E23: Closed Won | F23: 12321000 | G23: 100 | H23: 46039 | I23: 46138 | J23: 46138 | L23: Digital | O23: =IF(OR(E23="Closed Won",E23="Closed Lost"),0,1) -> 0 | P23: =INDEX(Accounts!$K$5:$K$336,MATCH(B23,Accounts!$A$5:$A$336,0)) -> Energy & Resources | Q23: =INDEX(Accounts!$D$5:$D$336,MATCH(B23,Accounts!$A$5:$A$336,0)) -> Priority | R23: =INDEX(Inputs!$B$11:$B$16,MATCH(E23,Inputs!$A$11:$A$16,0)) -> 100 | S23: =IF(F23="",0,F23)*R23/100 -> 12321000 | T23: =Inputs!$B$4-J23 -> 176 | U23: =IF(OR(F23="",F23=0),1,0) -> 0 | V23: =IF(K23="",1,0) -> 1 | W23: =IF(AND(O23=1,K23<>"",COUNTIFS(Owners!$A$5:$A$32,K23,Owners!$E$5:$E$32,"No")>0),1,0) -> 0 | X23: =IF(AND(O23=1,I23<Inputs!$B$4),1,0) -> 0 | Y23: =IF(AND(O23=1,T23>Inputs!$B$5),1,0) -> 0 | Z23: =IF(AND(O23=1,G23<>R23),1,0) -> 0 | AA23: =IF(AND(O23=1,M23=""),1,0) -> 0 | AB23: =IF(AND(E23="Closed Lost",N23=""),1,0) -> 0 | AC23: =SUM(U23:AB23) -> 1 | AD23: =IF(AC23=0,1,0) -> 0 | AE23: =IF(AND(O23=1,I23>=Inputs!$B$6,I23<=Inputs!$B$7),1,0) -> 0 | AF23: =IF(AND(E23="Closed Won",I23>=Inputs!$B$6,I23<=Inputs!$B$4),1,0) -> 0 | AG23: =IF(AND(O23=0,I23>Inputs!$B$4-Inputs!$B$8,I23<=Inputs!$B$4),1,0) -> 1 | AH23: =I23-H23 -> 99
A24: O00020 | B24: A0021 | C24: Zuri Asset Managers | Tax & Legal | compliance | D24: Tax & Legal | E24: Closed Won | F24: 10584000 | G24: 100 | H24: 45958 | I24: 46113 | J24: 46113 | K24: U007 | L24: Thought leadership | O24: =IF(OR(E24="Closed Won",E24="Closed Lost"),0,1) -> 0 | P24: =INDEX(Accounts!$K$5:$K$336,MATCH(B24,Accounts!$A$5:$A$336,0)) -> Financial Services | Q24: =INDEX(Accounts!$D$5:$D$336,MATCH(B24,Accounts!$A$5:$A$336,0)) -> Priority | R24: =INDEX(Inputs!$B$11:$B$16,MATCH(E24,Inputs!$A$11:$A$16,0)) -> 100 | S24: =IF(F24="",0,F24)*R24/100 -> 10584000 | T24: =Inputs!$B$4-J24 -> 201 | U24: =IF(OR(F24="",F24=0),1,0) -> 0 | V24: =IF(K24="",1,0) -> 0 | W24: =IF(AND(O24=1,K24<>"",COUNTIFS(Owners!$A$5:$A$32,K24,Owners!$E$5:$E$32,"No")>0),1,0) -> 0 | X24: =IF(AND(O24=1,I24<Inputs!$B$4),1,0) -> 0 | Y24: =IF(AND(O24=1,T24>Inputs!$B$5),1,0) -> 0 | Z24: =IF(AND(O24=1,G24<>R24),1,0) -> 0 | AA24: =IF(AND(O24=1,M24=""),1,0) -> 0 | AB24: =IF(AND(E24="Closed Lost",N24=""),1,0) -> 0 | AC24: =SUM(U24:AB24) -> 0 | AD24: =IF(AC24=0,1,0) -> 1 | AE24: =IF(AND(O24=1,I24>=Inputs!$B$6,I24<=Inputs!$B$7),1,0) -> 0 | AF24: =IF(AND(E24="Closed Won",I24>=Inputs!$B$6,I24<=Inputs!$B$4),1,0) -> 0 | AG24: =IF(AND(O24=0,I24>Inputs!$B$4-Inputs!$B$8,I24<=Inputs!$B$4),1,0) -> 1 | AH24: =I24-H24 -> 155
A25: O00021 | B25: A0138 | C25: Baobab Development Fund | Tax & Legal | support | D25: Tax & Legal | E25: Closed Lost | F25: 26258000 | G25: 0 | H25: 46017 | I25: 46107 | J25: 46107 | K25: U016 | L25: Existing client | N25: No decision | O25: =IF(OR(E25="Closed Won",E25="Closed Lost"),0,1) -> 0 | P25: =INDEX(Accounts!$K$5:$K$336,MATCH(B25,Accounts!$A$5:$A$336,0)) -> Public Sector & Development | Q25: =INDEX(Accounts!$D$5:$D$336,MATCH(B25,Accounts!$A$5:$A$336,0)) -> Standard | R25: =INDEX(Inputs!$B$11:$B$16,MATCH(E25,Inputs!$A$11:$A$16,0)) -> 0 | S25: =IF(F25="",0,F25)*R25/100 -> 0 | T25: =Inputs!$B$4-J25 -> 207 | U25: =IF(OR(F25="",F25=0),1,0) -> 0 | V25: =IF(K25="",1,0) -> 0 | W25: =IF(AND(O25=1,K25<>"",COUNTIFS(Owners!$A$5:$A$32,K25,Owners!$E$5:$E$32,"No")>0),1,0) -> 0 | X25: =IF(AND(O25=1,I25<Inputs!$B$4),1,0) -> 0 | Y25: =IF(AND(O25=1,T25>Inputs!$B$5),1,0) -> 0 | Z25: =IF(AND(O25=1,G25<>R25),1,0) -> 0 | AA25: =IF(AND(O25=1,M25=""),1,0) -> 0 | AB25: =IF(AND(E25="Closed Lost",N25=""),1,0) -> 0 | AC25: =SUM(U25:AB25) -> 0 | AD25: =IF(AC25=0,1,0) -> 1 | AE25: =IF(AND(O25=1,I25>=Inputs!$B$6,I25<=Inputs!$B$7),1,0) -> 0 | AF25: =IF(AND(E25="Closed Won",I25>=Inputs!$B$6,I25<=Inputs!$B$4),1,0) -> 0 | AG25: =IF(AND(O25=0,I25>Inputs!$B$4-Inputs!$B$8,I25<=Inputs!$B$4),1,0) -> 1 | AH25: =I25-H25 -> 90
A26: O00022 | B26: A0031 | C26: Acacia Hospital | Tax & Legal | review | D26: Tax & Legal | E26: Closed Lost | F26: 19420000 | G26: 0 | H26: 46048 | I26: 46150 | J26: 46150 | K26: U003 | L26: Existing client | N26: No decision | O26: =IF(OR(E26="Closed Won",E26="Closed Lost"),0,1) -> 0 | P26: =INDEX(Accounts!$K$5:$K$336,MATCH(B26,Accounts!$A$5:$A$336,0)) -> Unassigned | Q26: =INDEX(Accounts!$D$5:$D$336,MATCH(B26,Accounts!$A$5:$A$336,0)) -> Priority | R26: =INDEX(Inputs!$B$11:$B$16,MATCH(E26,Inputs!$A$11:$A$16,0)) -> 0 | S26: =IF(F26="",0,F26)*R26/100 -> 0 | T26: =Inputs!$B$4-J26 -> 164 | U26: =IF(OR(F26="",F26=0),1,0) -> 0 | V26: =IF(K26="",1,0) -> 0 | W26: =IF(AND(O26=1,K26<>"",COUNTIFS(Owners!$A$5:$A$32,K26,Owners!$E$5:$E$32,"No")>0),1,0) -> 0 | X26: =IF(AND(O26=1,I26<Inputs!$B$4),1,0) -> 0 | Y26: =IF(AND(O26=1,T26>Inputs!$B$5),1,0) -> 0 | Z26: =IF(AND(O26=1,G26<>R26),1,0) -> 0 | AA26: =IF(AND(O26=1,M26=""),1,0) -> 0 | AB26: =IF(AND(E26="Closed Lost",N26=""),1,0) -> 0 | AC26: =SUM(U26:AB26) -> 0 | AD26: =IF(AC26=0,1,0) -> 1 | AE26: =IF(AND(O26=1,I26>=Inputs!$B$6,I26<=Inputs!$B$7),1,0) -> 0 | AF26: =IF(AND(E26="Closed Won",I26>=Inputs!$B$6,I26<=Inputs!$B$4),1,0) -> 0 | AG26: =IF(AND(O26=0,I26>Inputs!$B$4-Inputs!$B$8,I26<=Inputs!$B$4),1,0) -> 1 | AH26: =I26-H26 -> 102
A27: O00023 | B27: A0028 | C27: Lakeview Hotels | Consulting | review | D27: Consulting | E27: Qualification | F27: 8663000 | G27: 25 | H27: 46159 | I27: 46381 | J27: 46302 | K27: U007 | L27: Referral | M27: Partner meeting | O27: =IF(OR(E27="Closed Won",E27="Closed Lost"),0,1) -> 1 | P27: =INDEX(Accounts!$K$5:$K$336,MATCH(B27,Accounts!$A$5:$A$336,0)) -> Consumer & Retail | Q27: =INDEX(Accounts!$D$5:$D$336,MATCH(B27,Accounts!$A$5:$A$336,0)) -> Priority | R27: =INDEX(Inputs!$B$11:$B$16,MATCH(E27,Inputs!$A$11:$A$16,0)) -> 25 | S27: =IF(F27="",0,F27)*R27/100 -> 2165750 | T27: =Inputs!$B$4-J27 -> 12 | U27: =IF(OR(F27="",F27=0),1,0) -> 0 | V27: =IF(K27="",1,0) -> 0 | W27: =IF(AND(O27=1,K27<>"",COUNTIFS(Owners!$A$5:$A$32,K27,Owners!$E$5:$E$32,"No")>0),1,0) -> 0 | X27: =IF(AND(O27=1,I27<Inputs!$B$4),1,0) -> 0 | Y27: =IF(AND(O27=1,T27>Inputs!$B$5),1,0) -> 0 | Z27: =IF(AND(O27=1,G27<>R27),1,0) -> 0 | AA27: =IF(AND(O27=1,M27=""),1,0) -> 0 | AB27: =IF(AND(E27="Closed Lost",N27=""),1,0) -> 0 | AC27: =SUM(U27:AB27) -> 0 | AD27: =IF(AC27=0,1,0) -> 1 | AE27: =IF(AND(O27=1,I27>=Inputs!$B$6,I27<=Inputs!$B$7),1,0) -> 1 | AF27: =IF(AND(E27="Closed Won",I27>=Inputs!$B$6,I27<=Inputs!$B$4),1,0) -> 0 | AG27: =IF(AND(O27=0,I27>Inputs!$B$4-Inputs!$B$8,I27<=Inputs!$B$4),1,0) -> 0 | AH27: =I27-H27 -> 222
A28: O00024 | B28: A0077 | C28: Umoja Foods | Consulting | support | D28: Consulting | E28: Prospecting | F28: 11361000 | G28: 10 | H28: 46271 | I28: 46355 | J28: 46240 | K28: U009 | L28: Digital | O28: =IF(OR(E28="Closed Won",E28="Closed Lost"),0,1) -> 1 | P28: =INDEX(Accounts!$K$5:$K$336,MATCH(B28,Accounts!$A$5:$A$336,0)) -> Consumer & Retail | Q28: =INDEX(Accounts!$D$5:$D$336,MATCH(B28,Accounts!$A$5:$A$336,0)) -> Key | R28: =INDEX(Inputs!$B$11:$B$16,MATCH(E28,Inputs!$A$11:$A$16,0)) -> 10 | S28: =IF(F28="",0,F28)*R28/100 -> 1136100 | T28: =Inputs!$B$4-J28 -> 74 | U28: =IF(OR(F28="",F28=0),1,0) -> 0 | V28: =IF(K28="",1,0) -> 0 | W28: =IF(AND(O28=1,K28<>"",COUNTIFS(Owners!$A$5:$A$32,K28,Owners!$E$5:$E$32,"No")>0),1,0) -> 0 | X28: =IF(AND(O28=1,I28<Inputs!$B$4),1,0) -> 0 | Y28: =IF(AND(O28=1,T28>Inputs!$B$5),1,0) -> 1 | Z28: =IF(AND(O28=1,G28<>R28),1,0) -> 0 | AA28: =IF(AND(O28=1,M28=""),1,0) -> 1 | AB28: =IF(AND(E28="Closed Lost",N28=""),1,0) -> 0 | AC28: =SUM(U28:AB28) -> 2 | AD28: =IF(AC28=0,1,0) -> 0 | AE28: =IF(AND(O28=1,I28>=Inputs!$B$6,I28<=Inputs!$B$7),1,0) -> 1 | AF28: =IF(AND(E28="Closed Won",I28>=Inputs!$B$6,I28<=Inputs!$B$4),1,0) -> 0 | AG28: =IF(AND(O28=0,I28>Inputs!$B$4-Inputs!$B$8,I28<=Inputs!$B$4),1,0) -> 0 | AH28: =I28-H28 -> 84
A29: O00025 | B29: A0231 | C29: Highland Foundation | Assurance | readiness | D29: Assurance | E29: Negotiation | F29: 7705000 | G29: 75 | H29: 46226 | I29: 46433 | J29: 46180 | K29: U021 | L29: Event | M29: Send proposal | O29: =IF(OR(E29="Closed Won",E29="Closed Lost"),0,1) -> 1 | P29: =INDEX(Accounts!$K$5:$K$336,MATCH(B29,Accounts!$A$5:$A$336,0)) -> Public Sector & Development | Q29: =INDEX(Accounts!$D$5:$D$336,MATCH(B29,Accounts!$A$5:$A$336,0)) -> Standard | R29: =INDEX(Inputs!$B$11:$B$16,MATCH(E29,Inputs!$A$11:$A$16,0)) -> 75 | S29: =IF(F29="",0,F29)*R29/100 -> 5778750 | T29: =Inputs!$B$4-J29 -> 134 | U29: =IF(OR(F29="",F29=0),1,0) -> 0 | V29: =IF(K29="",1,0) -> 0 | W29: =IF(AND(O29=1,K29<>"",COUNTIFS(Owners!$A$5:$A$32,K29,Owners!$E$5:$E$32,"No")>0),1,0) -> 0 | X29: =IF(AND(O29=1,I29<Inputs!$B$4),1,0) -> 0 | Y29: =IF(AND(O29=1,T29>Inputs!$B$5),1,0) -> 1 | Z29: =IF(AND(O29=1,G29<>R29),1,0) -> 0 | AA29: =IF(AND(O29=1,M29=""),1,0) -> 0 | AB29: =IF(AND(E29="Closed Lost",N29=""),1,0) -> 0 | AC29: =SUM(U29:AB29) -> 1 | AD29: =IF(AC29=0,1,0) -> 0 | AE29: =IF(AND(O29=1,I29>=Inputs!$B$6,I29<=Inputs!$B$7),1,0) -> 1 | AF29: =IF(AND(E29="Closed Won",I29>=Inputs!$B$6,I29<=Inputs!$B$4),1,0) -> 0 | AG29: =IF(AND(O29=0,I29>Inputs!$B$4-Inputs!$B$8,I29<=Inputs!$B$4),1,0) -> 0 | AH29: =I29-H29 -> 207
A30: O00026 | B30: A0306 | C30: Mto Cloud | Consulting | annual | D30: Consulting | E30: Negotiation | F30: 18475000 | G30: 75 | H30: 46094 | I30: 46352 | J30: 46292 | K30: U008 | L30: Existing client | M30: Follow-up call | O30: =IF(OR(E30="Closed Won",E30="Closed Lost"),0,1) -> 1 | P30: =INDEX(Accounts!$K$5:$K$336,MATCH(B30,Accounts!$A$5:$A$336,0)) -> Technology, Media & Telecom | Q30: =INDEX(Accounts!$D$5:$D$336,MATCH(B30,Accounts!$A$5:$A$336,0)) -> Standard | R30: =INDEX(Inputs!$B$11:$B$16,MATCH(E30,Inputs!$A$11:$A$16,0)) -> 75 | S30: =IF(F30="",0,F30)*R30/100 -> 13856250 | T30: =Inputs!$B$4-J30 -> 22 | U30: =IF(OR(F30="",F30=0),1,0) -> 0 | V30: =IF(K30="",1,0) -> 0 | W30: =IF(AND(O30=1,K30<>"",COUNTIFS(Owners!$A$5:$A$32,K30,Owners!$E$5:$E$32,"No")>0),1,0) -> 0 | X30: =IF(AND(O30=1,I30<Inputs!$B$4),1,0) -> 0 | Y30: =IF(AND(O30=1,T30>Inputs!$B$5),1,0) -> 0 | Z30: =IF(AND(O30=1,G30<>R30),1,0) -> 0 | AA30: =IF(AND(O30=1,M30=""),1,0) -> 0 | AB30: =IF(AND(E30="Closed Lost",N30=""),1,0) -> 0 | AC30: =SUM(U30:AB30) -> 0 | AD30: =IF(AC30=0,1,0) -> 1 | AE30: =IF(AND(O30=1,I30>=Inputs!$B$6,I30<=Inputs!$B$7),1,0) -> 1 | AF30: =IF(AND(E30="Closed Won",I30>=Inputs!$B$6,I30<=Inputs!$B$4),1,0) -> 0 | AG30: =IF(AND(O30=0,I30>Inputs!$B$4-Inputs!$B$8,I30<=Inputs!$B$4),1,0) -> 0 | AH30: =I30-H30 -> 258
A31: O00027 | B31: A0009 | C31: Rift Cloud | Risk | advisory | D31: Risk | E31: Proposal | F31: 3663000 | G31: 50 | H31: 46027 | I31: 46306 | J31: 46296 | K31: U002 | L31: Digital | M31: Send proposal | O31: =IF(OR(E31="Closed Won",E31="Closed Lost"),0,1) -> 1 | P31: =INDEX(Accounts!$K$5:$K$336,MATCH(B31,Accounts!$A$5:$A$336,0)) -> Technology, Media & Telecom | Q31: =INDEX(Accounts!$D$5:$D$336,MATCH(B31,Accounts!$A$5:$A$336,0)) -> Priority | R31: =INDEX(Inputs!$B$11:$B$16,MATCH(E31,Inputs!$A$11:$A$16,0)) -> 50 | S31: =IF(F31="",0,F31)*R31/100 -> 1831500 | T31: =Inputs!$B$4-J31 -> 18 | U31: =IF(OR(F31="",F31=0),1,0) -> 0 | V31: =IF(K31="",1,0) -> 0 | W31: =IF(AND(O31=1,K31<>"",COUNTIFS(Owners!$A$5:$A$32,K31,Owners!$E$5:$E$32,"No")>0),1,0) -> 0 | X31: =IF(AND(O31=1,I31<Inputs!$B$4),1,0) -> 1 | Y31: =IF(AND(O31=1,T31>Inputs!$B$5),1,0) -> 0 | Z31: =IF(AND(O31=1,G31<>R31),1,0) -> 0 | AA31: =IF(AND(O31=1,M31=""),1,0) -> 0 | AB31: =IF(AND(E31="Closed Lost",N31=""),1,0) -> 0 | AC31: =SUM(U31:AB31) -> 1 | AD31: =IF(AC31=0,1,0) -> 0 | AE31: =IF(AND(O31=1,I31>=Inputs!$B$6,I31<=Inputs!$B$7),1,0) -> 1 | AF31: =IF(AND(E31="Closed Won",I31>=Inputs!$B$6,I31<=Inputs!$B$4),1,0) -> 0 | AG31: =IF(AND(O31=0,I31>Inputs!$B$4-Inputs!$B$8,I31<=Inputs!$B$4),1,0) -> 0 | AH31: =I31-H31 -> 279
A32: O00028 | B32: A0134 | C32: Pwani Geothermal | Deals | due diligence | D32: Deals | E32: Proposal | F32: 60815000 | G32: 0 | H32: 46124 | I32: 46382 | J32: 46279 | K32: U025 | L32: Thought leadership | M32: Pricing review | O32: =IF(OR(E32="Closed Won",E32="Closed Lost"),0,1) -> 1 | P32: =INDEX(Accounts!$K$5:$K$336,MATCH(B32,Accounts!$A$5:$A$336,0)) -> Unassigned | Q32: =INDEX(Accounts!$D$5:$D$336,MATCH(B32,Accounts!$A$5:$A$336,0)) -> Standard | R32: =INDEX(Inputs!$B$11:$B$16,MATCH(E32,Inputs!$A$11:$A$16,0)) -> 50 | S32: =IF(F32="",0,F32)*R32/100 -> 30407500 | T32: =Inputs!$B$4-J32 -> 35 | U32: =IF(OR(F32="",F32=0),1,0) -> 0 | V32: =IF(K32="",1,0) -> 0 | W32: =IF(AND(O32=1,K32<>"",COUNTIFS(Owners!$A$5:$A$32,K32,Owners!$E$5:$E$32,"No")>0),1,0) -> 0 | X32: =IF(AND(O32=1,I32<Inputs!$B$4),1,0) -> 0 | Y32: =IF(AND(O32=1,T32>Inputs!$B$5),1,0) -> 0 | Z32: =IF(AND(O32=1,G32<>R32),1,0) -> 1 | AA32: =IF(AND(O32=1,M32=""),1,0) -> 0 | AB32: =IF(AND(E32="Closed Lost",N32=""),1,0) -> 0 | AC32: =SUM(U32:AB32) -> 1 | AD32: =IF(AC32=0,1,0) -> 0 | AE32: =IF(AND(O32=1,I32>=Inputs!$B$6,I32<=Inputs!$B$7),1,0) -> 1 | AF32: =IF(AND(E32="Closed Won",I32>=Inputs!$B$6,I32<=Inputs!$B$4),1,0) -> 0 | AG32: =IF(AND(O32=0,I32>Inputs!$B$4-Inputs!$B$8,I32<=Inputs!$B$4),1,0) -> 0 | AH32: =I32-H32 -> 258
A33: O00029 | B33: A0028 | C33: Lakeview Hotels | Consulting | advisory | D33: Consulting | E33: Negotiation | F33: 30478000 | G33: 75 | H33: 46240 | I33: 46479 | J33: 46269 | K33: U007 | L33: Referral | M33: Pricing review | O33: =IF(OR(E33="Closed Won",E33="Closed Lost"),0,1) -> 1 | P33: =INDEX(Accounts!$K$5:$K$336,MATCH(B33,Accounts!$A$5:$A$336,0)) -> Consumer & Retail | Q33: =INDEX(Accounts!$D$5:$D$336,MATCH(B33,Accounts!$A$5:$A$336,0)) -> Priority | R33: =INDEX(Inputs!$B$11:$B$16,MATCH(E33,Inputs!$A$11:$A$16,0)) -> 75 | S33: =IF(F33="",0,F33)*R33/100 -> 22858500 | T33: =Inputs!$B$4-J33 -> 45 | U33: =IF(OR(F33="",F33=0),1,0) -> 0 | V33: =IF(K33="",1,0) -> 0 | W33: =IF(AND(O33=1,K33<>"",COUNTIFS(Owners!$A$5:$A$32,K33,Owners!$E$5:$E$32,"No")>0),1,0) -> 0 | X33: =IF(AND(O33=1,I33<Inputs!$B$4),1,0) -> 0 | Y33: =IF(AND(O33=1,T33>Inputs!$B$5),1,0) -> 0 | Z33: =IF(AND(O33=1,G33<>R33),1,0) -> 0 | AA33: =IF(AND(O33=1,M33=""),1,0) -> 0 | AB33: =IF(AND(E33="Closed Lost",N33=""),1,0) -> 0 | AC33: =SUM(U33:AB33) -> 0 | AD33: =IF(AC33=0,1,0) -> 1 | AE33: =IF(AND(O33=1,I33>=Inputs!$B$6,I33<=Inputs!$B$7),1,0) -> 1 | AF33: =IF(AND(E33="Closed Won",I33>=Inputs!$B$6,I33<=Inputs!$B$4),1,0) -> 0 | AG33: =IF(AND(O33=0,I33>Inputs!$B$4-Inputs!$B$8,I33<=Inputs!$B$4),1,0) -> 0 | AH33: =I33-H33 -> 239
A34: O00030 | B34: A0065 | C34: Baobab Telecom | Tax & Legal | advisory | D34: Tax & Legal | E34: Closed Lost | F34: 3191000 | G34: 0 | H34: 46092 | I34: 46196 | J34: 46196 | K34: U020 | L34: Cold outreach | N34: Price | O34: =IF(OR(E34="Closed Won",E34="Closed Lost"),0,1) -> 0 | P34: =INDEX(Accounts!$K$5:$K$336,MATCH(B34,Accounts!$A$5:$A$336,0)) -> Technology, Media & Telecom | Q34: =INDEX(Accounts!$D$5:$D$336,MATCH(B34,Accounts!$A$5:$A$336,0)) -> Key | R34: =INDEX(Inputs!$B$11:$B$16,MATCH(E34,Inputs!$A$11:$A$16,0)) -> 0 | S34: =IF(F34="",0,F34)*R34/100 -> 0 | T34: =Inputs!$B$4-J34 -> 118 | U34: =IF(OR(F34="",F34=0),1,0) -> 0 | V34: =IF(K34="",1,0) -> 0 | W34: =IF(AND(O34=1,K34<>"",COUNTIFS(Owners!$A$5:$A$32,K34,Owners!$E$5:$E$32,"No")>0),1,0) -> 0 | X34: =IF(AND(O34=1,I34<Inputs!$B$4),1,0) -> 0 | Y34: =IF(AND(O34=1,T34>Inputs!$B$5),1,0) -> 0 | Z34: =IF(AND(O34=1,G34<>R34),1,0) -> 0 | AA34: =IF(AND(O34=1,M34=""),1,0) -> 0 | AB34: =IF(AND(E34="Closed Lost",N34=""),1,0) -> 0 | AC34: =SUM(U34:AB34) -> 0 | AD34: =IF(AC34=0,1,0) -> 1 | AE34: =IF(AND(O34=1,I34>=Inputs!$B$6,I34<=Inputs!$B$7),1,0) -> 0 | AF34: =IF(AND(E34="Closed Won",I34>=Inputs!$B$6,I34<=Inputs!$B$4),1,0) -> 0 | AG34: =IF(AND(O34=0,I34>Inputs!$B$4-Inputs!$B$8,I34<=Inputs!$B$4),1,0) -> 1 | AH34: =I34-H34 -> 104
A35: O00031 | B35: A0021 | C35: Zuri Asset Managers | Deals | transformation | D35: Deals | E35: Closed Won | F35: 5994000 | G35: 100 | H35: 45901 | I35: 46089 | J35: 46089 | K35: U027 | L35: Thought leadership | O35: =IF(OR(E35="Closed Won",E35="Closed Lost"),0,1) -> 0 | P35: =INDEX(Accounts!$K$5:$K$336,MATCH(B35,Accounts!$A$5:$A$336,0)) -> Financial Services | Q35: =INDEX(Accounts!$D$5:$D$336,MATCH(B35,Accounts!$A$5:$A$336,0)) -> Priority | R35: =INDEX(Inputs!$B$11:$B$16,MATCH(E35,Inputs!$A$11:$A$16,0)) -> 100 | S35: =IF(F35="",0,F35)*R35/100 -> 5994000 | T35: =Inputs!$B$4-J35 -> 225 | U35: =IF(OR(F35="",F35=0),1,0) -> 0 | V35: =IF(K35="",1,0) -> 0 | W35: =IF(AND(O35=1,K35<>"",COUNTIFS(Owners!$A$5:$A$32,K35,Owners!$E$5:$E$32,"No")>0),1,0) -> 0 | X35: =IF(AND(O35=1,I35<Inputs!$B$4),1,0) -> 0 | Y35: =IF(AND(O35=1,T35>Inputs!$B$5),1,0) -> 0 | Z35: =IF(AND(O35=1,G35<>R35),1,0) -> 0 | AA35: =IF(AND(O35=1,M35=""),1,0) -> 0 | AB35: =IF(AND(E35="Closed Lost",N35=""),1,0) -> 0 | AC35: =SUM(U35:AB35) -> 0 | AD35: =IF(AC35=0,1,0) -> 1 | AE35: =IF(AND(O35=1,I35>=Inputs!$B$6,I35<=Inputs!$B$7),1,0) -> 0 | AF35: =IF(AND(E35="Closed Won",I35>=Inputs!$B$6,I35<=Inputs!$B$4),1,0) -> 0 | AG35: =IF(AND(O35=0,I35>Inputs!$B$4-Inputs!$B$8,I35<=Inputs!$B$4),1,0) -> 1 | AH35: =I35-H35 -> 188
A36: O00032 | B36: A0091 | C36: Lakeview County Government | Tax & Legal | advisory | D36: Tax & Legal | E36: Proposal | F36: 6763000 | G36: 50 | H36: 46308 | I36: 46358 | J36: 46263 | K36: U024 | L36: Thought leadership | O36: =IF(OR(E36="Closed Won",E36="Closed Lost"),0,1) -> 1 | P36: =INDEX(Accounts!$K$5:$K$336,MATCH(B36,Accounts!$A$5:$A$336,0)) -> Public Sector & Development | Q36: =INDEX(Accounts!$D$5:$D$336,MATCH(B36,Accounts!$A$5:$A$336,0)) -> Key | R36: =INDEX(Inputs!$B$11:$B$16,MATCH(E36,Inputs!$A$11:$A$16,0)) -> 50 | S36: =IF(F36="",0,F36)*R36/100 -> 3381500 | T36: =Inputs!$B$4-J36 -> 51 | U36: =IF(OR(F36="",F36=0),1,0) -> 0 | V36: =IF(K36="",1,0) -> 0 | W36: =IF(AND(O36=1,K36<>"",COUNTIFS(Owners!$A$5:$A$32,K36,Owners!$E$5:$E$32,"No")>0),1,0) -> 1 | X36: =IF(AND(O36=1,I36<Inputs!$B$4),1,0) -> 0 | Y36: =IF(AND(O36=1,T36>Inputs!$B$5),1,0) -> 0 | Z36: =IF(AND(O36=1,G36<>R36),1,0) -> 0 | AA36: =IF(AND(O36=1,M36=""),1,0) -> 1 | AB36: =IF(AND(E36="Closed Lost",N36=""),1,0) -> 0 | AC36: =SUM(U36:AB36) -> 2 | AD36: =IF(AC36=0,1,0) -> 0 | AE36: =IF(AND(O36=1,I36>=Inputs!$B$6,I36<=Inputs!$B$7),1,0) -> 1 | AF36: =IF(AND(E36="Closed Won",I36>=Inputs!$B$6,I36<=Inputs!$B$4),1,0) -> 0 | AG36: =IF(AND(O36=0,I36>Inputs!$B$4-Inputs!$B$8,I36<=Inputs!$B$4),1,0) -> 0 | AH36: =I36-H36 -> 50
A37: O00033 | B37: A0039 | C37: Baobab Power | Consulting | due diligence | D37: Consulting | E37: Closed Lost | F37: 26983000 | G37: 0 | H37: 46150 | I37: 46218 | J37: 46218 | K37: U002 | L37: Existing client | N37: No decision | O37: =IF(OR(E37="Closed Won",E37="Closed Lost"),0,1) -> 0 | P37: =INDEX(Accounts!$K$5:$K$336,MATCH(B37,Accounts!$A$5:$A$336,0)) -> Energy & Resources | Q37: =INDEX(Accounts!$D$5:$D$336,MATCH(B37,Accounts!$A$5:$A$336,0)) -> Priority | R37: =INDEX(Inputs!$B$11:$B$16,MATCH(E37,Inputs!$A$11:$A$16,0)) -> 0 | S37: =IF(F37="",0,F37)*R37/100 -> 0 | T37: =Inputs!$B$4-J37 -> 96 | U37: =IF(OR(F37="",F37=0),1,0) -> 0 | V37: =IF(K37="",1,0) -> 0 | W37: =IF(AND(O37=1,K37<>"",COUNTIFS(Owners!$A$5:$A$32,K37,Owners!$E$5:$E$32,"No")>0),1,0) -> 0 | X37: =IF(AND(O37=1,I37<Inputs!$B$4),1,0) -> 0 | Y37: =IF(AND(O37=1,T37>Inputs!$B$5),1,0) -> 0 | Z37: =IF(AND(O37=1,G37<>R37),1,0) -> 0 | AA37: =IF(AND(O37=1,M37=""),1,0) -> 0 | AB37: =IF(AND(E37="Closed Lost",N37=""),1,0) -> 0 | AC37: =SUM(U37:AB37) -> 0 | AD37: =IF(AC37=0,1,0) -> 1 | AE37: =IF(AND(O37=1,I37>=Inputs!$B$6,I37<=Inputs!$B$7),1,0) -> 0 | AF37: =IF(AND(E37="Closed Won",I37>=Inputs!$B$6,I37<=Inputs!$B$4),1,0) -> 0 | AG37: =IF(AND(O37=0,I37>Inputs!$B$4-Inputs!$B$8,I37<=Inputs!$B$4),1,0) -> 1 | AH37: =I37-H37 -> 68
A38: O00034 | B38: A0220 | C38: Pwani Power | Assurance | readiness | D38: Assurance | E38: Qualification | F38: 17249000 | G38: 25 | H38: 46212 | I38: 46553 | J38: 46296 | K38: U027 | L38: Thought leadership | M38: Partner meeting | O38: =IF(OR(E38="Closed Won",E38="Closed Lost"),0,1) -> 1 | P38: =INDEX(Accounts!$K$5:$K$336,MATCH(B38,Accounts!$A$5:$A$336,0)) -> Energy & Resources | Q38: =INDEX(Accounts!$D$5:$D$336,MATCH(B38,Accounts!$A$5:$A$336,0)) -> Standard | R38: =INDEX(Inputs!$B$11:$B$16,MATCH(E38,Inputs!$A$11:$A$16,0)) -> 25 | S38: =IF(F38="",0,F38)*R38/100 -> 4312250 | T38: =Inputs!$B$4-J38 -> 18 | U38: =IF(OR(F38="",F38=0),1,0) -> 0 | V38: =IF(K38="",1,0) -> 0 | W38: =IF(AND(O38=1,K38<>"",COUNTIFS(Owners!$A$5:$A$32,K38,Owners!$E$5:$E$32,"No")>0),1,0) -> 0 | X38: =IF(AND(O38=1,I38<Inputs!$B$4),1,0) -> 0 | Y38: =IF(AND(O38=1,T38>Inputs!$B$5),1,0) -> 0 | Z38: =IF(AND(O38=1,G38<>R38),1,0) -> 0 | AA38: =IF(AND(O38=1,M38=""),1,0) -> 0 | AB38: =IF(AND(E38="Closed Lost",N38=""),1,0) -> 0 | AC38: =SUM(U38:AB38) -> 0 | AD38: =IF(AC38=0,1,0) -> 1 | AE38: =IF(AND(O38=1,I38>=Inputs!$B$6,I38<=Inputs!$B$7),1,0) -> 1 | AF38: =IF(AND(E38="Closed Won",I38>=Inputs!$B$6,I38<=Inputs!$B$4),1,0) -> 0 | AG38: =IF(AND(O38=0,I38>Inputs!$B$4-Inputs!$B$8,I38<=Inputs!$B$4),1,0) -> 0 | AH38: =I38-H38 -> 341
A39: O00035 | B39: A0330 | C39: Acacia Hospital | Tax & Legal | compliance | D39: Tax & Legal | E39: Closed Lost | F39: 4727000 | G39: 0 | H39: 45939 | I39: 46153 | J39: 46153 | K39: U022 | L39: Event | N39: Price | O39: =IF(OR(E39="Closed Won",E39="Closed Lost"),0,1) -> 0 | P39: =INDEX(Accounts!$K$5:$K$336,MATCH(B39,Accounts!$A$5:$A$336,0)) -> Unassigned | Q39: =INDEX(Accounts!$D$5:$D$336,MATCH(B39,Accounts!$A$5:$A$336,0)) -> Standard | R39: =INDEX(Inputs!$B$11:$B$16,MATCH(E39,Inputs!$A$11:$A$16,0)) -> 0 | S39: =IF(F39="",0,F39)*R39/100 -> 0 | T39: =Inputs!$B$4-J39 -> 161 | U39: =IF(OR(F39="",F39=0),1,0) -> 0 | V39: =IF(K39="",1,0) -> 0 | W39: =IF(AND(O39=1,K39<>"",COUNTIFS(Owners!$A$5:$A$32,K39,Owners!$E$5:$E$32,"No")>0),1,0) -> 0 | X39: =IF(AND(O39=1,I39<Inputs!$B$4),1,0) -> 0 | Y39: =IF(AND(O39=1,T39>Inputs!$B$5),1,0) -> 0 | Z39: =IF(AND(O39=1,G39<>R39),1,0) -> 0 | AA39: =IF(AND(O39=1,M39=""),1,0) -> 0 | AB39: =IF(AND(E39="Closed Lost",N39=""),1,0) -> 0 | AC39: =SUM(U39:AB39) -> 0 | AD39: =IF(AC39=0,1,0) -> 1 | AE39: =IF(AND(O39=1,I39>=Inputs!$B$6,I39<=Inputs!$B$7),1,0) -> 0 | AF39: =IF(AND(E39="Closed Won",I39>=Inputs!$B$6,I39<=Inputs!$B$4),1,0) -> 0 | AG39: =IF(AND(O39=0,I39>Inputs!$B$4-Inputs!$B$8,I39<=Inputs!$B$4),1,0) -> 1 | AH39: =I39-H39 -> 214
A40: O00036 | B40: A0020 | C40: Baobab Infrastructure | Deals | compliance | D40: Deals | E40: Closed Lost | F40: 15525000 | G40: 0 | H40: 46066 | I40: 46191 | J40: 46191 | K40: U006 | L40: Existing client | O40: =IF(OR(E40="Closed Won",E40="Closed Lost"),0,1) -> 0 | P40: =INDEX(Accounts!$K$5:$K$336,MATCH(B40,Accounts!$A$5:$A$336,0)) -> Real Estate & Infrastructure | Q40: =INDEX(Accounts!$D$5:$D$336,MATCH(B40,Accounts!$A$5:$A$336,0)) -> Priority | R40: =INDEX(Inputs!$B$11:$B$16,MATCH(E40,Inputs!$A$11:$A$16,0)) -> 0 | S40: =IF(F40="",0,F40)*R40/100 -> 0 | T40: =Inputs!$B$4-J40 -> 123 | U40: =IF(OR(F40="",F40=0),1,0) -> 0 | V40: =IF(K40="",1,0) -> 0 | W40: =IF(AND(O40=1,K40<>"",COUNTIFS(Owners!$A$5:$A$32,K40,Owners!$E$5:$E$32,"No")>0),1,0) -> 0 | X40: =IF(AND(O40=1,I40<Inputs!$B$4),1,0) -> 0 | Y40: =IF(AND(O40=1,T40>Inputs!$B$5),1,0) -> 0 | Z40: =IF(AND(O40=1,G40<>R40),1,0) -> 0 | AA40: =IF(AND(O40=1,M40=""),1,0) -> 0 | AB40: =IF(AND(E40="Closed Lost",N40=""),1,0) -> 1 | AC40: =SUM(U40:AB40) -> 1 | AD40: =IF(AC40=0,1,0) -> 0 | AE40: =IF(AND(O40=1,I40>=Inputs!$B$6,I40<=Inputs!$B$7),1,0) -> 0 | AF40: =IF(AND(E40="Closed Won",I40>=Inputs!$B$6,I40<=Inputs!$B$4),1,0) -> 0 | AG40: =IF(AND(O40=0,I40>Inputs!$B$4-Inputs!$B$8,I40<=Inputs!$B$4),1,0) -> 1 | AH40: =I40-H40 -> 125
A41: O00037 | B41: A0086 | C41: Zuri Infrastructure | Tax & Legal | advisory | D41: Tax & Legal | E41: Prospecting | F41: 1191000 | G41: 0 | H41: 46223 | I41: 46296 | J41: 46274 | K41: U026 | L41: Event | M41: Follow-up call | O41: =IF(OR(E41="Closed Won",E41="Closed Lost"),0,1) -> 1 | P41: =INDEX(Accounts!$K$5:$K$336,MATCH(B41,Accounts!$A$5:$A$336,0)) -> Real Estate & Infrastructure | Q41: =INDEX(Accounts!$D$5:$D$336,MATCH(B41,Accounts!$A$5:$A$336,0)) -> Key | R41: =INDEX(Inputs!$B$11:$B$16,MATCH(E41,Inputs!$A$11:$A$16,0)) -> 10 | S41: =IF(F41="",0,F41)*R41/100 -> 119100 | T41: =Inputs!$B$4-J41 -> 40 | U41: =IF(OR(F41="",F41=0),1,0) -> 0 | V41: =IF(K41="",1,0) -> 0 | W41: =IF(AND(O41=1,K41<>"",COUNTIFS(Owners!$A$5:$A$32,K41,Owners!$E$5:$E$32,"No")>0),1,0) -> 0 | X41: =IF(AND(O41=1,I41<Inputs!$B$4),1,0) -> 1 | Y41: =IF(AND(O41=1,T41>Inputs!$B$5),1,0) -> 0 | Z41: =IF(AND(O41=1,G41<>R41),1,0) -> 1 | AA41: =IF(AND(O41=1,M41=""),1,0) -> 0 | AB41: =IF(AND(E41="Closed Lost",N41=""),1,0) -> 0 | AC41: =SUM(U41:AB41) -> 2 | AD41: =IF(AC41=0,1,0) -> 0 | AE41: =IF(AND(O41=1,I41>=Inputs!$B$6,I41<=Inputs!$B$7),1,0) -> 1 | AF41: =IF(AND(E41="Closed Won",I41>=Inputs!$B$6,I41<=Inputs!$B$4),1,0) -> 0 | AG41: =IF(AND(O41=0,I41>Inputs!$B$4-Inputs!$B$8,I41<=Inputs!$B$4),1,0) -> 0 | AH41: =I41-H41 -> 73
A42: O00038 | B42: A0017 | C42: Twiga Power | Deals | due diligence | D42: Deals | E42: Qualification | F42: 16864000 | G42: 25 | H42: 46150 | I42: 46305 | J42: 46220 | K42: U018 | L42: Thought leadership | M42: Pricing review | O42: =IF(OR(E42="Closed Won",E42="Closed Lost"),0,1) -> 1 | P42: =INDEX(Accounts!$K$5:$K$336,MATCH(B42,Accounts!$A$5:$A$336,0)) -> Energy & Resources | Q42: =INDEX(Accounts!$D$5:$D$336,MATCH(B42,Accounts!$A$5:$A$336,0)) -> Priority | R42: =INDEX(Inputs!$B$11:$B$16,MATCH(E42,Inputs!$A$11:$A$16,0)) -> 25 | S42: =IF(F42="",0,F42)*R42/100 -> 4216000 | T42: =Inputs!$B$4-J42 -> 94 | U42: =IF(OR(F42="",F42=0),1,0) -> 0 | V42: =IF(K42="",1,0) -> 0 | W42: =IF(AND(O42=1,K42<>"",COUNTIFS(Owners!$A$5:$A$32,K42,Owners!$E$5:$E$32,"No")>0),1,0) -> 0 | X42: =IF(AND(O42=1,I42<Inputs!$B$4),1,0) -> 1 | Y42: =IF(AND(O42=1,T42>Inputs!$B$5),1,0) -> 1 | Z42: =IF(AND(O42=1,G42<>R42),1,0) -> 0 | AA42: =IF(AND(O42=1,M42=""),1,0) -> 0 | AB42: =IF(AND(E42="Closed Lost",N42=""),1,0) -> 0 | AC42: =SUM(U42:AB42) -> 2 | AD42: =IF(AC42=0,1,0) -> 0 | AE42: =IF(AND(O42=1,I42>=Inputs!$B$6,I42<=Inputs!$B$7),1,0) -> 1 | AF42: =IF(AND(E42="Closed Won",I42>=Inputs!$B$6,I42<=Inputs!$B$4),1,0) -> 0 | AG42: =IF(AND(O42=0,I42>Inputs!$B$4-Inputs!$B$8,I42<=Inputs!$B$4),1,0) -> 0 | AH42: =I42-H42 -> 155
A43: O00039 | B43: A0083 | C43: Lakeview Foods | Tax & Legal | annual | D43: Tax & Legal | E43: Closed Lost | G43: 0 | H43: 45983 | I43: 46247 | J43: 46247 | K43: U020 | L43: Existing client | N43: No decision | O43: =IF(OR(E43="Closed Won",E43="Closed Lost"),0,1) -> 0 | P43: =INDEX(Accounts!$K$5:$K$336,MATCH(B43,Accounts!$A$5:$A$336,0)) -> Consumer & Retail | Q43: =INDEX(Accounts!$D$5:$D$336,MATCH(B43,Accounts!$A$5:$A$336,0)) -> Key | R43: =INDEX(Inputs!$B$11:$B$16,MATCH(E43,Inputs!$A$11:$A$16,0)) -> 0 | S43: =IF(F43="",0,F43)*R43/100 -> 0 | T43: =Inputs!$B$4-J43 -> 67 | U43: =IF(OR(F43="",F43=0),1,0) -> 1 | V43: =IF(K43="",1,0) -> 0 | W43: =IF(AND(O43=1,K43<>"",COUNTIFS(Owners!$A$5:$A$32,K43,Owners!$E$5:$E$32,"No")>0),1,0) -> 0 | X43: =IF(AND(O43=1,I43<Inputs!$B$4),1,0) -> 0 | Y43: =IF(AND(O43=1,T43>Inputs!$B$5),1,0) -> 0 | Z43: =IF(AND(O43=1,G43<>R43),1,0) -> 0 | AA43: =IF(AND(O43=1,M43=""),1,0) -> 0 | AB43: =IF(AND(E43="Closed Lost",N43=""),1,0) -> 0 | AC43: =SUM(U43:AB43) -> 1 | AD43: =IF(AC43=0,1,0) -> 0 | AE43: =IF(AND(O43=1,I43>=Inputs!$B$6,I43<=Inputs!$B$7),1,0) -> 0 | AF43: =IF(AND(E43="Closed Won",I43>=Inputs!$B$6,I43<=Inputs!$B$4),1,0) -> 0 | AG43: =IF(AND(O43=0,I43>Inputs!$B$4-Inputs!$B$8,I43<=Inputs!$B$4),1,0) -> 1 | AH43: =I43-H43 -> 264
A44: O00040 | B44: A0022 | C44: Savanna Sacco | Deals | annual | D44: Deals | E44: Closed Lost | F44: 67191000 | G44: 0 | H44: 46095 | I44: 46207 | J44: 46207 | K44: U001 | L44: Digital | N44: No decision | O44: =IF(OR(E44="Closed Won",E44="Closed Lost"),0,1) -> 0 | P44: =INDEX(Accounts!$K$5:$K$336,MATCH(B44,Accounts!$A$5:$A$336,0)) -> Financial Services | Q44: =INDEX(Accounts!$D$5:$D$336,MATCH(B44,Accounts!$A$5:$A$336,0)) -> Priority | R44: =INDEX(Inputs!$B$11:$B$16,MATCH(E44,Inputs!$A$11:$A$16,0)) -> 0 | S44: =IF(F44="",0,F44)*R44/100 -> 0 | T44: =Inputs!$B$4-J44 -> 107 | U44: =IF(OR(F44="",F44=0),1,0) -> 0 | V44: =IF(K44="",1,0) -> 0 | W44: =IF(AND(O44=1,K44<>"",COUNTIFS(Owners!$A$5:$A$32,K44,Owners!$E$5:$E$32,"No")>0),1,0) -> 0 | X44: =IF(AND(O44=1,I44<Inputs!$B$4),1,0) -> 0 | Y44: =IF(AND(O44=1,T44>Inputs!$B$5),1,0) -> 0 | Z44: =IF(AND(O44=1,G44<>R44),1,0) -> 0 | AA44: =IF(AND(O44=1,M44=""),1,0) -> 0 | AB44: =IF(AND(E44="Closed Lost",N44=""),1,0) -> 0 | AC44: =SUM(U44:AB44) -> 0 | AD44: =IF(AC44=0,1,0) -> 1 | AE44: =IF(AND(O44=1,I44>=Inputs!$B$6,I44<=Inputs!$B$7),1,0) -> 0 | AF44: =IF(AND(E44="Closed Won",I44>=Inputs!$B$6,I44<=Inputs!$B$4),1,0) -> 0 | AG44: =IF(AND(O44=0,I44>Inputs!$B$4-Inputs!$B$8,I44<=Inputs!$B$4),1,0) -> 1 | AH44: =I44-H44 -> 112
A45: O00041 | B45: A0039 | C45: Baobab Power | Consulting | annual | D45: Consulting | E45: Closed Lost | F45: 3101000 | G45: 0 | H45: 46157 | I45: 46293 | J45: 46293 | K45: U004 | L45: Referral | N45: Incumbent retained | O45: =IF(OR(E45="Closed Won",E45="Closed Lost"),0,1) -> 0 | P45: =INDEX(Accounts!$K$5:$K$336,MATCH(B45,Accounts!$A$5:$A$336,0)) -> Energy & Resources | Q45: =INDEX(Accounts!$D$5:$D$336,MATCH(B45,Accounts!$A$5:$A$336,0)) -> Priority | R45: =INDEX(Inputs!$B$11:$B$16,MATCH(E45,Inputs!$A$11:$A$16,0)) -> 0 | S45: =IF(F45="",0,F45)*R45/100 -> 0 | T45: =Inputs!$B$4-J45 -> 21 | U45: =IF(OR(F45="",F45=0),1,0) -> 0 | V45: =IF(K45="",1,0) -> 0 | W45: =IF(AND(O45=1,K45<>"",COUNTIFS(Owners!$A$5:$A$32,K45,Owners!$E$5:$E$32,"No")>0),1,0) -> 0 | X45: =IF(AND(O45=1,I45<Inputs!$B$4),1,0) -> 0 | Y45: =IF(AND(O45=1,T45>Inputs!$B$5),1,0) -> 0 | Z45: =IF(AND(O45=1,G45<>R45),1,0) -> 0 | AA45: =IF(AND(O45=1,M45=""),1,0) -> 0 | AB45: =IF(AND(E45="Closed Lost",N45=""),1,0) -> 0 | AC45: =SUM(U45:AB45) -> 0 | AD45: =IF(AC45=0,1,0) -> 1 | AE45: =IF(AND(O45=1,I45>=Inputs!$B$6,I45<=Inputs!$B$7),1,0) -> 0 | AF45: =IF(AND(E45="Closed Won",I45>=Inputs!$B$6,I45<=Inputs!$B$4),1,0) -> 0 | AG45: =IF(AND(O45=0,I45>Inputs!$B$4-Inputs!$B$8,I45<=Inputs!$B$4),1,0) -> 1 | AH45: =I45-H45 -> 136
A46: O00042 | B46: A0046 | C46: Nyota Telecom | Assurance | compliance | D46: Assurance | E46: Closed Lost | F46: 14007000 | G46: 0 | H46: 46154 | I46: 46311 | J46: 46311 | K46: U018 | L46: Existing client | N46: Scope change | O46: =IF(OR(E46="Closed Won",E46="Closed Lost"),0,1) -> 0 | P46: =INDEX(Accounts!$K$5:$K$336,MATCH(B46,Accounts!$A$5:$A$336,0)) -> Technology, Media & Telecom | Q46: =INDEX(Accounts!$D$5:$D$336,MATCH(B46,Accounts!$A$5:$A$336,0)) -> Key | R46: =INDEX(Inputs!$B$11:$B$16,MATCH(E46,Inputs!$A$11:$A$16,0)) -> 0 | S46: =IF(F46="",0,F46)*R46/100 -> 0 | T46: =Inputs!$B$4-J46 -> 3 | U46: =IF(OR(F46="",F46=0),1,0) -> 0 | V46: =IF(K46="",1,0) -> 0 | W46: =IF(AND(O46=1,K46<>"",COUNTIFS(Owners!$A$5:$A$32,K46,Owners!$E$5:$E$32,"No")>0),1,0) -> 0 | X46: =IF(AND(O46=1,I46<Inputs!$B$4),1,0) -> 0 | Y46: =IF(AND(O46=1,T46>Inputs!$B$5),1,0) -> 0 | Z46: =IF(AND(O46=1,G46<>R46),1,0) -> 0 | AA46: =IF(AND(O46=1,M46=""),1,0) -> 0 | AB46: =IF(AND(E46="Closed Lost",N46=""),1,0) -> 0 | AC46: =SUM(U46:AB46) -> 0 | AD46: =IF(AC46=0,1,0) -> 1 | AE46: =IF(AND(O46=1,I46>=Inputs!$B$6,I46<=Inputs!$B$7),1,0) -> 0 | AF46: =IF(AND(E46="Closed Won",I46>=Inputs!$B$6,I46<=Inputs!$B$4),1,0) -> 0 | AG46: =IF(AND(O46=0,I46>Inputs!$B$4-Inputs!$B$8,I46<=Inputs!$B$4),1,0) -> 1 | AH46: =I46-H46 -> 157
A47: O00043 | B47: A0203 | C47: Jambo Capital | Risk | advisory | D47: Risk | E47: Closed Won | F47: 8821000 | G47: 100 | H47: 46094 | I47: 46285 | J47: 46285 | K47: U024 | L47: Thought leadership | O47: =IF(OR(E47="Closed Won",E47="Closed Lost"),0,1) -> 0 | P47: =INDEX(Accounts!$K$5:$K$336,MATCH(B47,Accounts!$A$5:$A$336,0)) -> Financial Services | Q47: =INDEX(Accounts!$D$5:$D$336,MATCH(B47,Accounts!$A$5:$A$336,0)) -> Standard | R47: =INDEX(Inputs!$B$11:$B$16,MATCH(E47,Inputs!$A$11:$A$16,0)) -> 100 | S47: =IF(F47="",0,F47)*R47/100 -> 8821000 | T47: =Inputs!$B$4-J47 -> 29 | U47: =IF(OR(F47="",F47=0),1,0) -> 0 | V47: =IF(K47="",1,0) -> 0 | W47: =IF(AND(O47=1,K47<>"",COUNTIFS(Owners!$A$5:$A$32,K47,Owners!$E$5:$E$32,"No")>0),1,0) -> 0 | X47: =IF(AND(O47=1,I47<Inputs!$B$4),1,0) -> 0 | Y47: =IF(AND(O47=1,T47>Inputs!$B$5),1,0) -> 0 | Z47: =IF(AND(O47=1,G47<>R47),1,0) -> 0 | AA47: =IF(AND(O47=1,M47=""),1,0) -> 0 | AB47: =IF(AND(E47="Closed Lost",N47=""),1,0) -> 0 | AC47: =SUM(U47:AB47) -> 0 | AD47: =IF(AC47=0,1,0) -> 1 | AE47: =IF(AND(O47=1,I47>=Inputs!$B$6,I47<=Inputs!$B$7),1,0) -> 0 | AF47: =IF(AND(E47="Closed Won",I47>=Inputs!$B$6,I47<=Inputs!$B$4),1,0) -> 1 | AG47: =IF(AND(O47=0,I47>Inputs!$B$4-Inputs!$B$8,I47<=Inputs!$B$4),1,0) -> 1 | AH47: =I47-H47 -> 191
A48: O00044 | B48: A0095 | C48: Equator Supermarkets | Consulting | annual | D48: Consulting | E48: Closed Won | F48: 17551000 | G48: 100 | H48: 45977 | I48: 46137 | J48: 46137 | K48: U005 | L48: Cold outreach | O48: =IF(OR(E48="Closed Won",E48="Closed Lost"),0,1) -> 0 | P48: =INDEX(Accounts!$K$5:$K$336,MATCH(B48,Accounts!$A$5:$A$336,0)) -> Consumer & Retail | Q48: =INDEX(Accounts!$D$5:$D$336,MATCH(B48,Accounts!$A$5:$A$336,0)) -> Key | R48: =INDEX(Inputs!$B$11:$B$16,MATCH(E48,Inputs!$A$11:$A$16,0)) -> 100 | S48: =IF(F48="",0,F48)*R48/100 -> 17551000 | T48: =Inputs!$B$4-J48 -> 177 | U48: =IF(OR(F48="",F48=0),1,0) -> 0 | V48: =IF(K48="",1,0) -> 0 | W48: =IF(AND(O48=1,K48<>"",COUNTIFS(Owners!$A$5:$A$32,K48,Owners!$E$5:$E$32,"No")>0),1,0) -> 0 | X48: =IF(AND(O48=1,I48<Inputs!$B$4),1,0) -> 0 | Y48: =IF(AND(O48=1,T48>Inputs!$B$5),1,0) -> 0 | Z48: =IF(AND(O48=1,G48<>R48),1,0) -> 0 | AA48: =IF(AND(O48=1,M48=""),1,0) -> 0 | AB48: =IF(AND(E48="Closed Lost",N48=""),1,0) -> 0 | AC48: =SUM(U48:AB48) -> 0 | AD48: =IF(AC48=0,1,0) -> 1 | AE48: =IF(AND(O48=1,I48>=Inputs!$B$6,I48<=Inputs!$B$7),1,0) -> 0 | AF48: =IF(AND(E48="Closed Won",I48>=Inputs!$B$6,I48<=Inputs!$B$4),1,0) -> 0 | AG48: =IF(AND(O48=0,I48>Inputs!$B$4-Inputs!$B$8,I48<=Inputs!$B$4),1,0) -> 1 | AH48: =I48-H48 -> 160
A49: O00045 | B49: A0326 | C49: Savanna Power | Tax & Legal | support | D49: Tax & Legal | E49: Closed Won | F49: 12680000 | G49: 100 | H49: 46016 | I49: 46168 | J49: 46168 | K49: U004 | L49: Referral | O49: =IF(OR(E49="Closed Won",E49="Closed Lost"),0,1) -> 0 | P49: =INDEX(Accounts!$K$5:$K$336,MATCH(B49,Accounts!$A$5:$A$336,0)) -> Energy & Resources | Q49: =INDEX(Accounts!$D$5:$D$336,MATCH(B49,Accounts!$A$5:$A$336,0)) -> Standard | R49: =INDEX(Inputs!$B$11:$B$16,MATCH(E49,Inputs!$A$11:$A$16,0)) -> 100 | S49: =IF(F49="",0,F49)*R49/100 -> 12680000 | T49: =Inputs!$B$4-J49 -> 146 | U49: =IF(OR(F49="",F49=0),1,0) -> 0 | V49: =IF(K49="",1,0) -> 0 | W49: =IF(AND(O49=1,K49<>"",COUNTIFS(Owners!$A$5:$A$32,K49,Owners!$E$5:$E$32,"No")>0),1,0) -> 0 | X49: =IF(AND(O49=1,I49<Inputs!$B$4),1,0) -> 0 | Y49: =IF(AND(O49=1,T49>Inputs!$B$5),1,0) -> 0 | Z49: =IF(AND(O49=1,G49<>R49),1,0) -> 0 | AA49: =IF(AND(O49=1,M49=""),1,0) -> 0 | AB49: =IF(AND(E49="Closed Lost",N49=""),1,0) -> 0 | AC49: =SUM(U49:AB49) -> 0 | AD49: =IF(AC49=0,1,0) -> 1 | AE49: =IF(AND(O49=1,I49>=Inputs!$B$6,I49<=Inputs!$B$7),1,0) -> 0 | AF49: =IF(AND(E49="Closed Won",I49>=Inputs!$B$6,I49<=Inputs!$B$4),1,0) -> 0 | AG49: =IF(AND(O49=0,I49>Inputs!$B$4-Inputs!$B$8,I49<=Inputs!$B$4),1,0) -> 1 | AH49: =I49-H49 -> 152
A50: O00046 | B50: A0066 | C50: Pwani Hospital | Tax & Legal | transformation | D50: Tax & Legal | E50: Closed Lost | F50: 3387000 | G50: 0 | H50: 45985 | I50: 46282 | J50: 46282 | K50: U018 | L50: Existing client | N50: No decision | O50: =IF(OR(E50="Closed Won",E50="Closed Lost"),0,1) -> 0 | P50: =INDEX(Accounts!$K$5:$K$336,MATCH(B50,Accounts!$A$5:$A$336,0)) -> Health | Q50: =INDEX(Accounts!$D$5:$D$336,MATCH(B50,Accounts!$A$5:$A$336,0)) -> Key | R50: =INDEX(Inputs!$B$11:$B$16,MATCH(E50,Inputs!$A$11:$A$16,0)) -> 0 | S50: =IF(F50="",0,F50)*R50/100 -> 0 | T50: =Inputs!$B$4-J50 -> 32 | U50: =IF(OR(F50="",F50=0),1,0) -> 0 | V50: =IF(K50="",1,0) -> 0 | W50: =IF(AND(O50=1,K50<>"",COUNTIFS(Owners!$A$5:$A$32,K50,Owners!$E$5:$E$32,"No")>0),1,0) -> 0 | X50: =IF(AND(O50=1,I50<Inputs!$B$4),1,0) -> 0 | Y50: =IF(AND(O50=1,T50>Inputs!$B$5),1,0) -> 0 | Z50: =IF(AND(O50=1,G50<>R50),1,0) -> 0 | AA50: =IF(AND(O50=1,M50=""),1,0) -> 0 | AB50: =IF(AND(E50="Closed Lost",N50=""),1,0) -> 0 | AC50: =SUM(U50:AB50) -> 0 | AD50: =IF(AC50=0,1,0) -> 1 | AE50: =IF(AND(O50=1,I50>=Inputs!$B$6,I50<=Inputs!$B$7),1,0) -> 0 | AF50: =IF(AND(E50="Closed Won",I50>=Inputs!$B$6,I50<=Inputs!$B$4),1,0) -> 0 | AG50: =IF(AND(O50=0,I50>Inputs!$B$4-Inputs!$B$8,I50<=Inputs!$B$4),1,0) -> 1 | AH50: =I50-H50 -> 297
A51: O00047 | B51: A0031 | C51: Acacia Hospital | Tax & Legal | due diligence | D51: Tax & Legal | E51: Closed Lost | F51: 2468000 | G51: 0 | H51: 45911 | I51: 46183 | J51: 46183 | K51: U003 | L51: Digital | N51: Competitor | O51: =IF(OR(E51="Closed Won",E51="Closed Lost"),0,1) -> 0 | P51: =INDEX(Accounts!$K$5:$K$336,MATCH(B51,Accounts!$A$5:$A$336,0)) -> Unassigned | Q51: =INDEX(Accounts!$D$5:$D$336,MATCH(B51,Accounts!$A$5:$A$336,0)) -> Priority | R51: =INDEX(Inputs!$B$11:$B$16,MATCH(E51,Inputs!$A$11:$A$16,0)) -> 0 | S51: =IF(F51="",0,F51)*R51/100 -> 0 | T51: =Inputs!$B$4-J51 -> 131 | U51: =IF(OR(F51="",F51=0),1,0) -> 0 | V51: =IF(K51="",1,0) -> 0 | W51: =IF(AND(O51=1,K51<>"",COUNTIFS(Owners!$A$5:$A$32,K51,Owners!$E$5:$E$32,"No")>0),1,0) -> 0 | X51: =IF(AND(O51=1,I51<Inputs!$B$4),1,0) -> 0 | Y51: =IF(AND(O51=1,T51>Inputs!$B$5),1,0) -> 0 | Z51: =IF(AND(O51=1,G51<>R51),1,0) -> 0 | AA51: =IF(AND(O51=1,M51=""),1,0) -> 0 | AB51: =IF(AND(E51="Closed Lost",N51=""),1,0) -> 0 | AC51: =SUM(U51:AB51) -> 0 | AD51: =IF(AC51=0,1,0) -> 1 | AE51: =IF(AND(O51=1,I51>=Inputs!$B$6,I51<=Inputs!$B$7),1,0) -> 0 | AF51: =IF(AND(E51="Closed Won",I51>=Inputs!$B$6,I51<=Inputs!$B$4),1,0) -> 0 | AG51: =IF(AND(O51=0,I51>Inputs!$B$4-Inputs!$B$8,I51<=Inputs!$B$4),1,0) -> 1 | AH51: =I51-H51 -> 272
A52: O00048 | B52: A0255 | C52: Savanna Capital | Tax & Legal | support | D52: Tax & Legal | E52: Proposal | F52: 6729000 | G52: 50 | H52: 46078 | I52: 46299 | J52: 46283 | K52: U010 | L52: Digital | M52: Scope workshop | O52: =IF(OR(E52="Closed Won",E52="Closed Lost"),0,1) -> 1 | P52: =INDEX(Accounts!$K$5:$K$336,MATCH(B52,Accounts!$A$5:$A$336,0)) -> Unassigned | Q52: =INDEX(Accounts!$D$5:$D$336,MATCH(B52,Accounts!$A$5:$A$336,0)) -> Standard | R52: =INDEX(Inputs!$B$11:$B$16,MATCH(E52,Inputs!$A$11:$A$16,0)) -> 50 | S52: =IF(F52="",0,F52)*R52/100 -> 3364500 | T52: =Inputs!$B$4-J52 -> 31 | U52: =IF(OR(F52="",F52=0),1,0) -> 0 | V52: =IF(K52="",1,0) -> 0 | W52: =IF(AND(O52=1,K52<>"",COUNTIFS(Owners!$A$5:$A$32,K52,Owners!$E$5:$E$32,"No")>0),1,0) -> 0 | X52: =IF(AND(O52=1,I52<Inputs!$B$4),1,0) -> 1 | Y52: =IF(AND(O52=1,T52>Inputs!$B$5),1,0) -> 0 | Z52: =IF(AND(O52=1,G52<>R52),1,0) -> 0 | AA52: =IF(AND(O52=1,M52=""),1,0) -> 0 | AB52: =IF(AND(E52="Closed Lost",N52=""),1,0) -> 0 | AC52: =SUM(U52:AB52) -> 1 | AD52: =IF(AC52=0,1,0) -> 0 | AE52: =IF(AND(O52=1,I52>=Inputs!$B$6,I52<=Inputs!$B$7),1,0) -> 1 | AF52: =IF(AND(E52="Closed Won",I52>=Inputs!$B$6,I52<=Inputs!$B$4),1,0) -> 0 | AG52: =IF(AND(O52=0,I52>Inputs!$B$4-Inputs!$B$8,I52<=Inputs!$B$4),1,0) -> 0 | AH52: =I52-H52 -> 221
A53: O00049 | B53: A0164 | C53: Highland Development Fund | Assurance | review | D53: Assurance | E53: Closed Won | F53: 8504000 | G53: 100 | H53: 45994 | I53: 46202 | J53: 46202 | K53: U019 | L53: Referral | O53: =IF(OR(E53="Closed Won",E53="Closed Lost"),0,1) -> 0 | P53: =INDEX(Accounts!$K$5:$K$336,MATCH(B53,Accounts!$A$5:$A$336,0)) -> Public Sector & Development | Q53: =INDEX(Accounts!$D$5:$D$336,MATCH(B53,Accounts!$A$5:$A$336,0)) -> Standard | R53: =INDEX(Inputs!$B$11:$B$16,MATCH(E53,Inputs!$A$11:$A$16,0)) -> 100 | S53: =IF(F53="",0,F53)*R53/100 -> 8504000 | T53: =Inputs!$B$4-J53 -> 112 | U53: =IF(OR(F53="",F53=0),1,0) -> 0 | V53: =IF(K53="",1,0) -> 0 | W53: =IF(AND(O53=1,K53<>"",COUNTIFS(Owners!$A$5:$A$32,K53,Owners!$E$5:$E$32,"No")>0),1,0) -> 0 | X53: =IF(AND(O53=1,I53<Inputs!$B$4),1,0) -> 0 | Y53: =IF(AND(O53=1,T53>Inputs!$B$5),1,0) -> 0 | Z53: =IF(AND(O53=1,G53<>R53),1,0) -> 0 | AA53: =IF(AND(O53=1,M53=""),1,0) -> 0 | AB53: =IF(AND(E53="Closed Lost",N53=""),1,0) -> 0 | AC53: =SUM(U53:AB53) -> 0 | AD53: =IF(AC53=0,1,0) -> 1 | AE53: =IF(AND(O53=1,I53>=Inputs!$B$6,I53<=Inputs!$B$7),1,0) -> 0 | AF53: =IF(AND(E53="Closed Won",I53>=Inputs!$B$6,I53<=Inputs!$B$4),1,0) -> 0 | AG53: =IF(AND(O53=0,I53>Inputs!$B$4-Inputs!$B$8,I53<=Inputs!$B$4),1,0) -> 1 | AH53: =I53-H53 -> 208
A54: O00050 | B54: A0036 | C54: Amani Authority | Assurance | transformation | D54: Assurance | E54: Closed Lost | F54: 3229000 | G54: 0 | H54: 46052 | I54: 46278 | J54: 46278 | K54: U001 | L54: Cold outreach | N54: Independence conflict | O54: =IF(OR(E54="Closed Won",E54="Closed Lost"),0,1) -> 0 | P54: =INDEX(Accounts!$K$5:$K$336,MATCH(B54,Accounts!$A$5:$A$336,0)) -> Public Sector & Development | Q54: =INDEX(Accounts!$D$5:$D$336,MATCH(B54,Accounts!$A$5:$A$336,0)) -> Priority | R54: =INDEX(Inputs!$B$11:$B$16,MATCH(E54,Inputs!$A$11:$A$16,0)) -> 0 | S54: =IF(F54="",0,F54)*R54/100 -> 0 | T54: =Inputs!$B$4-J54 -> 36 | U54: =IF(OR(F54="",F54=0),1,0) -> 0 | V54: =IF(K54="",1,0) -> 0 | W54: =IF(AND(O54=1,K54<>"",COUNTIFS(Owners!$A$5:$A$32,K54,Owners!$E$5:$E$32,"No")>0),1,0) -> 0 | X54: =IF(AND(O54=1,I54<Inputs!$B$4),1,0) -> 0 | Y54: =IF(AND(O54=1,T54>Inputs!$B$5),1,0) -> 0 | Z54: =IF(AND(O54=1,G54<>R54),1,0) -> 0 | AA54: =IF(AND(O54=1,M54=""),1,0) -> 0 | AB54: =IF(AND(E54="Closed Lost",N54=""),1,0) -> 0 | AC54: =SUM(U54:AB54) -> 0 | AD54: =IF(AC54=0,1,0) -> 1 | AE54: =IF(AND(O54=1,I54>=Inputs!$B$6,I54<=Inputs!$B$7),1,0) -> 0 | AF54: =IF(AND(E54="Closed Won",I54>=Inputs!$B$6,I54<=Inputs!$B$4),1,0) -> 0 | AG54: =IF(AND(O54=0,I54>Inputs!$B$4-Inputs!$B$8,I54<=Inputs!$B$4),1,0) -> 1 | AH54: =I54-H54 -> 226
A55: O00051 | B55: A0030 | C55: Nile Networks | Tax & Legal | transformation | D55: Tax & Legal | E55: Qualification | F55: 1534000 | G55: 25 | H55: 46306 | I55: 46321 | J55: 46289 | K55: U002 | L55: Event | M55: Await tender outcome | O55: =IF(OR(E55="Closed Won",E55="Closed Lost"),0,1) -> 1 | P55: =INDEX(Accounts!$K$5:$K$336,MATCH(B55,Accounts!$A$5:$A$336,0)) -> Technology, Media & Telecom | Q55: =INDEX(Accounts!$D$5:$D$336,MATCH(B55,Accounts!$A$5:$A$336,0)) -> Priority | R55: =INDEX(Inputs!$B$11:$B$16,MATCH(E55,Inputs!$A$11:$A$16,0)) -> 25 | S55: =IF(F55="",0,F55)*R55/100 -> 383500 | T55: =Inputs!$B$4-J55 -> 25 | U55: =IF(OR(F55="",F55=0),1,0) -> 0 | V55: =IF(K55="",1,0) -> 0 | W55: =IF(AND(O55=1,K55<>"",COUNTIFS(Owners!$A$5:$A$32,K55,Owners!$E$5:$E$32,"No")>0),1,0) -> 0 | X55: =IF(AND(O55=1,I55<Inputs!$B$4),1,0) -> 0 | Y55: =IF(AND(O55=1,T55>Inputs!$B$5),1,0) -> 0 | Z55: =IF(AND(O55=1,G55<>R55),1,0) -> 0 | AA55: =IF(AND(O55=1,M55=""),1,0) -> 0 | AB55: =IF(AND(E55="Closed Lost",N55=""),1,0) -> 0 | AC55: =SUM(U55:AB55) -> 0 | AD55: =IF(AC55=0,1,0) -> 1 | AE55: =IF(AND(O55=1,I55>=Inputs!$B$6,I55<=Inputs!$B$7),1,0) -> 1 | AF55: =IF(AND(E55="Closed Won",I55>=Inputs!$B$6,I55<=Inputs!$B$4),1,0) -> 0 | AG55: =IF(AND(O55=0,I55>Inputs!$B$4-Inputs!$B$8,I55<=Inputs!$B$4),1,0) -> 0 | AH55: =I55-H55 -> 15
A56: O00052 | B56: A0166 | C56: Harambee Foundation | Assurance | due diligence | D56: Assurance | E56: Closed Lost | F56: 17284000 | G56: 0 | H56: 45965 | I56: 46124 | J56: 46124 | K56: U016 | L56: Referral | N56: Independence conflict | O56: =IF(OR(E56="Closed Won",E56="Closed Lost"),0,1) -> 0 | P56: =INDEX(Accounts!$K$5:$K$336,MATCH(B56,Accounts!$A$5:$A$336,0)) -> Public Sector & Development | Q56: =INDEX(Accounts!$D$5:$D$336,MATCH(B56,Accounts!$A$5:$A$336,0)) -> Standard | R56: =INDEX(Inputs!$B$11:$B$16,MATCH(E56,Inputs!$A$11:$A$16,0)) -> 0 | S56: =IF(F56="",0,F56)*R56/100 -> 0 | T56: =Inputs!$B$4-J56 -> 190 | U56: =IF(OR(F56="",F56=0),1,0) -> 0 | V56: =IF(K56="",1,0) -> 0 | W56: =IF(AND(O56=1,K56<>"",COUNTIFS(Owners!$A$5:$A$32,K56,Owners!$E$5:$E$32,"No")>0),1,0) -> 0 | X56: =IF(AND(O56=1,I56<Inputs!$B$4),1,0) -> 0 | Y56: =IF(AND(O56=1,T56>Inputs!$B$5),1,0) -> 0 | Z56: =IF(AND(O56=1,G56<>R56),1,0) -> 0 | AA56: =IF(AND(O56=1,M56=""),1,0) -> 0 | AB56: =IF(AND(E56="Closed Lost",N56=""),1,0) -> 0 | AC56: =SUM(U56:AB56) -> 0 | AD56: =IF(AC56=0,1,0) -> 1 | AE56: =IF(AND(O56=1,I56>=Inputs!$B$6,I56<=Inputs!$B$7),1,0) -> 0 | AF56: =IF(AND(E56="Closed Won",I56>=Inputs!$B$6,I56<=Inputs!$B$4),1,0) -> 0 | AG56: =IF(AND(O56=0,I56>Inputs!$B$4-Inputs!$B$8,I56<=Inputs!$B$4),1,0) -> 1 | AH56: =I56-H56 -> 159
A57: O00053 | B57: A0203 | C57: Jambo Capital | Deals | readiness | D57: Deals | E57: Closed Won | G57: 100 | H57: 46015 | I57: 46086 | J57: 46086 | K57: U023 | L57: Cold outreach | O57: =IF(OR(E57="Closed Won",E57="Closed Lost"),0,1) -> 0 | P57: =INDEX(Accounts!$K$5:$K$336,MATCH(B57,Accounts!$A$5:$A$336,0)) -> Financial Services | Q57: =INDEX(Accounts!$D$5:$D$336,MATCH(B57,Accounts!$A$5:$A$336,0)) -> Standard | R57: =INDEX(Inputs!$B$11:$B$16,MATCH(E57,Inputs!$A$11:$A$16,0)) -> 100 | S57: =IF(F57="",0,F57)*R57/100 -> 0 | T57: =Inputs!$B$4-J57 -> 228 | U57: =IF(OR(F57="",F57=0),1,0) -> 1 | V57: =IF(K57="",1,0) -> 0 | W57: =IF(AND(O57=1,K57<>"",COUNTIFS(Owners!$A$5:$A$32,K57,Owners!$E$5:$E$32,"No")>0),1,0) -> 0 | X57: =IF(AND(O57=1,I57<Inputs!$B$4),1,0) -> 0 | Y57: =IF(AND(O57=1,T57>Inputs!$B$5),1,0) -> 0 | Z57: =IF(AND(O57=1,G57<>R57),1,0) -> 0 | AA57: =IF(AND(O57=1,M57=""),1,0) -> 0 | AB57: =IF(AND(E57="Closed Lost",N57=""),1,0) -> 0 | AC57: =SUM(U57:AB57) -> 1 | AD57: =IF(AC57=0,1,0) -> 0 | AE57: =IF(AND(O57=1,I57>=Inputs!$B$6,I57<=Inputs!$B$7),1,0) -> 0 | AF57: =IF(AND(E57="Closed Won",I57>=Inputs!$B$6,I57<=Inputs!$B$4),1,0) -> 0 | AG57: =IF(AND(O57=0,I57>Inputs!$B$4-Inputs!$B$8,I57<=Inputs!$B$4),1,0) -> 1 | AH57: =I57-H57 -> 71
A58: O00054 | B58: A0111 | C58: Equator Petroleum | Deals | transformation | D58: Deals | E58: Proposal | F58: 13035000 | G58: 90 | H58: 46271 | I58: 46284 | J58: 46299 | K58: U009 | L58: Cold outreach | M58: Pricing review | O58: =IF(OR(E58="Closed Won",E58="Closed Lost"),0,1) -> 1 | P58: =INDEX(Accounts!$K$5:$K$336,MATCH(B58,Accounts!$A$5:$A$336,0)) -> Energy & Resources | Q58: =INDEX(Accounts!$D$5:$D$336,MATCH(B58,Accounts!$A$5:$A$336,0)) -> Standard | R58: =INDEX(Inputs!$B$11:$B$16,MATCH(E58,Inputs!$A$11:$A$16,0)) -> 50 | S58: =IF(F58="",0,F58)*R58/100 -> 6517500 | T58: =Inputs!$B$4-J58 -> 15 | U58: =IF(OR(F58="",F58=0),1,0) -> 0 | V58: =IF(K58="",1,0) -> 0 | W58: =IF(AND(O58=1,K58<>"",COUNTIFS(Owners!$A$5:$A$32,K58,Owners!$E$5:$E$32,"No")>0),1,0) -> 0 | X58: =IF(AND(O58=1,I58<Inputs!$B$4),1,0) -> 1 | Y58: =IF(AND(O58=1,T58>Inputs!$B$5),1,0) -> 0 | Z58: =IF(AND(O58=1,G58<>R58),1,0) -> 1 | AA58: =IF(AND(O58=1,M58=""),1,0) -> 0 | AB58: =IF(AND(E58="Closed Lost",N58=""),1,0) -> 0 | AC58: =SUM(U58:AB58) -> 2 | AD58: =IF(AC58=0,1,0) -> 0 | AE58: =IF(AND(O58=1,I58>=Inputs!$B$6,I58<=Inputs!$B$7),1,0) -> 1 | AF58: =IF(AND(E58="Closed Won",I58>=Inputs!$B$6,I58<=Inputs!$B$4),1,0) -> 0 | AG58: =IF(AND(O58=0,I58>Inputs!$B$4-Inputs!$B$8,I58<=Inputs!$B$4),1,0) -> 0 | AH58: =I58-H58 -> 13
A59: O00055 | B59: A0049 | C59: Baobab Agri | Tax & Legal | annual | D59: Tax & Legal | E59: Negotiation | F59: 1880000 | G59: 75 | H59: 46262 | I59: 46471 | J59: 46263 | K59: U008 | L59: Event | O59: =IF(OR(E59="Closed Won",E59="Closed Lost"),0,1) -> 1 | P59: =INDEX(Accounts!$K$5:$K$336,MATCH(B59,Accounts!$A$5:$A$336,0)) -> Agribusiness | Q59: =INDEX(Accounts!$D$5:$D$336,MATCH(B59,Accounts!$A$5:$A$336,0)) -> Key | R59: =INDEX(Inputs!$B$11:$B$16,MATCH(E59,Inputs!$A$11:$A$16,0)) -> 75 | S59: =IF(F59="",0,F59)*R59/100 -> 1410000 | T59: =Inputs!$B$4-J59 -> 51 | U59: =IF(OR(F59="",F59=0),1,0) -> 0 | V59: =IF(K59="",1,0) -> 0 | W59: =IF(AND(O59=1,K59<>"",COUNTIFS(Owners!$A$5:$A$32,K59,Owners!$E$5:$E$32,"No")>0),1,0) -> 0 | X59: =IF(AND(O59=1,I59<Inputs!$B$4),1,0) -> 0 | Y59: =IF(AND(O59=1,T59>Inputs!$B$5),1,0) -> 0 | Z59: =IF(AND(O59=1,G59<>R59),1,0) -> 0 | AA59: =IF(AND(O59=1,M59=""),1,0) -> 1 | AB59: =IF(AND(E59="Closed Lost",N59=""),1,0) -> 0 | AC59: =SUM(U59:AB59) -> 1 | AD59: =IF(AC59=0,1,0) -> 0 | AE59: =IF(AND(O59=1,I59>=Inputs!$B$6,I59<=Inputs!$B$7),1,0) -> 1 | AF59: =IF(AND(E59="Closed Won",I59>=Inputs!$B$6,I59<=Inputs!$B$4),1,0) -> 0 | AG59: =IF(AND(O59=0,I59>Inputs!$B$4-Inputs!$B$8,I59<=Inputs!$B$4),1,0) -> 0 | AH59: =I59-H59 -> 209
A60: O00056 | B60: A0026 | C60: Lakeview Development Fund | Assurance | compliance | D60: Assurance | E60: Qualification | F60: 5656000 | G60: 25 | H60: 46302 | I60: 46382 | J60: 46173 | L60: Referral | O60: =IF(OR(E60="Closed Won",E60="Closed Lost"),0,1) -> 1 | P60: =INDEX(Accounts!$K$5:$K$336,MATCH(B60,Accounts!$A$5:$A$336,0)) -> Public Sector & Development | Q60: =INDEX(Accounts!$D$5:$D$336,MATCH(B60,Accounts!$A$5:$A$336,0)) -> Priority | R60: =INDEX(Inputs!$B$11:$B$16,MATCH(E60,Inputs!$A$11:$A$16,0)) -> 25 | S60: =IF(F60="",0,F60)*R60/100 -> 1414000 | T60: =Inputs!$B$4-J60 -> 141 | U60: =IF(OR(F60="",F60=0),1,0) -> 0 | V60: =IF(K60="",1,0) -> 1 | W60: =IF(AND(O60=1,K60<>"",COUNTIFS(Owners!$A$5:$A$32,K60,Owners!$E$5:$E$32,"No")>0),1,0) -> 0 | X60: =IF(AND(O60=1,I60<Inputs!$B$4),1,0) -> 0 | Y60: =IF(AND(O60=1,T60>Inputs!$B$5),1,0) -> 1 | Z60: =IF(AND(O60=1,G60<>R60),1,0) -> 0 | AA60: =IF(AND(O60=1,M60=""),1,0) -> 1 | AB60: =IF(AND(E60="Closed Lost",N60=""),1,0) -> 0 | AC60: =SUM(U60:AB60) -> 3 | AD60: =IF(AC60=0,1,0) -> 0 | AE60: =IF(AND(O60=1,I60>=Inputs!$B$6,I60<=Inputs!$B$7),1,0) -> 1 | AF60: =IF(AND(E60="Closed Won",I60>=Inputs!$B$6,I60<=Inputs!$B$4),1,0) -> 0 | AG60: =IF(AND(O60=0,I60>Inputs!$B$4-Inputs!$B$8,I60<=Inputs!$B$4),1,0) -> 0 | AH60: =I60-H60 -> 80
A61: O00057 | B61: A0015 | C61: Baobab Energy | Tax & Legal | advisory | D61: Tax & Legal | E61: Qualification | F61: 2932000 | G61: 25 | H61: 46236 | I61: 46277 | J61: 46270 | K61: U001 | L61: Cold outreach | M61: Scope workshop | O61: =IF(OR(E61="Closed Won",E61="Closed Lost"),0,1) -> 1 | P61: =INDEX(Accounts!$K$5:$K$336,MATCH(B61,Accounts!$A$5:$A$336,0)) -> Energy & Resources | Q61: =INDEX(Accounts!$D$5:$D$336,MATCH(B61,Accounts!$A$5:$A$336,0)) -> Priority | R61: =INDEX(Inputs!$B$11:$B$16,MATCH(E61,Inputs!$A$11:$A$16,0)) -> 25 | S61: =IF(F61="",0,F61)*R61/100 -> 733000 | T61: =Inputs!$B$4-J61 -> 44 | U61: =IF(OR(F61="",F61=0),1,0) -> 0 | V61: =IF(K61="",1,0) -> 0 | W61: =IF(AND(O61=1,K61<>"",COUNTIFS(Owners!$A$5:$A$32,K61,Owners!$E$5:$E$32,"No")>0),1,0) -> 0 | X61: =IF(AND(O61=1,I61<Inputs!$B$4),1,0) -> 1 | Y61: =IF(AND(O61=1,T61>Inputs!$B$5),1,0) -> 0 | Z61: =IF(AND(O61=1,G61<>R61),1,0) -> 0 | AA61: =IF(AND(O61=1,M61=""),1,0) -> 0 | AB61: =IF(AND(E61="Closed Lost",N61=""),1,0) -> 0 | AC61: =SUM(U61:AB61) -> 1 | AD61: =IF(AC61=0,1,0) -> 0 | AE61: =IF(AND(O61=1,I61>=Inputs!$B$6,I61<=Inputs!$B$7),1,0) -> 1 | AF61: =IF(AND(E61="Closed Won",I61>=Inputs!$B$6,I61<=Inputs!$B$4),1,0) -> 0 | AG61: =IF(AND(O61=0,I61>Inputs!$B$4-Inputs!$B$8,I61<=Inputs!$B$4),1,0) -> 0 | AH61: =I61-H61 -> 41
A62: O00058 | B62: A0040 | C62: Amani Insurance | Tax & Legal | compliance | D62: Tax & Legal | E62: Qualification | F62: 18156000 | G62: 25 | H62: 46269 | I62: 46413 | J62: 46282 | K62: U005 | L62: Existing client | M62: Await tender outcome | O62: =IF(OR(E62="Closed Won",E62="Closed Lost"),0,1) -> 1 | P62: =INDEX(Accounts!$K$5:$K$336,MATCH(B62,Accounts!$A$5:$A$336,0)) -> Financial Services | Q62: =INDEX(Accounts!$D$5:$D$336,MATCH(B62,Accounts!$A$5:$A$336,0)) -> Priority | R62: =INDEX(Inputs!$B$11:$B$16,MATCH(E62,Inputs!$A$11:$A$16,0)) -> 25 | S62: =IF(F62="",0,F62)*R62/100 -> 4539000 | T62: =Inputs!$B$4-J62 -> 32 | U62: =IF(OR(F62="",F62=0),1,0) -> 0 | V62: =IF(K62="",1,0) -> 0 | W62: =IF(AND(O62=1,K62<>"",COUNTIFS(Owners!$A$5:$A$32,K62,Owners!$E$5:$E$32,"No")>0),1,0) -> 0 | X62: =IF(AND(O62=1,I62<Inputs!$B$4),1,0) -> 0 | Y62: =IF(AND(O62=1,T62>Inputs!$B$5),1,0) -> 0 | Z62: =IF(AND(O62=1,G62<>R62),1,0) -> 0 | AA62: =IF(AND(O62=1,M62=""),1,0) -> 0 | AB62: =IF(AND(E62="Closed Lost",N62=""),1,0) -> 0 | AC62: =SUM(U62:AB62) -> 0 | AD62: =IF(AC62=0,1,0) -> 1 | AE62: =IF(AND(O62=1,I62>=Inputs!$B$6,I62<=Inputs!$B$7),1,0) -> 1 | AF62: =IF(AND(E62="Closed Won",I62>=Inputs!$B$6,I62<=Inputs!$B$4),1,0) -> 0 | AG62: =IF(AND(O62=0,I62>Inputs!$B$4-Inputs!$B$8,I62<=Inputs!$B$4),1,0) -> 0 | AH62: =I62-H62 -> 144
A63: O00059 | B63: A0014 | C63: Jua Beverages | Consulting | compliance | D63: Consulting | E63: Prospecting | F63: 6075000 | G63: 10 | H63: 46151 | I63: 46439 | J63: 46280 | K63: U007 | L63: Referral | M63: Partner meeting | O63: =IF(OR(E63="Closed Won",E63="Closed Lost"),0,1) -> 1 | P63: =INDEX(Accounts!$K$5:$K$336,MATCH(B63,Accounts!$A$5:$A$336,0)) -> Consumer & Retail | Q63: =INDEX(Accounts!$D$5:$D$336,MATCH(B63,Accounts!$A$5:$A$336,0)) -> Priority | R63: =INDEX(Inputs!$B$11:$B$16,MATCH(E63,Inputs!$A$11:$A$16,0)) -> 10 | S63: =IF(F63="",0,F63)*R63/100 -> 607500 | T63: =Inputs!$B$4-J63 -> 34 | U63: =IF(OR(F63="",F63=0),1,0) -> 0 | V63: =IF(K63="",1,0) -> 0 | W63: =IF(AND(O63=1,K63<>"",COUNTIFS(Owners!$A$5:$A$32,K63,Owners!$E$5:$E$32,"No")>0),1,0) -> 0 | X63: =IF(AND(O63=1,I63<Inputs!$B$4),1,0) -> 0 | Y63: =IF(AND(O63=1,T63>Inputs!$B$5),1,0) -> 0 | Z63: =IF(AND(O63=1,G63<>R63),1,0) -> 0 | AA63: =IF(AND(O63=1,M63=""),1,0) -> 0 | AB63: =IF(AND(E63="Closed Lost",N63=""),1,0) -> 0 | AC63: =SUM(U63:AB63) -> 0 | AD63: =IF(AC63=0,1,0) -> 1 | AE63: =IF(AND(O63=1,I63>=Inputs!$B$6,I63<=Inputs!$B$7),1,0) -> 1 | AF63: =IF(AND(E63="Closed Won",I63>=Inputs!$B$6,I63<=Inputs!$B$4),1,0) -> 0 | AG63: =IF(AND(O63=0,I63>Inputs!$B$4-Inputs!$B$8,I63<=Inputs!$B$4),1,0) -> 0 | AH63: =I63-H63 -> 288
A64: O00060 | B64: A0107 | C64: Highland Supermarkets | Assurance | compliance | D64: Assurance | E64: Closed Lost | F64: 39589000 | G64: 0 | H64: 45933 | I64: 46126 | J64: 46126 | K64: U011 | L64: Existing client | N64: Scope change | O64: =IF(OR(E64="Closed Won",E64="Closed Lost"),0,1) -> 0 | P64: =INDEX(Accounts!$K$5:$K$336,MATCH(B64,Accounts!$A$5:$A$336,0)) -> Consumer & Retail | Q64: =INDEX(Accounts!$D$5:$D$336,MATCH(B64,Accounts!$A$5:$A$336,0)) -> Key | R64: =INDEX(Inputs!$B$11:$B$16,MATCH(E64,Inputs!$A$11:$A$16,0)) -> 0 | S64: =IF(F64="",0,F64)*R64/100 -> 0 | T64: =Inputs!$B$4-J64 -> 188 | U64: =IF(OR(F64="",F64=0),1,0) -> 0 | V64: =IF(K64="",1,0) -> 0 | W64: =IF(AND(O64=1,K64<>"",COUNTIFS(Owners!$A$5:$A$32,K64,Owners!$E$5:$E$32,"No")>0),1,0) -> 0 | X64: =IF(AND(O64=1,I64<Inputs!$B$4),1,0) -> 0 | Y64: =IF(AND(O64=1,T64>Inputs!$B$5),1,0) -> 0 | Z64: =IF(AND(O64=1,G64<>R64),1,0) -> 0 | AA64: =IF(AND(O64=1,M64=""),1,0) -> 0 | AB64: =IF(AND(E64="Closed Lost",N64=""),1,0) -> 0 | AC64: =SUM(U64:AB64) -> 0 | AD64: =IF(AC64=0,1,0) -> 1 | AE64: =IF(AND(O64=1,I64>=Inputs!$B$6,I64<=Inputs!$B$7),1,0) -> 0 | AF64: =IF(AND(E64="Closed Won",I64>=Inputs!$B$6,I64<=Inputs!$B$4),1,0) -> 0 | AG64: =IF(AND(O64=0,I64>Inputs!$B$4-Inputs!$B$8,I64<=Inputs!$B$4),1,0) -> 1 | AH64: =I64-H64 -> 193
A65: O00061 | B65: A0107 | C65: Highland Supermarkets | Risk | review | D65: Risk | E65: Proposal | F65: 6477000 | G65: 50 | H65: 46184 | I65: 46468 | J65: 46279 | K65: U011 | L65: Cold outreach | M65: Pricing review | O65: =IF(OR(E65="Closed Won",E65="Closed Lost"),0,1) -> 1 | P65: =INDEX(Accounts!$K$5:$K$336,MATCH(B65,Accounts!$A$5:$A$336,0)) -> Consumer & Retail | Q65: =INDEX(Accounts!$D$5:$D$336,MATCH(B65,Accounts!$A$5:$A$336,0)) -> Key | R65: =INDEX(Inputs!$B$11:$B$16,MATCH(E65,Inputs!$A$11:$A$16,0)) -> 50 | S65: =IF(F65="",0,F65)*R65/100 -> 3238500 | T65: =Inputs!$B$4-J65 -> 35 | U65: =IF(OR(F65="",F65=0),1,0) -> 0 | V65: =IF(K65="",1,0) -> 0 | W65: =IF(AND(O65=1,K65<>"",COUNTIFS(Owners!$A$5:$A$32,K65,Owners!$E$5:$E$32,"No")>0),1,0) -> 0 | X65: =IF(AND(O65=1,I65<Inputs!$B$4),1,0) -> 0 | Y65: =IF(AND(O65=1,T65>Inputs!$B$5),1,0) -> 0 | Z65: =IF(AND(O65=1,G65<>R65),1,0) -> 0 | AA65: =IF(AND(O65=1,M65=""),1,0) -> 0 | AB65: =IF(AND(E65="Closed Lost",N65=""),1,0) -> 0 | AC65: =SUM(U65:AB65) -> 0 | AD65: =IF(AC65=0,1,0) -> 1 | AE65: =IF(AND(O65=1,I65>=Inputs!$B$6,I65<=Inputs!$B$7),1,0) -> 1 | AF65: =IF(AND(E65="Closed Won",I65>=Inputs!$B$6,I65<=Inputs!$B$4),1,0) -> 0 | AG65: =IF(AND(O65=0,I65>Inputs!$B$4-Inputs!$B$8,I65<=Inputs!$B$4),1,0) -> 0 | AH65: =I65-H65 -> 284
A66: O00062 | B66: A0042 | C66: Amani Media | Assurance | compliance | D66: Assurance | E66: Closed Lost | F66: 4294000 | G66: 0 | H66: 45954 | I66: 46211 | J66: 46211 | K66: U016 | L66: Existing client | N66: Scope change | O66: =IF(OR(E66="Closed Won",E66="Closed Lost"),0,1) -> 0 | P66: =INDEX(Accounts!$K$5:$K$336,MATCH(B66,Accounts!$A$5:$A$336,0)) -> Technology, Media & Telecom | Q66: =INDEX(Accounts!$D$5:$D$336,MATCH(B66,Accounts!$A$5:$A$336,0)) -> Key | R66: =INDEX(Inputs!$B$11:$B$16,MATCH(E66,Inputs!$A$11:$A$16,0)) -> 0 | S66: =IF(F66="",0,F66)*R66/100 -> 0 | T66: =Inputs!$B$4-J66 -> 103 | U66: =IF(OR(F66="",F66=0),1,0) -> 0 | V66: =IF(K66="",1,0) -> 0 | W66: =IF(AND(O66=1,K66<>"",COUNTIFS(Owners!$A$5:$A$32,K66,Owners!$E$5:$E$32,"No")>0),1,0) -> 0 | X66: =IF(AND(O66=1,I66<Inputs!$B$4),1,0) -> 0 | Y66: =IF(AND(O66=1,T66>Inputs!$B$5),1,0) -> 0 | Z66: =IF(AND(O66=1,G66<>R66),1,0) -> 0 | AA66: =IF(AND(O66=1,M66=""),1,0) -> 0 | AB66: =IF(AND(E66="Closed Lost",N66=""),1,0) -> 0 | AC66: =SUM(U66:AB66) -> 0 | AD66: =IF(AC66=0,1,0) -> 1 | AE66: =IF(AND(O66=1,I66>=Inputs!$B$6,I66<=Inputs!$B$7),1,0) -> 0 | AF66: =IF(AND(E66="Closed Won",I66>=Inputs!$B$6,I66<=Inputs!$B$4),1,0) -> 0 | AG66: =IF(AND(O66=0,I66>Inputs!$B$4-Inputs!$B$8,I66<=Inputs!$B$4),1,0) -> 1 | AH66: =I66-H66 -> 257
A67: O00063 | B67: A0032 | C67: Jambo Tea Estates | Consulting | due diligence | D67: Consulting | E67: Negotiation | F67: 137156000 | G67: 75 | H67: 46176 | I67: 46547 | J67: 46169 | K67: U004 | L67: Existing client | M67: Scope workshop | O67: =IF(OR(E67="Closed Won",E67="Closed Lost"),0,1) -> 1 | P67: =INDEX(Accounts!$K$5:$K$336,MATCH(B67,Accounts!$A$5:$A$336,0)) -> Agribusiness | Q67: =INDEX(Accounts!$D$5:$D$336,MATCH(B67,Accounts!$A$5:$A$336,0)) -> Priority | R67: =INDEX(Inputs!$B$11:$B$16,MATCH(E67,Inputs!$A$11:$A$16,0)) -> 75 | S67: =IF(F67="",0,F67)*R67/100 -> 102867000 | T67: =Inputs!$B$4-J67 -> 145 | U67: =IF(OR(F67="",F67=0),1,0) -> 0 | V67: =IF(K67="",1,0) -> 0 | W67: =IF(AND(O67=1,K67<>"",COUNTIFS(Owners!$A$5:$A$32,K67,Owners!$E$5:$E$32,"No")>0),1,0) -> 0 | X67: =IF(AND(O67=1,I67<Inputs!$B$4),1,0) -> 0 | Y67: =IF(AND(O67=1,T67>Inputs!$B$5),1,0) -> 1 | Z67: =IF(AND(O67=1,G67<>R67),1,0) -> 0 | AA67: =IF(AND(O67=1,M67=""),1,0) -> 0 | AB67: =IF(AND(E67="Closed Lost",N67=""),1,0) -> 0 | AC67: =SUM(U67:AB67) -> 1 | AD67: =IF(AC67=0,1,0) -> 0 | AE67: =IF(AND(O67=1,I67>=Inputs!$B$6,I67<=Inputs!$B$7),1,0) -> 1 | AF67: =IF(AND(E67="Closed Won",I67>=Inputs!$B$6,I67<=Inputs!$B$4),1,0) -> 0 | AG67: =IF(AND(O67=0,I67>Inputs!$B$4-Inputs!$B$8,I67<=Inputs!$B$4),1,0) -> 0 | AH67: =I67-H67 -> 371
A68: O00064 | B68: A0183 | C68: Simba County Government | Consulting | support | D68: Consulting | E68: Closed Won | F68: 7278000 | G68: 100 | H68: 45957 | I68: 46033 | J68: 46033 | K68: U002 | L68: Thought leadership | O68: =IF(OR(E68="Closed Won",E68="Closed Lost"),0,1) -> 0 | P68: =INDEX(Accounts!$K$5:$K$336,MATCH(B68,Accounts!$A$5:$A$336,0)) -> Public Sector & Development | Q68: =INDEX(Accounts!$D$5:$D$336,MATCH(B68,Accounts!$A$5:$A$336,0)) -> Standard | R68: =INDEX(Inputs!$B$11:$B$16,MATCH(E68,Inputs!$A$11:$A$16,0)) -> 100 | S68: =IF(F68="",0,F68)*R68/100 -> 7278000 | T68: =Inputs!$B$4-J68 -> 281 | U68: =IF(OR(F68="",F68=0),1,0) -> 0 | V68: =IF(K68="",1,0) -> 0 | W68: =IF(AND(O68=1,K68<>"",COUNTIFS(Owners!$A$5:$A$32,K68,Owners!$E$5:$E$32,"No")>0),1,0) -> 0 | X68: =IF(AND(O68=1,I68<Inputs!$B$4),1,0) -> 0 | Y68: =IF(AND(O68=1,T68>Inputs!$B$5),1,0) -> 0 | Z68: =IF(AND(O68=1,G68<>R68),1,0) -> 0 | AA68: =IF(AND(O68=1,M68=""),1,0) -> 0 | AB68: =IF(AND(E68="Closed Lost",N68=""),1,0) -> 0 | AC68: =SUM(U68:AB68) -> 0 | AD68: =IF(AC68=0,1,0) -> 1 | AE68: =IF(AND(O68=1,I68>=Inputs!$B$6,I68<=Inputs!$B$7),1,0) -> 0 | AF68: =IF(AND(E68="Closed Won",I68>=Inputs!$B$6,I68<=Inputs!$B$4),1,0) -> 0 | AG68: =IF(AND(O68=0,I68>Inputs!$B$4-Inputs!$B$8,I68<=Inputs!$B$4),1,0) -> 1 | AH68: =I68-H68 -> 76
A69: O00065 | B69: A0050 | C69: Mara Commission | Deals | transformation | D69: Deals | E69: Closed Won | F69: 26295000 | G69: 100 | H69: 46104 | I69: 46260 | J69: 46260 | K69: U016 | L69: Digital | O69: =IF(OR(E69="Closed Won",E69="Closed Lost"),0,1) -> 0 | P69: =INDEX(Accounts!$K$5:$K$336,MATCH(B69,Accounts!$A$5:$A$336,0)) -> Public Sector & Development | Q69: =INDEX(Accounts!$D$5:$D$336,MATCH(B69,Accounts!$A$5:$A$336,0)) -> Key | R69: =INDEX(Inputs!$B$11:$B$16,MATCH(E69,Inputs!$A$11:$A$16,0)) -> 100 | S69: =IF(F69="",0,F69)*R69/100 -> 26295000 | T69: =Inputs!$B$4-J69 -> 54 | U69: =IF(OR(F69="",F69=0),1,0) -> 0 | V69: =IF(K69="",1,0) -> 0 | W69: =IF(AND(O69=1,K69<>"",COUNTIFS(Owners!$A$5:$A$32,K69,Owners!$E$5:$E$32,"No")>0),1,0) -> 0 | X69: =IF(AND(O69=1,I69<Inputs!$B$4),1,0) -> 0 | Y69: =IF(AND(O69=1,T69>Inputs!$B$5),1,0) -> 0 | Z69: =IF(AND(O69=1,G69<>R69),1,0) -> 0 | AA69: =IF(AND(O69=1,M69=""),1,0) -> 0 | AB69: =IF(AND(E69="Closed Lost",N69=""),1,0) -> 0 | AC69: =SUM(U69:AB69) -> 0 | AD69: =IF(AC69=0,1,0) -> 1 | AE69: =IF(AND(O69=1,I69>=Inputs!$B$6,I69<=Inputs!$B$7),1,0) -> 0 | AF69: =IF(AND(E69="Closed Won",I69>=Inputs!$B$6,I69<=Inputs!$B$4),1,0) -> 1 | AG69: =IF(AND(O69=0,I69>Inputs!$B$4-Inputs!$B$8,I69<=Inputs!$B$4),1,0) -> 1 | AH69: =I69-H69 -> 156
A70: O00066 | B70: A0028 | C70: Lakeview Hotels | Consulting | compliance | D70: Consulting | E70: Prospecting | F70: 46850000 | G70: 10 | H70: 46224 | I70: 46427 | J70: 46284 | K70: U007 | L70: Existing client | M70: Partner meeting | O70: =IF(OR(E70="Closed Won",E70="Closed Lost"),0,1) -> 1 | P70: =INDEX(Accounts!$K$5:$K$336,MATCH(B70,Accounts!$A$5:$A$336,0)) -> Consumer & Retail | Q70: =INDEX(Accounts!$D$5:$D$336,MATCH(B70,Accounts!$A$5:$A$336,0)) -> Priority | R70: =INDEX(Inputs!$B$11:$B$16,MATCH(E70,Inputs!$A$11:$A$16,0)) -> 10 | S70: =IF(F70="",0,F70)*R70/100 -> 4685000 | T70: =Inputs!$B$4-J70 -> 30 | U70: =IF(OR(F70="",F70=0),1,0) -> 0 | V70: =IF(K70="",1,0) -> 0 | W70: =IF(AND(O70=1,K70<>"",COUNTIFS(Owners!$A$5:$A$32,K70,Owners!$E$5:$E$32,"No")>0),1,0) -> 0 | X70: =IF(AND(O70=1,I70<Inputs!$B$4),1,0) -> 0 | Y70: =IF(AND(O70=1,T70>Inputs!$B$5),1,0) -> 0 | Z70: =IF(AND(O70=1,G70<>R70),1,0) -> 0 | AA70: =IF(AND(O70=1,M70=""),1,0) -> 0 | AB70: =IF(AND(E70="Closed Lost",N70=""),1,0) -> 0 | AC70: =SUM(U70:AB70) -> 0 | AD70: =IF(AC70=0,1,0) -> 1 | AE70: =IF(AND(O70=1,I70>=Inputs!$B$6,I70<=Inputs!$B$7),1,0) -> 1 | AF70: =IF(AND(E70="Closed Won",I70>=Inputs!$B$6,I70<=Inputs!$B$4),1,0) -> 0 | AG70: =IF(AND(O70=0,I70>Inputs!$B$4-Inputs!$B$8,I70<=Inputs!$B$4),1,0) -> 0 | AH70: =I70-H70 -> 203
A71: O00067 | B71: A0004 | C71: Pwani Asset Managers | Tax & Legal | support | D71: Tax & Legal | E71: Closed Won | F71: 4095000 | G71: 100 | H71: 45895 | I71: 46153 | J71: 46153 | K71: U004 | L71: Cold outreach | O71: =IF(OR(E71="Closed Won",E71="Closed Lost"),0,1) -> 0 | P71: =INDEX(Accounts!$K$5:$K$336,MATCH(B71,Accounts!$A$5:$A$336,0)) -> Financial Services | Q71: =INDEX(Accounts!$D$5:$D$336,MATCH(B71,Accounts!$A$5:$A$336,0)) -> Priority | R71: =INDEX(Inputs!$B$11:$B$16,MATCH(E71,Inputs!$A$11:$A$16,0)) -> 100 | S71: =IF(F71="",0,F71)*R71/100 -> 4095000 | T71: =Inputs!$B$4-J71 -> 161 | U71: =IF(OR(F71="",F71=0),1,0) -> 0 | V71: =IF(K71="",1,0) -> 0 | W71: =IF(AND(O71=1,K71<>"",COUNTIFS(Owners!$A$5:$A$32,K71,Owners!$E$5:$E$32,"No")>0),1,0) -> 0 | X71: =IF(AND(O71=1,I71<Inputs!$B$4),1,0) -> 0 | Y71: =IF(AND(O71=1,T71>Inputs!$B$5),1,0) -> 0 | Z71: =IF(AND(O71=1,G71<>R71),1,0) -> 0 | AA71: =IF(AND(O71=1,M71=""),1,0) -> 0 | AB71: =IF(AND(E71="Closed Lost",N71=""),1,0) -> 0 | AC71: =SUM(U71:AB71) -> 0 | AD71: =IF(AC71=0,1,0) -> 1 | AE71: =IF(AND(O71=1,I71>=Inputs!$B$6,I71<=Inputs!$B$7),1,0) -> 0 | AF71: =IF(AND(E71="Closed Won",I71>=Inputs!$B$6,I71<=Inputs!$B$4),1,0) -> 0 | AG71: =IF(AND(O71=0,I71>Inputs!$B$4-Inputs!$B$8,I71<=Inputs!$B$4),1,0) -> 1 | AH71: =I71-H71 -> 258
A72: O00068 | B72: A0150 | C72: Umoja Hospital | Risk | transformation | D72: Risk | E72: Closed Lost | F72: 3323000 | G72: 0 | H72: 45935 | I72: 46074 | J72: 46074 | K72: U015 | L72: Thought leadership | N72: Competitor | O72: =IF(OR(E72="Closed Won",E72="Closed Lost"),0,1) -> 0 | P72: =INDEX(Accounts!$K$5:$K$336,MATCH(B72,Accounts!$A$5:$A$336,0)) -> Health | Q72: =INDEX(Accounts!$D$5:$D$336,MATCH(B72,Accounts!$A$5:$A$336,0)) -> Standard | R72: =INDEX(Inputs!$B$11:$B$16,MATCH(E72,Inputs!$A$11:$A$16,0)) -> 0 | S72: =IF(F72="",0,F72)*R72/100 -> 0 | T72: =Inputs!$B$4-J72 -> 240 | U72: =IF(OR(F72="",F72=0),1,0) -> 0 | V72: =IF(K72="",1,0) -> 0 | W72: =IF(AND(O72=1,K72<>"",COUNTIFS(Owners!$A$5:$A$32,K72,Owners!$E$5:$E$32,"No")>0),1,0) -> 0 | X72: =IF(AND(O72=1,I72<Inputs!$B$4),1,0) -> 0 | Y72: =IF(AND(O72=1,T72>Inputs!$B$5),1,0) -> 0 | Z72: =IF(AND(O72=1,G72<>R72),1,0) -> 0 | AA72: =IF(AND(O72=1,M72=""),1,0) -> 0 | AB72: =IF(AND(E72="Closed Lost",N72=""),1,0) -> 0 | AC72: =SUM(U72:AB72) -> 0 | AD72: =IF(AC72=0,1,0) -> 1 | AE72: =IF(AND(O72=1,I72>=Inputs!$B$6,I72<=Inputs!$B$7),1,0) -> 0 | AF72: =IF(AND(E72="Closed Won",I72>=Inputs!$B$6,I72<=Inputs!$B$4),1,0) -> 0 | AG72: =IF(AND(O72=0,I72>Inputs!$B$4-Inputs!$B$8,I72<=Inputs!$B$4),1,0) -> 1 | AH72: =I72-H72 -> 139
A73: O00069 | B73: A0030 | C73: Nile Networks | Consulting | advisory | D73: Consulting | E73: Closed Lost | F73: 15906000 | G73: 0 | H73: 46141 | I73: 46232 | J73: 46232 | K73: U002 | L73: Event | O73: =IF(OR(E73="Closed Won",E73="Closed Lost"),0,1) -> 0 | P73: =INDEX(Accounts!$K$5:$K$336,MATCH(B73,Accounts!$A$5:$A$336,0)) -> Technology, Media & Telecom | Q73: =INDEX(Accounts!$D$5:$D$336,MATCH(B73,Accounts!$A$5:$A$336,0)) -> Priority | R73: =INDEX(Inputs!$B$11:$B$16,MATCH(E73,Inputs!$A$11:$A$16,0)) -> 0 | S73: =IF(F73="",0,F73)*R73/100 -> 0 | T73: =Inputs!$B$4-J73 -> 82 | U73: =IF(OR(F73="",F73=0),1,0) -> 0 | V73: =IF(K73="",1,0) -> 0 | W73: =IF(AND(O73=1,K73<>"",COUNTIFS(Owners!$A$5:$A$32,K73,Owners!$E$5:$E$32,"No")>0),1,0) -> 0 | X73: =IF(AND(O73=1,I73<Inputs!$B$4),1,0) -> 0 | Y73: =IF(AND(O73=1,T73>Inputs!$B$5),1,0) -> 0 | Z73: =IF(AND(O73=1,G73<>R73),1,0) -> 0 | AA73: =IF(AND(O73=1,M73=""),1,0) -> 0 | AB73: =IF(AND(E73="Closed Lost",N73=""),1,0) -> 1 | AC73: =SUM(U73:AB73) -> 1 | AD73: =IF(AC73=0,1,0) -> 0 | AE73: =IF(AND(O73=1,I73>=Inputs!$B$6,I73<=Inputs!$B$7),1,0) -> 0 | AF73: =IF(AND(E73="Closed Won",I73>=Inputs!$B$6,I73<=Inputs!$B$4),1,0) -> 0 | AG73: =IF(AND(O73=0,I73>Inputs!$B$4-Inputs!$B$8,I73<=Inputs!$B$4),1,0) -> 1 | AH73: =I73-H73 -> 91
A74: O00070 | B74: A0002 | C74: Umoja Capital | Tax & Legal | compliance | D74: Tax & Legal | E74: Closed Lost | G74: 0 | H74: 45909 | I74: 46171 | J74: 46171 | K74: U002 | L74: Referral | O74: =IF(OR(E74="Closed Won",E74="Closed Lost"),0,1) -> 0 | P74: =INDEX(Accounts!$K$5:$K$336,MATCH(B74,Accounts!$A$5:$A$336,0)) -> Financial Services | Q74: =INDEX(Accounts!$D$5:$D$336,MATCH(B74,Accounts!$A$5:$A$336,0)) -> Priority | R74: =INDEX(Inputs!$B$11:$B$16,MATCH(E74,Inputs!$A$11:$A$16,0)) -> 0 | S74: =IF(F74="",0,F74)*R74/100 -> 0 | T74: =Inputs!$B$4-J74 -> 143 | U74: =IF(OR(F74="",F74=0),1,0) -> 1 | V74: =IF(K74="",1,0) -> 0 | W74: =IF(AND(O74=1,K74<>"",COUNTIFS(Owners!$A$5:$A$32,K74,Owners!$E$5:$E$32,"No")>0),1,0) -> 0 | X74: =IF(AND(O74=1,I74<Inputs!$B$4),1,0) -> 0 | Y74: =IF(AND(O74=1,T74>Inputs!$B$5),1,0) -> 0 | Z74: =IF(AND(O74=1,G74<>R74),1,0) -> 0 | AA74: =IF(AND(O74=1,M74=""),1,0) -> 0 | AB74: =IF(AND(E74="Closed Lost",N74=""),1,0) -> 1 | AC74: =SUM(U74:AB74) -> 2 | AD74: =IF(AC74=0,1,0) -> 0 | AE74: =IF(AND(O74=1,I74>=Inputs!$B$6,I74<=Inputs!$B$7),1,0) -> 0 | AF74: =IF(AND(E74="Closed Won",I74>=Inputs!$B$6,I74<=Inputs!$B$4),1,0) -> 0 | AG74: =IF(AND(O74=0,I74>Inputs!$B$4-Inputs!$B$8,I74<=Inputs!$B$4),1,0) -> 1 | AH74: =I74-H74 -> 262
A75: O00071 | B75: A0005 | C75: Twiga Agri | Consulting | review | D75: Consulting | E75: Prospecting | F75: 16730000 | G75: 10 | H75: 46202 | I75: 46415 | J75: 46304 | K75: U002 | L75: Referral | M75: Send proposal | O75: =IF(OR(E75="Closed Won",E75="Closed Lost"),0,1) -> 1 | P75: =INDEX(Accounts!$K$5:$K$336,MATCH(B75,Accounts!$A$5:$A$336,0)) -> Agribusiness | Q75: =INDEX(Accounts!$D$5:$D$336,MATCH(B75,Accounts!$A$5:$A$336,0)) -> Priority | R75: =INDEX(Inputs!$B$11:$B$16,MATCH(E75,Inputs!$A$11:$A$16,0)) -> 10 | S75: =IF(F75="",0,F75)*R75/100 -> 1673000 | T75: =Inputs!$B$4-J75 -> 10 | U75: =IF(OR(F75="",F75=0),1,0) -> 0 | V75: =IF(K75="",1,0) -> 0 | W75: =IF(AND(O75=1,K75<>"",COUNTIFS(Owners!$A$5:$A$32,K75,Owners!$E$5:$E$32,"No")>0),1,0) -> 0 | X75: =IF(AND(O75=1,I75<Inputs!$B$4),1,0) -> 0 | Y75: =IF(AND(O75=1,T75>Inputs!$B$5),1,0) -> 0 | Z75: =IF(AND(O75=1,G75<>R75),1,0) -> 0 | AA75: =IF(AND(O75=1,M75=""),1,0) -> 0 | AB75: =IF(AND(E75="Closed Lost",N75=""),1,0) -> 0 | AC75: =SUM(U75:AB75) -> 0 | AD75: =IF(AC75=0,1,0) -> 1 | AE75: =IF(AND(O75=1,I75>=Inputs!$B$6,I75<=Inputs!$B$7),1,0) -> 1 | AF75: =IF(AND(E75="Closed Won",I75>=Inputs!$B$6,I75<=Inputs!$B$4),1,0) -> 0 | AG75: =IF(AND(O75=0,I75>Inputs!$B$4-Inputs!$B$8,I75<=Inputs!$B$4),1,0) -> 0 | AH75: =I75-H75 -> 213
A76: O00072 | B76: A0064 | C76: Twiga Insurance | Risk | due diligence | D76: Risk | E76: Closed Lost | F76: 25443000 | G76: 0 | H76: 45996 | I76: 46273 | J76: 46273 | K76: U019 | L76: Thought leadership | N76: Price | O76: =IF(OR(E76="Closed Won",E76="Closed Lost"),0,1) -> 0 | P76: =INDEX(Accounts!$K$5:$K$336,MATCH(B76,Accounts!$A$5:$A$336,0)) -> Financial Services | Q76: =INDEX(Accounts!$D$5:$D$336,MATCH(B76,Accounts!$A$5:$A$336,0)) -> Key | R76: =INDEX(Inputs!$B$11:$B$16,MATCH(E76,Inputs!$A$11:$A$16,0)) -> 0 | S76: =IF(F76="",0,F76)*R76/100 -> 0 | T76: =Inputs!$B$4-J76 -> 41 | U76: =IF(OR(F76="",F76=0),1,0) -> 0 | V76: =IF(K76="",1,0) -> 0 | W76: =IF(AND(O76=1,K76<>"",COUNTIFS(Owners!$A$5:$A$32,K76,Owners!$E$5:$E$32,"No")>0),1,0) -> 0 | X76: =IF(AND(O76=1,I76<Inputs!$B$4),1,0) -> 0 | Y76: =IF(AND(O76=1,T76>Inputs!$B$5),1,0) -> 0 | Z76: =IF(AND(O76=1,G76<>R76),1,0) -> 0 | AA76: =IF(AND(O76=1,M76=""),1,0) -> 0 | AB76: =IF(AND(E76="Closed Lost",N76=""),1,0) -> 0 | AC76: =SUM(U76:AB76) -> 0 | AD76: =IF(AC76=0,1,0) -> 1 | AE76: =IF(AND(O76=1,I76>=Inputs!$B$6,I76<=Inputs!$B$7),1,0) -> 0 | AF76: =IF(AND(E76="Closed Won",I76>=Inputs!$B$6,I76<=Inputs!$B$4),1,0) -> 0 | AG76: =IF(AND(O76=0,I76>Inputs!$B$4-Inputs!$B$8,I76<=Inputs!$B$4),1,0) -> 1 | AH76: =I76-H76 -> 277
A77: O00073 | B77: A0013 | C77: Kilimanjaro Capital | Deals | due diligence | D77: Deals | E77: Qualification | F77: 14618000 | G77: 25 | H77: 46272 | I77: 46514 | J77: 46297 | K77: U015 | L77: Event | M77: Await tender outcome | O77: =IF(OR(E77="Closed Won",E77="Closed Lost"),0,1) -> 1 | P77: =INDEX(Accounts!$K$5:$K$336,MATCH(B77,Accounts!$A$5:$A$336,0)) -> Financial Services | Q77: =INDEX(Accounts!$D$5:$D$336,MATCH(B77,Accounts!$A$5:$A$336,0)) -> Priority | R77: =INDEX(Inputs!$B$11:$B$16,MATCH(E77,Inputs!$A$11:$A$16,0)) -> 25 | S77: =IF(F77="",0,F77)*R77/100 -> 3654500 | T77: =Inputs!$B$4-J77 -> 17 | U77: =IF(OR(F77="",F77=0),1,0) -> 0 | V77: =IF(K77="",1,0) -> 0 | W77: =IF(AND(O77=1,K77<>"",COUNTIFS(Owners!$A$5:$A$32,K77,Owners!$E$5:$E$32,"No")>0),1,0) -> 0 | X77: =IF(AND(O77=1,I77<Inputs!$B$4),1,0) -> 0 | Y77: =IF(AND(O77=1,T77>Inputs!$B$5),1,0) -> 0 | Z77: =IF(AND(O77=1,G77<>R77),1,0) -> 0 | AA77: =IF(AND(O77=1,M77=""),1,0) -> 0 | AB77: =IF(AND(E77="Closed Lost",N77=""),1,0) -> 0 | AC77: =SUM(U77:AB77) -> 0 | AD77: =IF(AC77=0,1,0) -> 1 | AE77: =IF(AND(O77=1,I77>=Inputs!$B$6,I77<=Inputs!$B$7),1,0) -> 1 | AF77: =IF(AND(E77="Closed Won",I77>=Inputs!$B$6,I77<=Inputs!$B$4),1,0) -> 0 | AG77: =IF(AND(O77=0,I77>Inputs!$B$4-Inputs!$B$8,I77<=Inputs!$B$4),1,0) -> 0 | AH77: =I77-H77 -> 242
A78: O00074 | B78: A0037 | C78: Zuri Hotels | Consulting | annual | D78: Consulting | E78: Closed Lost | F78: 15071000 | G78: 0 | H78: 46188 | I78: 46274 | J78: 46274 | K78: U002 | L78: Cold outreach | N78: Independence conflict | O78: =IF(OR(E78="Closed Won",E78="Closed Lost"),0,1) -> 0 | P78: =INDEX(Accounts!$K$5:$K$336,MATCH(B78,Accounts!$A$5:$A$336,0)) -> Unassigned | Q78: =INDEX(Accounts!$D$5:$D$336,MATCH(B78,Accounts!$A$5:$A$336,0)) -> Priority | R78: =INDEX(Inputs!$B$11:$B$16,MATCH(E78,Inputs!$A$11:$A$16,0)) -> 0 | S78: =IF(F78="",0,F78)*R78/100 -> 0 | T78: =Inputs!$B$4-J78 -> 40 | U78: =IF(OR(F78="",F78=0),1,0) -> 0 | V78: =IF(K78="",1,0) -> 0 | W78: =IF(AND(O78=1,K78<>"",COUNTIFS(Owners!$A$5:$A$32,K78,Owners!$E$5:$E$32,"No")>0),1,0) -> 0 | X78: =IF(AND(O78=1,I78<Inputs!$B$4),1,0) -> 0 | Y78: =IF(AND(O78=1,T78>Inputs!$B$5),1,0) -> 0 | Z78: =IF(AND(O78=1,G78<>R78),1,0) -> 0 | AA78: =IF(AND(O78=1,M78=""),1,0) -> 0 | AB78: =IF(AND(E78="Closed Lost",N78=""),1,0) -> 0 | AC78: =SUM(U78:AB78) -> 0 | AD78: =IF(AC78=0,1,0) -> 1 | AE78: =IF(AND(O78=1,I78>=Inputs!$B$6,I78<=Inputs!$B$7),1,0) -> 0 | AF78: =IF(AND(E78="Closed Won",I78>=Inputs!$B$6,I78<=Inputs!$B$4),1,0) -> 0 | AG78: =IF(AND(O78=0,I78>Inputs!$B$4-Inputs!$B$8,I78<=Inputs!$B$4),1,0) -> 1 | AH78: =I78-H78 -> 86
A79: O00075 | B79: A0098 | C79: Twiga Networks | Consulting | readiness | D79: Consulting | E79: Negotiation | F79: 34086000 | G79: 75 | H79: 46219 | I79: 46347 | J79: 46268 | K79: U022 | L79: Existing client | M79: Scope workshop | O79: =IF(OR(E79="Closed Won",E79="Closed Lost"),0,1) -> 1 | P79: =INDEX(Accounts!$K$5:$K$336,MATCH(B79,Accounts!$A$5:$A$336,0)) -> Technology, Media & Telecom | Q79: =INDEX(Accounts!$D$5:$D$336,MATCH(B79,Accounts!$A$5:$A$336,0)) -> Key | R79: =INDEX(Inputs!$B$11:$B$16,MATCH(E79,Inputs!$A$11:$A$16,0)) -> 75 | S79: =IF(F79="",0,F79)*R79/100 -> 25564500 | T79: =Inputs!$B$4-J79 -> 46 | U79: =IF(OR(F79="",F79=0),1,0) -> 0 | V79: =IF(K79="",1,0) -> 0 | W79: =IF(AND(O79=1,K79<>"",COUNTIFS(Owners!$A$5:$A$32,K79,Owners!$E$5:$E$32,"No")>0),1,0) -> 0 | X79: =IF(AND(O79=1,I79<Inputs!$B$4),1,0) -> 0 | Y79: =IF(AND(O79=1,T79>Inputs!$B$5),1,0) -> 0 | Z79: =IF(AND(O79=1,G79<>R79),1,0) -> 0 | AA79: =IF(AND(O79=1,M79=""),1,0) -> 0 | AB79: =IF(AND(E79="Closed Lost",N79=""),1,0) -> 0 | AC79: =SUM(U79:AB79) -> 0 | AD79: =IF(AC79=0,1,0) -> 1 | AE79: =IF(AND(O79=1,I79>=Inputs!$B$6,I79<=Inputs!$B$7),1,0) -> 1 | AF79: =IF(AND(E79="Closed Won",I79>=Inputs!$B$6,I79<=Inputs!$B$4),1,0) -> 0 | AG79: =IF(AND(O79=0,I79>Inputs!$B$4-Inputs!$B$8,I79<=Inputs!$B$4),1,0) -> 0 | AH79: =I79-H79 -> 128
A80: O00076 | B80: A0293 | C80: Highland Networks | Assurance | review | D80: Assurance | E80: Negotiation | F80: 3734000 | G80: 75 | H80: 46244 | I80: 46309 | J80: 46288 | K80: U024 | L80: Event | M80: Scope workshop | O80: =IF(OR(E80="Closed Won",E80="Closed Lost"),0,1) -> 1 | P80: =INDEX(Accounts!$K$5:$K$336,MATCH(B80,Accounts!$A$5:$A$336,0)) -> Technology, Media & Telecom | Q80: =INDEX(Accounts!$D$5:$D$336,MATCH(B80,Accounts!$A$5:$A$336,0)) -> Standard | R80: =INDEX(Inputs!$B$11:$B$16,MATCH(E80,Inputs!$A$11:$A$16,0)) -> 75 | S80: =IF(F80="",0,F80)*R80/100 -> 2800500 | T80: =Inputs!$B$4-J80 -> 26 | U80: =IF(OR(F80="",F80=0),1,0) -> 0 | V80: =IF(K80="",1,0) -> 0 | W80: =IF(AND(O80=1,K80<>"",COUNTIFS(Owners!$A$5:$A$32,K80,Owners!$E$5:$E$32,"No")>0),1,0) -> 1 | X80: =IF(AND(O80=1,I80<Inputs!$B$4),1,0) -> 1 | Y80: =IF(AND(O80=1,T80>Inputs!$B$5),1,0) -> 0 | Z80: =IF(AND(O80=1,G80<>R80),1,0) -> 0 | AA80: =IF(AND(O80=1,M80=""),1,0) -> 0 | AB80: =IF(AND(E80="Closed Lost",N80=""),1,0) -> 0 | AC80: =SUM(U80:AB80) -> 2 | AD80: =IF(AC80=0,1,0) -> 0 | AE80: =IF(AND(O80=1,I80>=Inputs!$B$6,I80<=Inputs!$B$7),1,0) -> 1 | AF80: =IF(AND(E80="Closed Won",I80>=Inputs!$B$6,I80<=Inputs!$B$4),1,0) -> 0 | AG80: =IF(AND(O80=0,I80>Inputs!$B$4-Inputs!$B$8,I80<=Inputs!$B$4),1,0) -> 0 | AH80: =I80-H80 -> 65
A81: O00077 | B81: A0007 | C81: Nile County Government | Deals | annual | D81: Deals | E81: Qualification | F81: 7619000 | G81: 25 | H81: 46244 | I81: 46333 | J81: 46222 | K81: U007 | L81: Referral | M81: Send proposal | O81: =IF(OR(E81="Closed Won",E81="Closed Lost"),0,1) -> 1 | P81: =INDEX(Accounts!$K$5:$K$336,MATCH(B81,Accounts!$A$5:$A$336,0)) -> Public Sector & Development | Q81: =INDEX(Accounts!$D$5:$D$336,MATCH(B81,Accounts!$A$5:$A$336,0)) -> Priority | R81: =INDEX(Inputs!$B$11:$B$16,MATCH(E81,Inputs!$A$11:$A$16,0)) -> 25 | S81: =IF(F81="",0,F81)*R81/100 -> 1904750 | T81: =Inputs!$B$4-J81 -> 92 | U81: =IF(OR(F81="",F81=0),1,0) -> 0 | V81: =IF(K81="",1,0) -> 0 | W81: =IF(AND(O81=1,K81<>"",COUNTIFS(Owners!$A$5:$A$32,K81,Owners!$E$5:$E$32,"No")>0),1,0) -> 0 | X81: =IF(AND(O81=1,I81<Inputs!$B$4),1,0) -> 0 | Y81: =IF(AND(O81=1,T81>Inputs!$B$5),1,0) -> 1 | Z81: =IF(AND(O81=1,G81<>R81),1,0) -> 0 | AA81: =IF(AND(O81=1,M81=""),1,0) -> 0 | AB81: =IF(AND(E81="Closed Lost",N81=""),1,0) -> 0 | AC81: =SUM(U81:AB81) -> 1 | AD81: =IF(AC81=0,1,0) -> 0 | AE81: =IF(AND(O81=1,I81>=Inputs!$B$6,I81<=Inputs!$B$7),1,0) -> 1 | AF81: =IF(AND(E81="Closed Won",I81>=Inputs!$B$6,I81<=Inputs!$B$4),1,0) -> 0 | AG81: =IF(AND(O81=0,I81>Inputs!$B$4-Inputs!$B$8,I81<=Inputs!$B$4),1,0) -> 0 | AH81: =I81-H81 -> 89
A82: O00078 | B82: A0008 | C82: Tembo Capital | Tax & Legal | due diligence | D82: Tax & Legal | E82: Prospecting | F82: 13173000 | G82: 10 | H82: 46118 | I82: 46375 | J82: 46293 | K82: U001 | L82: Event | M82: Partner meeting | O82: =IF(OR(E82="Closed Won",E82="Closed Lost"),0,1) -> 1 | P82: =INDEX(Accounts!$K$5:$K$336,MATCH(B82,Accounts!$A$5:$A$336,0)) -> Financial Services | Q82: =INDEX(Accounts!$D$5:$D$336,MATCH(B82,Accounts!$A$5:$A$336,0)) -> Priority | R82: =INDEX(Inputs!$B$11:$B$16,MATCH(E82,Inputs!$A$11:$A$16,0)) -> 10 | S82: =IF(F82="",0,F82)*R82/100 -> 1317300 | T82: =Inputs!$B$4-J82 -> 21 | U82: =IF(OR(F82="",F82=0),1,0) -> 0 | V82: =IF(K82="",1,0) -> 0 | W82: =IF(AND(O82=1,K82<>"",COUNTIFS(Owners!$A$5:$A$32,K82,Owners!$E$5:$E$32,"No")>0),1,0) -> 0 | X82: =IF(AND(O82=1,I82<Inputs!$B$4),1,0) -> 0 | Y82: =IF(AND(O82=1,T82>Inputs!$B$5),1,0) -> 0 | Z82: =IF(AND(O82=1,G82<>R82),1,0) -> 0 | AA82: =IF(AND(O82=1,M82=""),1,0) -> 0 | AB82: =IF(AND(E82="Closed Lost",N82=""),1,0) -> 0 | AC82: =SUM(U82:AB82) -> 0 | AD82: =IF(AC82=0,1,0) -> 1 | AE82: =IF(AND(O82=1,I82>=Inputs!$B$6,I82<=Inputs!$B$7),1,0) -> 1 | AF82: =IF(AND(E82="Closed Won",I82>=Inputs!$B$6,I82<=Inputs!$B$4),1,0) -> 0 | AG82: =IF(AND(O82=0,I82>Inputs!$B$4-Inputs!$B$8,I82<=Inputs!$B$4),1,0) -> 0 | AH82: =I82-H82 -> 257
A83: O00079 | B83: A0040 | C83: Amani Insurance | Deals | compliance | D83: Deals | E83: Closed Won | F83: 46177000 | G83: 100 | H83: 45967 | I83: 46199 | J83: 46199 | K83: U005 | L83: Existing client | O83: =IF(OR(E83="Closed Won",E83="Closed Lost"),0,1) -> 0 | P83: =INDEX(Accounts!$K$5:$K$336,MATCH(B83,Accounts!$A$5:$A$336,0)) -> Financial Services | Q83: =INDEX(Accounts!$D$5:$D$336,MATCH(B83,Accounts!$A$5:$A$336,0)) -> Priority | R83: =INDEX(Inputs!$B$11:$B$16,MATCH(E83,Inputs!$A$11:$A$16,0)) -> 100 | S83: =IF(F83="",0,F83)*R83/100 -> 46177000 | T83: =Inputs!$B$4-J83 -> 115 | U83: =IF(OR(F83="",F83=0),1,0) -> 0 | V83: =IF(K83="",1,0) -> 0 | W83: =IF(AND(O83=1,K83<>"",COUNTIFS(Owners!$A$5:$A$32,K83,Owners!$E$5:$E$32,"No")>0),1,0) -> 0 | X83: =IF(AND(O83=1,I83<Inputs!$B$4),1,0) -> 0 | Y83: =IF(AND(O83=1,T83>Inputs!$B$5),1,0) -> 0 | Z83: =IF(AND(O83=1,G83<>R83),1,0) -> 0 | AA83: =IF(AND(O83=1,M83=""),1,0) -> 0 | AB83: =IF(AND(E83="Closed Lost",N83=""),1,0) -> 0 | AC83: =SUM(U83:AB83) -> 0 | AD83: =IF(AC83=0,1,0) -> 1 | AE83: =IF(AND(O83=1,I83>=Inputs!$B$6,I83<=Inputs!$B$7),1,0) -> 0 | AF83: =IF(AND(E83="Closed Won",I83>=Inputs!$B$6,I83<=Inputs!$B$4),1,0) -> 0 | AG83: =IF(AND(O83=0,I83>Inputs!$B$4-Inputs!$B$8,I83<=Inputs!$B$4),1,0) -> 1 | AH83: =I83-H83 -> 232
A84: O00080 | B84: A0245 | C84: Mara Retail | Risk | annual | D84: Risk | E84: Closed Lost | F84: 6856000 | G84: 0 | H84: 45999 | I84: 46195 | J84: 46195 | K84: U023 | L84: Referral | N84: No decision | O84: =IF(OR(E84="Closed Won",E84="Closed Lost"),0,1) -> 0 | P84: =INDEX(Accounts!$K$5:$K$336,MATCH(B84,Accounts!$A$5:$A$336,0)) -> Consumer & Retail | Q84: =INDEX(Accounts!$D$5:$D$336,MATCH(B84,Accounts!$A$5:$A$336,0)) -> Standard | R84: =INDEX(Inputs!$B$11:$B$16,MATCH(E84,Inputs!$A$11:$A$16,0)) -> 0 | S84: =IF(F84="",0,F84)*R84/100 -> 0 | T84: =Inputs!$B$4-J84 -> 119 | U84: =IF(OR(F84="",F84=0),1,0) -> 0 | V84: =IF(K84="",1,0) -> 0 | W84: =IF(AND(O84=1,K84<>"",COUNTIFS(Owners!$A$5:$A$32,K84,Owners!$E$5:$E$32,"No")>0),1,0) -> 0 | X84: =IF(AND(O84=1,I84<Inputs!$B$4),1,0) -> 0 | Y84: =IF(AND(O84=1,T84>Inputs!$B$5),1,0) -> 0 | Z84: =IF(AND(O84=1,G84<>R84),1,0) -> 0 | AA84: =IF(AND(O84=1,M84=""),1,0) -> 0 | AB84: =IF(AND(E84="Closed Lost",N84=""),1,0) -> 0 | AC84: =SUM(U84:AB84) -> 0 | AD84: =IF(AC84=0,1,0) -> 1 | AE84: =IF(AND(O84=1,I84>=Inputs!$B$6,I84<=Inputs!$B$7),1,0) -> 0 | AF84: =IF(AND(E84="Closed Won",I84>=Inputs!$B$6,I84<=Inputs!$B$4),1,0) -> 0 | AG84: =IF(AND(O84=0,I84>Inputs!$B$4-Inputs!$B$8,I84<=Inputs!$B$4),1,0) -> 1 | AH84: =I84-H84 -> 196
A85: O00081 | B85: A0013 | C85: Kilimanjaro Capital | Assurance | compliance | D85: Assurance | E85: Closed Lost | F85: 6863000 | G85: 0 | H85: 46070 | I85: 46274 | J85: 46274 | K85: U006 | L85: Thought leadership | N85: Price | O85: =IF(OR(E85="Closed Won",E85="Closed Lost"),0,1) -> 0 | P85: =INDEX(Accounts!$K$5:$K$336,MATCH(B85,Accounts!$A$5:$A$336,0)) -> Financial Services | Q85: =INDEX(Accounts!$D$5:$D$336,MATCH(B85,Accounts!$A$5:$A$336,0)) -> Priority | R85: =INDEX(Inputs!$B$11:$B$16,MATCH(E85,Inputs!$A$11:$A$16,0)) -> 0 | S85: =IF(F85="",0,F85)*R85/100 -> 0 | T85: =Inputs!$B$4-J85 -> 40 | U85: =IF(OR(F85="",F85=0),1,0) -> 0 | V85: =IF(K85="",1,0) -> 0 | W85: =IF(AND(O85=1,K85<>"",COUNTIFS(Owners!$A$5:$A$32,K85,Owners!$E$5:$E$32,"No")>0),1,0) -> 0 | X85: =IF(AND(O85=1,I85<Inputs!$B$4),1,0) -> 0 | Y85: =IF(AND(O85=1,T85>Inputs!$B$5),1,0) -> 0 | Z85: =IF(AND(O85=1,G85<>R85),1,0) -> 0 | AA85: =IF(AND(O85=1,M85=""),1,0) -> 0 | AB85: =IF(AND(E85="Closed Lost",N85=""),1,0) -> 0 | AC85: =SUM(U85:AB85) -> 0 | AD85: =IF(AC85=0,1,0) -> 1 | AE85: =IF(AND(O85=1,I85>=Inputs!$B$6,I85<=Inputs!$B$7),1,0) -> 0 | AF85: =IF(AND(E85="Closed Won",I85>=Inputs!$B$6,I85<=Inputs!$B$4),1,0) -> 0 | AG85: =IF(AND(O85=0,I85>Inputs!$B$4-Inputs!$B$8,I85<=Inputs!$B$4),1,0) -> 1 | AH85: =I85-H85 -> 204
A86: O00082 | B86: A0052 | C86: Highland Telecom | Tax & Legal | support | D86: Tax & Legal | E86: Proposal | F86: 19063000 | G86: 50 | H86: 46205 | I86: 46381 | J86: 46281 | K86: U026 | L86: Existing client | M86: Follow-up call | O86: =IF(OR(E86="Closed Won",E86="Closed Lost"),0,1) -> 1 | P86: =INDEX(Accounts!$K$5:$K$336,MATCH(B86,Accounts!$A$5:$A$336,0)) -> Technology, Media & Telecom | Q86: =INDEX(Accounts!$D$5:$D$336,MATCH(B86,Accounts!$A$5:$A$336,0)) -> Key | R86: =INDEX(Inputs!$B$11:$B$16,MATCH(E86,Inputs!$A$11:$A$16,0)) -> 50 | S86: =IF(F86="",0,F86)*R86/100 -> 9531500 | T86: =Inputs!$B$4-J86 -> 33 | U86: =IF(OR(F86="",F86=0),1,0) -> 0 | V86: =IF(K86="",1,0) -> 0 | W86: =IF(AND(O86=1,K86<>"",COUNTIFS(Owners!$A$5:$A$32,K86,Owners!$E$5:$E$32,"No")>0),1,0) -> 0 | X86: =IF(AND(O86=1,I86<Inputs!$B$4),1,0) -> 0 | Y86: =IF(AND(O86=1,T86>Inputs!$B$5),1,0) -> 0 | Z86: =IF(AND(O86=1,G86<>R86),1,0) -> 0 | AA86: =IF(AND(O86=1,M86=""),1,0) -> 0 | AB86: =IF(AND(E86="Closed Lost",N86=""),1,0) -> 0 | AC86: =SUM(U86:AB86) -> 0 | AD86: =IF(AC86=0,1,0) -> 1 | AE86: =IF(AND(O86=1,I86>=Inputs!$B$6,I86<=Inputs!$B$7),1,0) -> 1 | AF86: =IF(AND(E86="Closed Won",I86>=Inputs!$B$6,I86<=Inputs!$B$4),1,0) -> 0 | AG86: =IF(AND(O86=0,I86>Inputs!$B$4-Inputs!$B$8,I86<=Inputs!$B$4),1,0) -> 0 | AH86: =I86-H86 -> 176
A87: O00083 | B87: A0158 | C87: Kibo Digital | Risk | support | D87: Risk | E87: Closed Won | F87: 30106000 | G87: 100 | H87: 46068 | I87: 46233 | J87: 46233 | K87: U016 | L87: Thought leadership | O87: =IF(OR(E87="Closed Won",E87="Closed Lost"),0,1) -> 0 | P87: =INDEX(Accounts!$K$5:$K$336,MATCH(B87,Accounts!$A$5:$A$336,0)) -> Technology, Media & Telecom | Q87: =INDEX(Accounts!$D$5:$D$336,MATCH(B87,Accounts!$A$5:$A$336,0)) -> Standard | R87: =INDEX(Inputs!$B$11:$B$16,MATCH(E87,Inputs!$A$11:$A$16,0)) -> 100 | S87: =IF(F87="",0,F87)*R87/100 -> 30106000 | T87: =Inputs!$B$4-J87 -> 81 | U87: =IF(OR(F87="",F87=0),1,0) -> 0 | V87: =IF(K87="",1,0) -> 0 | W87: =IF(AND(O87=1,K87<>"",COUNTIFS(Owners!$A$5:$A$32,K87,Owners!$E$5:$E$32,"No")>0),1,0) -> 0 | X87: =IF(AND(O87=1,I87<Inputs!$B$4),1,0) -> 0 | Y87: =IF(AND(O87=1,T87>Inputs!$B$5),1,0) -> 0 | Z87: =IF(AND(O87=1,G87<>R87),1,0) -> 0 | AA87: =IF(AND(O87=1,M87=""),1,0) -> 0 | AB87: =IF(AND(E87="Closed Lost",N87=""),1,0) -> 0 | AC87: =SUM(U87:AB87) -> 0 | AD87: =IF(AC87=0,1,0) -> 1 | AE87: =IF(AND(O87=1,I87>=Inputs!$B$6,I87<=Inputs!$B$7),1,0) -> 0 | AF87: =IF(AND(E87="Closed Won",I87>=Inputs!$B$6,I87<=Inputs!$B$4),1,0) -> 1 | AG87: =IF(AND(O87=0,I87>Inputs!$B$4-Inputs!$B$8,I87<=Inputs!$B$4),1,0) -> 1 | AH87: =I87-H87 -> 165
A88: O00084 | B88: A0246 | C88: Tembo Microfinance | Consulting | due diligence | D88: Consulting | E88: Closed Lost | F88: 11300000 | G88: 0 | H88: 46035 | I88: 46238 | J88: 46238 | K88: U025 | L88: Digital | N88: Independence conflict | O88: =IF(OR(E88="Closed Won",E88="Closed Lost"),0,1) -> 0 | P88: =INDEX(Accounts!$K$5:$K$336,MATCH(B88,Accounts!$A$5:$A$336,0)) -> Financial Services | Q88: =INDEX(Accounts!$D$5:$D$336,MATCH(B88,Accounts!$A$5:$A$336,0)) -> Standard | R88: =INDEX(Inputs!$B$11:$B$16,MATCH(E88,Inputs!$A$11:$A$16,0)) -> 0 | S88: =IF(F88="",0,F88)*R88/100 -> 0 | T88: =Inputs!$B$4-J88 -> 76 | U88: =IF(OR(F88="",F88=0),1,0) -> 0 | V88: =IF(K88="",1,0) -> 0 | W88: =IF(AND(O88=1,K88<>"",COUNTIFS(Owners!$A$5:$A$32,K88,Owners!$E$5:$E$32,"No")>0),1,0) -> 0 | X88: =IF(AND(O88=1,I88<Inputs!$B$4),1,0) -> 0 | Y88: =IF(AND(O88=1,T88>Inputs!$B$5),1,0) -> 0 | Z88: =IF(AND(O88=1,G88<>R88),1,0) -> 0 | AA88: =IF(AND(O88=1,M88=""),1,0) -> 0 | AB88: =IF(AND(E88="Closed Lost",N88=""),1,0) -> 0 | AC88: =SUM(U88:AB88) -> 0 | AD88: =IF(AC88=0,1,0) -> 1 | AE88: =IF(AND(O88=1,I88>=Inputs!$B$6,I88<=Inputs!$B$7),1,0) -> 0 | AF88: =IF(AND(E88="Closed Won",I88>=Inputs!$B$6,I88<=Inputs!$B$4),1,0) -> 0 | AG88: =IF(AND(O88=0,I88>Inputs!$B$4-Inputs!$B$8,I88<=Inputs!$B$4),1,0) -> 1 | AH88: =I88-H88 -> 203
A89: O00085 | B89: A0048 | C89: Safari Pharma | Tax & Legal | support | D89: Tax & Legal | E89: Negotiation | F89: 3360000 | G89: 75 | H89: 46199 | I89: 46499 | J89: 46297 | K89: U017 | L89: Event | M89: Await tender outcome | O89: =IF(OR(E89="Closed Won",E89="Closed Lost"),0,1) -> 1 | P89: =INDEX(Accounts!$K$5:$K$336,MATCH(B89,Accounts!$A$5:$A$336,0)) -> Health | Q89: =INDEX(Accounts!$D$5:$D$336,MATCH(B89,Accounts!$A$5:$A$336,0)) -> Key | R89: =INDEX(Inputs!$B$11:$B$16,MATCH(E89,Inputs!$A$11:$A$16,0)) -> 75 | S89: =IF(F89="",0,F89)*R89/100 -> 2520000 | T89: =Inputs!$B$4-J89 -> 17 | U89: =IF(OR(F89="",F89=0),1,0) -> 0 | V89: =IF(K89="",1,0) -> 0 | W89: =IF(AND(O89=1,K89<>"",COUNTIFS(Owners!$A$5:$A$32,K89,Owners!$E$5:$E$32,"No")>0),1,0) -> 0 | X89: =IF(AND(O89=1,I89<Inputs!$B$4),1,0) -> 0 | Y89: =IF(AND(O89=1,T89>Inputs!$B$5),1,0) -> 0 | Z89: =IF(AND(O89=1,G89<>R89),1,0) -> 0 | AA89: =IF(AND(O89=1,M89=""),1,0) -> 0 | AB89: =IF(AND(E89="Closed Lost",N89=""),1,0) -> 0 | AC89: =SUM(U89:AB89) -> 0 | AD89: =IF(AC89=0,1,0) -> 1 | AE89: =IF(AND(O89=1,I89>=Inputs!$B$6,I89<=Inputs!$B$7),1,0) -> 1 | AF89: =IF(AND(E89="Closed Won",I89>=Inputs!$B$6,I89<=Inputs!$B$4),1,0) -> 0 | AG89: =IF(AND(O89=0,I89>Inputs!$B$4-Inputs!$B$8,I89<=Inputs!$B$4),1,0) -> 0 | AH89: =I89-H89 -> 300
A90: O00086 | B90: A0033 | C90: Twiga Horticulture | Tax & Legal | advisory | D90: Tax & Legal | E90: Proposal | F90: 6045000 | G90: 50 | H90: 46183 | I90: 46396 | J90: 46293 | K90: U005 | L90: Existing client | M90: Follow-up call | O90: =IF(OR(E90="Closed Won",E90="Closed Lost"),0,1) -> 1 | P90: =INDEX(Accounts!$K$5:$K$336,MATCH(B90,Accounts!$A$5:$A$336,0)) -> Agribusiness | Q90: =INDEX(Accounts!$D$5:$D$336,MATCH(B90,Accounts!$A$5:$A$336,0)) -> Priority | R90: =INDEX(Inputs!$B$11:$B$16,MATCH(E90,Inputs!$A$11:$A$16,0)) -> 50 | S90: =IF(F90="",0,F90)*R90/100 -> 3022500 | T90: =Inputs!$B$4-J90 -> 21 | U90: =IF(OR(F90="",F90=0),1,0) -> 0 | V90: =IF(K90="",1,0) -> 0 | W90: =IF(AND(O90=1,K90<>"",COUNTIFS(Owners!$A$5:$A$32,K90,Owners!$E$5:$E$32,"No")>0),1,0) -> 0 | X90: =IF(AND(O90=1,I90<Inputs!$B$4),1,0) -> 0 | Y90: =IF(AND(O90=1,T90>Inputs!$B$5),1,0) -> 0 | Z90: =IF(AND(O90=1,G90<>R90),1,0) -> 0 | AA90: =IF(AND(O90=1,M90=""),1,0) -> 0 | AB90: =IF(AND(E90="Closed Lost",N90=""),1,0) -> 0 | AC90: =SUM(U90:AB90) -> 0 | AD90: =IF(AC90=0,1,0) -> 1 | AE90: =IF(AND(O90=1,I90>=Inputs!$B$6,I90<=Inputs!$B$7),1,0) -> 1 | AF90: =IF(AND(E90="Closed Won",I90>=Inputs!$B$6,I90<=Inputs!$B$4),1,0) -> 0 | AG90: =IF(AND(O90=0,I90>Inputs!$B$4-Inputs!$B$8,I90<=Inputs!$B$4),1,0) -> 0 | AH90: =I90-H90 -> 213
A91: O00087 | B91: A0052 | C91: Highland Telecom | Tax & Legal | support | D91: Tax & Legal | E91: Proposal | F91: 5261000 | G91: 50 | H91: 46115 | I91: 46512 | J91: 46288 | K91: U026 | L91: Referral | M91: Scope workshop | O91: =IF(OR(E91="Closed Won",E91="Closed Lost"),0,1) -> 1 | P91: =INDEX(Accounts!$K$5:$K$336,MATCH(B91,Accounts!$A$5:$A$336,0)) -> Technology, Media & Telecom | Q91: =INDEX(Accounts!$D$5:$D$336,MATCH(B91,Accounts!$A$5:$A$336,0)) -> Key | R91: =INDEX(Inputs!$B$11:$B$16,MATCH(E91,Inputs!$A$11:$A$16,0)) -> 50 | S91: =IF(F91="",0,F91)*R91/100 -> 2630500 | T91: =Inputs!$B$4-J91 -> 26 | U91: =IF(OR(F91="",F91=0),1,0) -> 0 | V91: =IF(K91="",1,0) -> 0 | W91: =IF(AND(O91=1,K91<>"",COUNTIFS(Owners!$A$5:$A$32,K91,Owners!$E$5:$E$32,"No")>0),1,0) -> 0 | X91: =IF(AND(O91=1,I91<Inputs!$B$4),1,0) -> 0 | Y91: =IF(AND(O91=1,T91>Inputs!$B$5),1,0) -> 0 | Z91: =IF(AND(O91=1,G91<>R91),1,0) -> 0 | AA91: =IF(AND(O91=1,M91=""),1,0) -> 0 | AB91: =IF(AND(E91="Closed Lost",N91=""),1,0) -> 0 | AC91: =SUM(U91:AB91) -> 0 | AD91: =IF(AC91=0,1,0) -> 1 | AE91: =IF(AND(O91=1,I91>=Inputs!$B$6,I91<=Inputs!$B$7),1,0) -> 1 | AF91: =IF(AND(E91="Closed Won",I91>=Inputs!$B$6,I91<=Inputs!$B$4),1,0) -> 0 | AG91: =IF(AND(O91=0,I91>Inputs!$B$4-Inputs!$B$8,I91<=Inputs!$B$4),1,0) -> 0 | AH91: =I91-H91 -> 397
A92: O00088 | B92: A0109 | C92: Mara Asset Managers | Tax & Legal | due diligence | D92: Tax & Legal | E92: Qualification | F92: 5846000 | G92: 25 | H92: 46188 | I92: 46554 | J92: 46135 | K92: U024 | L92: Existing client | M92: Send proposal | O92: =IF(OR(E92="Closed Won",E92="Closed Lost"),0,1) -> 1 | P92: =INDEX(Accounts!$K$5:$K$336,MATCH(B92,Accounts!$A$5:$A$336,0)) -> Financial Services | Q92: =INDEX(Accounts!$D$5:$D$336,MATCH(B92,Accounts!$A$5:$A$336,0)) -> Key | R92: =INDEX(Inputs!$B$11:$B$16,MATCH(E92,Inputs!$A$11:$A$16,0)) -> 25 | S92: =IF(F92="",0,F92)*R92/100 -> 1461500 | T92: =Inputs!$B$4-J92 -> 179 | U92: =IF(OR(F92="",F92=0),1,0) -> 0 | V92: =IF(K92="",1,0) -> 0 | W92: =IF(AND(O92=1,K92<>"",COUNTIFS(Owners!$A$5:$A$32,K92,Owners!$E$5:$E$32,"No")>0),1,0) -> 1 | X92: =IF(AND(O92=1,I92<Inputs!$B$4),1,0) -> 0 | Y92: =IF(AND(O92=1,T92>Inputs!$B$5),1,0) -> 1 | Z92: =IF(AND(O92=1,G92<>R92),1,0) -> 0 | AA92: =IF(AND(O92=1,M92=""),1,0) -> 0 | AB92: =IF(AND(E92="Closed Lost",N92=""),1,0) -> 0 | AC92: =SUM(U92:AB92) -> 2 | AD92: =IF(AC92=0,1,0) -> 0 | AE92: =IF(AND(O92=1,I92>=Inputs!$B$6,I92<=Inputs!$B$7),1,0) -> 1 | AF92: =IF(AND(E92="Closed Won",I92>=Inputs!$B$6,I92<=Inputs!$B$4),1,0) -> 0 | AG92: =IF(AND(O92=0,I92>Inputs!$B$4-Inputs!$B$8,I92<=Inputs!$B$4),1,0) -> 0 | AH92: =I92-H92 -> 366
A93: O00089 | B93: A0013 | C93: Kilimanjaro Capital | Assurance | readiness | D93: Assurance | E93: Closed Won | G93: 100 | H93: 46045 | I93: 46136 | J93: 46136 | K93: U005 | L93: Existing client | O93: =IF(OR(E93="Closed Won",E93="Closed Lost"),0,1) -> 0 | P93: =INDEX(Accounts!$K$5:$K$336,MATCH(B93,Accounts!$A$5:$A$336,0)) -> Financial Services | Q93: =INDEX(Accounts!$D$5:$D$336,MATCH(B93,Accounts!$A$5:$A$336,0)) -> Priority | R93: =INDEX(Inputs!$B$11:$B$16,MATCH(E93,Inputs!$A$11:$A$16,0)) -> 100 | S93: =IF(F93="",0,F93)*R93/100 -> 0 | T93: =Inputs!$B$4-J93 -> 178 | U93: =IF(OR(F93="",F93=0),1,0) -> 1 | V93: =IF(K93="",1,0) -> 0 | W93: =IF(AND(O93=1,K93<>"",COUNTIFS(Owners!$A$5:$A$32,K93,Owners!$E$5:$E$32,"No")>0),1,0) -> 0 | X93: =IF(AND(O93=1,I93<Inputs!$B$4),1,0) -> 0 | Y93: =IF(AND(O93=1,T93>Inputs!$B$5),1,0) -> 0 | Z93: =IF(AND(O93=1,G93<>R93),1,0) -> 0 | AA93: =IF(AND(O93=1,M93=""),1,0) -> 0 | AB93: =IF(AND(E93="Closed Lost",N93=""),1,0) -> 0 | AC93: =SUM(U93:AB93) -> 1 | AD93: =IF(AC93=0,1,0) -> 0 | AE93: =IF(AND(O93=1,I93>=Inputs!$B$6,I93<=Inputs!$B$7),1,0) -> 0 | AF93: =IF(AND(E93="Closed Won",I93>=Inputs!$B$6,I93<=Inputs!$B$4),1,0) -> 0 | AG93: =IF(AND(O93=0,I93>Inputs!$B$4-Inputs!$B$8,I93<=Inputs!$B$4),1,0) -> 1 | AH93: =I93-H93 -> 91
A94: O00090 | B94: A0291 | C94: Simba Sacco | Consulting | due diligence | D94: Consulting | E94: Closed Lost | F94: 78775000 | G94: 0 | H94: 46061 | I94: 46308 | J94: 46308 | K94: U025 | L94: Cold outreach | O94: =IF(OR(E94="Closed Won",E94="Closed Lost"),0,1) -> 0 | P94: =INDEX(Accounts!$K$5:$K$336,MATCH(B94,Accounts!$A$5:$A$336,0)) -> Financial Services | Q94: =INDEX(Accounts!$D$5:$D$336,MATCH(B94,Accounts!$A$5:$A$336,0)) -> Standard | R94: =INDEX(Inputs!$B$11:$B$16,MATCH(E94,Inputs!$A$11:$A$16,0)) -> 0 | S94: =IF(F94="",0,F94)*R94/100 -> 0 | T94: =Inputs!$B$4-J94 -> 6 | U94: =IF(OR(F94="",F94=0),1,0) -> 0 | V94: =IF(K94="",1,0) -> 0 | W94: =IF(AND(O94=1,K94<>"",COUNTIFS(Owners!$A$5:$A$32,K94,Owners!$E$5:$E$32,"No")>0),1,0) -> 0 | X94: =IF(AND(O94=1,I94<Inputs!$B$4),1,0) -> 0 | Y94: =IF(AND(O94=1,T94>Inputs!$B$5),1,0) -> 0 | Z94: =IF(AND(O94=1,G94<>R94),1,0) -> 0 | AA94: =IF(AND(O94=1,M94=""),1,0) -> 0 | AB94: =IF(AND(E94="Closed Lost",N94=""),1,0) -> 1 | AC94: =SUM(U94:AB94) -> 1 | AD94: =IF(AC94=0,1,0) -> 0 | AE94: =IF(AND(O94=1,I94>=Inputs!$B$6,I94<=Inputs!$B$7),1,0) -> 0 | AF94: =IF(AND(E94="Closed Won",I94>=Inputs!$B$6,I94<=Inputs!$B$4),1,0) -> 0 | AG94: =IF(AND(O94=0,I94>Inputs!$B$4-Inputs!$B$8,I94<=Inputs!$B$4),1,0) -> 1 | AH94: =I94-H94 -> 247
A95: O00091 | B95: A0077 | C95: Umoja Foods | Tax & Legal | annual | D95: Tax & Legal | E95: Closed Lost | F95: 5883000 | G95: 0 | H95: 45992 | I95: 46199 | J95: 46199 | K95: U009 | L95: Cold outreach | N95: No decision | O95: =IF(OR(E95="Closed Won",E95="Closed Lost"),0,1) -> 0 | P95: =INDEX(Accounts!$K$5:$K$336,MATCH(B95,Accounts!$A$5:$A$336,0)) -> Consumer & Retail | Q95: =INDEX(Accounts!$D$5:$D$336,MATCH(B95,Accounts!$A$5:$A$336,0)) -> Key | R95: =INDEX(Inputs!$B$11:$B$16,MATCH(E95,Inputs!$A$11:$A$16,0)) -> 0 | S95: =IF(F95="",0,F95)*R95/100 -> 0 | T95: =Inputs!$B$4-J95 -> 115 | U95: =IF(OR(F95="",F95=0),1,0) -> 0 | V95: =IF(K95="",1,0) -> 0 | W95: =IF(AND(O95=1,K95<>"",COUNTIFS(Owners!$A$5:$A$32,K95,Owners!$E$5:$E$32,"No")>0),1,0) -> 0 | X95: =IF(AND(O95=1,I95<Inputs!$B$4),1,0) -> 0 | Y95: =IF(AND(O95=1,T95>Inputs!$B$5),1,0) -> 0 | Z95: =IF(AND(O95=1,G95<>R95),1,0) -> 0 | AA95: =IF(AND(O95=1,M95=""),1,0) -> 0 | AB95: =IF(AND(E95="Closed Lost",N95=""),1,0) -> 0 | AC95: =SUM(U95:AB95) -> 0 | AD95: =IF(AC95=0,1,0) -> 1 | AE95: =IF(AND(O95=1,I95>=Inputs!$B$6,I95<=Inputs!$B$7),1,0) -> 0 | AF95: =IF(AND(E95="Closed Won",I95>=Inputs!$B$6,I95<=Inputs!$B$4),1,0) -> 0 | AG95: =IF(AND(O95=0,I95>Inputs!$B$4-Inputs!$B$8,I95<=Inputs!$B$4),1,0) -> 1 | AH95: =I95-H95 -> 207
A96: O00092 | B96: A0012 | C96: Safari Microfinance | Tax & Legal | review | D96: Tax & Legal | E96: Closed Lost | F96: 2668000 | G96: 0 | H96: 46051 | I96: 46238 | J96: 46238 | K96: U005 | L96: Event | N96: Scope change | O96: =IF(OR(E96="Closed Won",E96="Closed Lost"),0,1) -> 0 | P96: =INDEX(Accounts!$K$5:$K$336,MATCH(B96,Accounts!$A$5:$A$336,0)) -> Financial Services | Q96: =INDEX(Accounts!$D$5:$D$336,MATCH(B96,Accounts!$A$5:$A$336,0)) -> Priority | R96: =INDEX(Inputs!$B$11:$B$16,MATCH(E96,Inputs!$A$11:$A$16,0)) -> 0 | S96: =IF(F96="",0,F96)*R96/100 -> 0 | T96: =Inputs!$B$4-J96 -> 76 | U96: =IF(OR(F96="",F96=0),1,0) -> 0 | V96: =IF(K96="",1,0) -> 0 | W96: =IF(AND(O96=1,K96<>"",COUNTIFS(Owners!$A$5:$A$32,K96,Owners!$E$5:$E$32,"No")>0),1,0) -> 0 | X96: =IF(AND(O96=1,I96<Inputs!$B$4),1,0) -> 0 | Y96: =IF(AND(O96=1,T96>Inputs!$B$5),1,0) -> 0 | Z96: =IF(AND(O96=1,G96<>R96),1,0) -> 0 | AA96: =IF(AND(O96=1,M96=""),1,0) -> 0 | AB96: =IF(AND(E96="Closed Lost",N96=""),1,0) -> 0 | AC96: =SUM(U96:AB96) -> 0 | AD96: =IF(AC96=0,1,0) -> 1 | AE96: =IF(AND(O96=1,I96>=Inputs!$B$6,I96<=Inputs!$B$7),1,0) -> 0 | AF96: =IF(AND(E96="Closed Won",I96>=Inputs!$B$6,I96<=Inputs!$B$4),1,0) -> 0 | AG96: =IF(AND(O96=0,I96>Inputs!$B$4-Inputs!$B$8,I96<=Inputs!$B$4),1,0) -> 1 | AH96: =I96-H96 -> 187
A97: O00093 | B97: A0013 | C97: Kilimanjaro Capital | Deals | transformation | D97: Deals | E97: Closed Won | F97: 24527000 | G97: 100 | H97: 46242 | I97: 46308 | J97: 46308 | K97: U006 | L97: Digital | O97: =IF(OR(E97="Closed Won",E97="Closed Lost"),0,1) -> 0 | P97: =INDEX(Accounts!$K$5:$K$336,MATCH(B97,Accounts!$A$5:$A$336,0)) -> Financial Services | Q97: =INDEX(Accounts!$D$5:$D$336,MATCH(B97,Accounts!$A$5:$A$336,0)) -> Priority | R97: =INDEX(Inputs!$B$11:$B$16,MATCH(E97,Inputs!$A$11:$A$16,0)) -> 100 | S97: =IF(F97="",0,F97)*R97/100 -> 24527000 | T97: =Inputs!$B$4-J97 -> 6 | U97: =IF(OR(F97="",F97=0),1,0) -> 0 | V97: =IF(K97="",1,0) -> 0 | W97: =IF(AND(O97=1,K97<>"",COUNTIFS(Owners!$A$5:$A$32,K97,Owners!$E$5:$E$32,"No")>0),1,0) -> 0 | X97: =IF(AND(O97=1,I97<Inputs!$B$4),1,0) -> 0 | Y97: =IF(AND(O97=1,T97>Inputs!$B$5),1,0) -> 0 | Z97: =IF(AND(O97=1,G97<>R97),1,0) -> 0 | AA97: =IF(AND(O97=1,M97=""),1,0) -> 0 | AB97: =IF(AND(E97="Closed Lost",N97=""),1,0) -> 0 | AC97: =SUM(U97:AB97) -> 0 | AD97: =IF(AC97=0,1,0) -> 1 | AE97: =IF(AND(O97=1,I97>=Inputs!$B$6,I97<=Inputs!$B$7),1,0) -> 0 | AF97: =IF(AND(E97="Closed Won",I97>=Inputs!$B$6,I97<=Inputs!$B$4),1,0) -> 1 | AG97: =IF(AND(O97=0,I97>Inputs!$B$4-Inputs!$B$8,I97<=Inputs!$B$4),1,0) -> 1 | AH97: =I97-H97 -> 66
A98: O00094 | B98: A0088 | C98: Savanna Development Fund | Risk | advisory | D98: Risk | E98: Closed Lost | F98: 6565000 | G98: 0 | H98: 46031 | I98: 46131 | J98: 46131 | K98: U004 | L98: Event | N98: Scope change | O98: =IF(OR(E98="Closed Won",E98="Closed Lost"),0,1) -> 0 | P98: =INDEX(Accounts!$K$5:$K$336,MATCH(B98,Accounts!$A$5:$A$336,0)) -> Public Sector & Development | Q98: =INDEX(Accounts!$D$5:$D$336,MATCH(B98,Accounts!$A$5:$A$336,0)) -> Key | R98: =INDEX(Inputs!$B$11:$B$16,MATCH(E98,Inputs!$A$11:$A$16,0)) -> 0 | S98: =IF(F98="",0,F98)*R98/100 -> 0 | T98: =Inputs!$B$4-J98 -> 183 | U98: =IF(OR(F98="",F98=0),1,0) -> 0 | V98: =IF(K98="",1,0) -> 0 | W98: =IF(AND(O98=1,K98<>"",COUNTIFS(Owners!$A$5:$A$32,K98,Owners!$E$5:$E$32,"No")>0),1,0) -> 0 | X98: =IF(AND(O98=1,I98<Inputs!$B$4),1,0) -> 0 | Y98: =IF(AND(O98=1,T98>Inputs!$B$5),1,0) -> 0 | Z98: =IF(AND(O98=1,G98<>R98),1,0) -> 0 | AA98: =IF(AND(O98=1,M98=""),1,0) -> 0 | AB98: =IF(AND(E98="Closed Lost",N98=""),1,0) -> 0 | AC98: =SUM(U98:AB98) -> 0 | AD98: =IF(AC98=0,1,0) -> 1 | AE98: =IF(AND(O98=1,I98>=Inputs!$B$6,I98<=Inputs!$B$7),1,0) -> 0 | AF98: =IF(AND(E98="Closed Won",I98>=Inputs!$B$6,I98<=Inputs!$B$4),1,0) -> 0 | AG98: =IF(AND(O98=0,I98>Inputs!$B$4-Inputs!$B$8,I98<=Inputs!$B$4),1,0) -> 1 | AH98: =I98-H98 -> 100
A99: O00095 | B99: A0023 | C99: Jambo Petroleum | Tax & Legal | due diligence | D99: Tax & Legal | E99: Closed Won | F99: 5629000 | G99: 100 | H99: 46182 | I99: 46308 | J99: 46308 | K99: U006 | L99: Event | O99: =IF(OR(E99="Closed Won",E99="Closed Lost"),0,1) -> 0 | P99: =INDEX(Accounts!$K$5:$K$336,MATCH(B99,Accounts!$A$5:$A$336,0)) -> Energy & Resources | Q99: =INDEX(Accounts!$D$5:$D$336,MATCH(B99,Accounts!$A$5:$A$336,0)) -> Priority | R99: =INDEX(Inputs!$B$11:$B$16,MATCH(E99,Inputs!$A$11:$A$16,0)) -> 100 | S99: =IF(F99="",0,F99)*R99/100 -> 5629000 | T99: =Inputs!$B$4-J99 -> 6 | U99: =IF(OR(F99="",F99=0),1,0) -> 0 | V99: =IF(K99="",1,0) -> 0 | W99: =IF(AND(O99=1,K99<>"",COUNTIFS(Owners!$A$5:$A$32,K99,Owners!$E$5:$E$32,"No")>0),1,0) -> 0 | X99: =IF(AND(O99=1,I99<Inputs!$B$4),1,0) -> 0 | Y99: =IF(AND(O99=1,T99>Inputs!$B$5),1,0) -> 0 | Z99: =IF(AND(O99=1,G99<>R99),1,0) -> 0 | AA99: =IF(AND(O99=1,M99=""),1,0) -> 0 | AB99: =IF(AND(E99="Closed Lost",N99=""),1,0) -> 0 | AC99: =SUM(U99:AB99) -> 0 | AD99: =IF(AC99=0,1,0) -> 1 | AE99: =IF(AND(O99=1,I99>=Inputs!$B$6,I99<=Inputs!$B$7),1,0) -> 0 | AF99: =IF(AND(E99="Closed Won",I99>=Inputs!$B$6,I99<=Inputs!$B$4),1,0) -> 1 | AG99: =IF(AND(O99=0,I99>Inputs!$B$4-Inputs!$B$8,I99<=Inputs!$B$4),1,0) -> 1 | AH99: =I99-H99 -> 126
A100: O00096 | B100: A0307 | C100: Harambee Energy | Tax & Legal | readiness | D100: Tax & Legal | E100: Closed Won | F100: 9921000 | G100: 100 | H100: 46001 | I100: 46287 | J100: 46287 | K100: U019 | L100: Existing client | O100: =IF(OR(E100="Closed Won",E100="Closed Lost"),0,1) -> 0 | P100: =INDEX(Accounts!$K$5:$K$336,MATCH(B100,Accounts!$A$5:$A$336,0)) -> Energy & Resources | Q100: =INDEX(Accounts!$D$5:$D$336,MATCH(B100,Accounts!$A$5:$A$336,0)) -> Standard | R100: =INDEX(Inputs!$B$11:$B$16,MATCH(E100,Inputs!$A$11:$A$16,0)) -> 100 | S100: =IF(F100="",0,F100)*R100/100 -> 9921000 | T100: =Inputs!$B$4-J100 -> 27 | U100: =IF(OR(F100="",F100=0),1,0) -> 0 | V100: =IF(K100="",1,0) -> 0 | W100: =IF(AND(O100=1,K100<>"",COUNTIFS(Owners!$A$5:$A$32,K100,Owners!$E$5:$E$32,"No")>0),1,0) -> 0 | X100: =IF(AND(O100=1,I100<Inputs!$B$4),1,0) -> 0 | Y100: =IF(AND(O100=1,T100>Inputs!$B$5),1,0) -> 0 | Z100: =IF(AND(O100=1,G100<>R100),1,0) -> 0 | AA100: =IF(AND(O100=1,M100=""),1,0) -> 0 | AB100: =IF(AND(E100="Closed Lost",N100=""),1,0) -> 0 | AC100: =SUM(U100:AB100) -> 0 | AD100: =IF(AC100=0,1,0) -> 1 | AE100: =IF(AND(O100=1,I100>=Inputs!$B$6,I100<=Inputs!$B$7),1,0) -> 0 | AF100: =IF(AND(E100="Closed Won",I100>=Inputs!$B$6,I100<=Inputs!$B$4),1,0) -> 1 | AG100: =IF(AND(O100=0,I100>Inputs!$B$4-Inputs!$B$8,I100<=Inputs!$B$4),1,0) -> 1 | AH100: =I100-H100 -> 286
A101: O00097 | B101: A0025 | C101: Lakeview Bank | Risk | annual | D101: Risk | E101: Closed Won | F101: 3797000 | G101: 100 | H101: 45971 | I101: 46242 | J101: 46242 | K101: U028 | L101: Thought leadership | O101: =IF(OR(E101="Closed Won",E101="Closed Lost"),0,1) -> 0 | P101: =INDEX(Accounts!$K$5:$K$336,MATCH(B101,Accounts!$A$5:$A$336,0)) -> Financial Services | Q101: =INDEX(Accounts!$D$5:$D$336,MATCH(B101,Accounts!$A$5:$A$336,0)) -> Priority | R101: =INDEX(Inputs!$B$11:$B$16,MATCH(E101,Inputs!$A$11:$A$16,0)) -> 100 | S101: =IF(F101="",0,F101)*R101/100 -> 3797000 | T101: =Inputs!$B$4-J101 -> 72 | U101: =IF(OR(F101="",F101=0),1,0) -> 0 | V101: =IF(K101="",1,0) -> 0 | W101: =IF(AND(O101=1,K101<>"",COUNTIFS(Owners!$A$5:$A$32,K101,Owners!$E$5:$E$32,"No")>0),1,0) -> 0 | X101: =IF(AND(O101=1,I101<Inputs!$B$4),1,0) -> 0 | Y101: =IF(AND(O101=1,T101>Inputs!$B$5),1,0) -> 0 | Z101: =IF(AND(O101=1,G101<>R101),1,0) -> 0 | AA101: =IF(AND(O101=1,M101=""),1,0) -> 0 | AB101: =IF(AND(E101="Closed Lost",N101=""),1,0) -> 0 | AC101: =SUM(U101:AB101) -> 0 | AD101: =IF(AC101=0,1,0) -> 1 | AE101: =IF(AND(O101=1,I101>=Inputs!$B$6,I101<=Inputs!$B$7),1,0) -> 0 | AF101: =IF(AND(E101="Closed Won",I101>=Inputs!$B$6,I101<=Inputs!$B$4),1,0) -> 1 | AG101: =IF(AND(O101=0,I101>Inputs!$B$4-Inputs!$B$8,I101<=Inputs!$B$4),1,0) -> 1 | AH101: =I101-H101 -> 271
...

Sheet Accounts
A1: Accounts
A2: Raw export + normalised-name key [E] from Python. Duplicate flag and master ID are live formulas.
A4: Account ID | B4: Account name | C4: Industry (raw) | D4: Tier | E4: Type | F4: City | G4: Account driver | H4: Normalised name key [E] | I4: Duplicate? | J4: Master account ID | K4: Industry (clean) | L4: Missing industry?
A5: A0001 | B5: Jambo Microfinance Limited | C5: Financial Services | D5: Priority | E5: Listed company | F5: Nairobi | G5: U001 | H5: jambomicrofinance | I5: =IF(COUNTIF($H$5:$H$336,H5)>1,1,0) -> 0 | J5: =INDEX($A$5:$A$336,MATCH(H5,$H$5:$H$336,0)) -> A0001 | K5: =IF(C5<>"",C5,IF(INDEX($C$5:$C$336,MATCH(J5,$A$5:$A$336,0))<>"",INDEX($C$5:$C$336,MATCH(J5,$A$5:$A$336,0)),"Unassigned")) -> Financial Services | L5: =IF(C5="",1,0) -> 0
A6: A0002 | B6: Umoja Capital Limited | C6: Financial Services | D6: Priority | E6: Private company | F6: Mombasa | G6: U002 | H6: umojacapital | I6: =IF(COUNTIF($H$5:$H$336,H6)>1,1,0) -> 0 | J6: =INDEX($A$5:$A$336,MATCH(H6,$H$5:$H$336,0)) -> A0002 | K6: =IF(C6<>"",C6,IF(INDEX($C$5:$C$336,MATCH(J6,$A$5:$A$336,0))<>"",INDEX($C$5:$C$336,MATCH(J6,$A$5:$A$336,0)),"Unassigned")) -> Financial Services | L6: =IF(C6="",1,0) -> 0
A7: A0003 | B7: Nile Microfinance Limited | C7: Financial Services | D7: Priority | E7: Public sector | F7: Nairobi | G7: U003 | H7: nilemicrofinance | I7: =IF(COUNTIF($H$5:$H$336,H7)>1,1,0) -> 0 | J7: =INDEX($A$5:$A$336,MATCH(H7,$H$5:$H$336,0)) -> A0003 | K7: =IF(C7<>"",C7,IF(INDEX($C$5:$C$336,MATCH(J7,$A$5:$A$336,0))<>"",INDEX($C$5:$C$336,MATCH(J7,$A$5:$A$336,0)),"Unassigned")) -> Financial Services | L7: =IF(C7="",1,0) -> 0
A8: A0004 | B8: Pwani Asset Managers Limited | C8: Financial Services | D8: Priority | E8: NGO / development partner | F8: Nairobi | G8: U004 | H8: pwaniassetmanagers | I8: =IF(COUNTIF($H$5:$H$336,H8)>1,1,0) -> 0 | J8: =INDEX($A$5:$A$336,MATCH(H8,$H$5:$H$336,0)) -> A0004 | K8: =IF(C8<>"",C8,IF(INDEX($C$5:$C$336,MATCH(J8,$A$5:$A$336,0))<>"",INDEX($C$5:$C$336,MATCH(J8,$A$5:$A$336,0)),"Unassigned")) -> Financial Services | L8: =IF(C8="",1,0) -> 0
A9: A0005 | B9: Twiga Agri Limited | C9: Agribusiness | D9: Priority | E9: Private company | F9: Nairobi | G9: U005 | H9: twigaagri | I9: =IF(COUNTIF($H$5:$H$336,H9)>1,1,0) -> 0 | J9: =INDEX($A$5:$A$336,MATCH(H9,$H$5:$H$336,0)) -> A0005 | K9: =IF(C9<>"",C9,IF(INDEX($C$5:$C$336,MATCH(J9,$A$5:$A$336,0))<>"",INDEX($C$5:$C$336,MATCH(J9,$A$5:$A$336,0)),"Unassigned")) -> Agribusiness | L9: =IF(C9="",1,0) -> 0
A10: A0006 | B10: Kibo Microfinance Limited | C10: Financial Services | D10: Priority | E10: Private company | F10: Nairobi | G10: U006 | H10: kibomicrofinance | I10: =IF(COUNTIF($H$5:$H$336,H10)>1,1,0) -> 0 | J10: =INDEX($A$5:$A$336,MATCH(H10,$H$5:$H$336,0)) -> A0006 | K10: =IF(C10<>"",C10,IF(INDEX($C$5:$C$336,MATCH(J10,$A$5:$A$336,0))<>"",INDEX($C$5:$C$336,MATCH(J10,$A$5:$A$336,0)),"Unassigned")) -> Financial Services | L10: =IF(C10="",1,0) -> 0
A11: A0007 | B11: Nile County Government | C11: Public Sector & Development | D11: Priority | E11: Private company | F11: Nairobi | G11: U007 | H11: nilecountygovernment | I11: =IF(COUNTIF($H$5:$H$336,H11)>1,1,0) -> 0 | J11: =INDEX($A$5:$A$336,MATCH(H11,$H$5:$H$336,0)) -> A0007 | K11: =IF(C11<>"",C11,IF(INDEX($C$5:$C$336,MATCH(J11,$A$5:$A$336,0))<>"",INDEX($C$5:$C$336,MATCH(J11,$A$5:$A$336,0)),"Unassigned")) -> Public Sector & Development | L11: =IF(C11="",1,0) -> 0
A12: A0008 | B12: Tembo Capital Limited | C12: Financial Services | D12: Priority | E12: Public sector | F12: Nairobi | G12: U001 | H12: tembocapital | I12: =IF(COUNTIF($H$5:$H$336,H12)>1,1,0) -> 0 | J12: =INDEX($A$5:$A$336,MATCH(H12,$H$5:$H$336,0)) -> A0008 | K12: =IF(C12<>"",C12,IF(INDEX($C$5:$C$336,MATCH(J12,$A$5:$A$336,0))<>"",INDEX($C$5:$C$336,MATCH(J12,$A$5:$A$336,0)),"Unassigned")) -> Financial Services | L12: =IF(C12="",1,0) -> 0
A13: A0009 | B13: Rift Cloud Limited | C13: Technology, Media & Telecom | D13: Priority | E13: Private company | F13: Nairobi | G13: U002 | H13: riftcloud | I13: =IF(COUNTIF($H$5:$H$336,H13)>1,1,0) -> 0 | J13: =INDEX($A$5:$A$336,MATCH(H13,$H$5:$H$336,0)) -> A0009 | K13: =IF(C13<>"",C13,IF(INDEX($C$5:$C$336,MATCH(J13,$A$5:$A$336,0))<>"",INDEX($C$5:$C$336,MATCH(J13,$A$5:$A$336,0)),"Unassigned")) -> Technology, Media & Telecom | L13: =IF(C13="",1,0) -> 0
A14: A0010 | B14: Umoja Asset Managers Limited | C14: Financial Services | D14: Priority | E14: Private company | F14: Kisumu | G14: U003 | H14: umojaassetmanagers | I14: =IF(COUNTIF($H$5:$H$336,H14)>1,1,0) -> 0 | J14: =INDEX($A$5:$A$336,MATCH(H14,$H$5:$H$336,0)) -> A0010 | K14: =IF(C14<>"",C14,IF(INDEX($C$5:$C$336,MATCH(J14,$A$5:$A$336,0))<>"",INDEX($C$5:$C$336,MATCH(J14,$A$5:$A$336,0)),"Unassigned")) -> Financial Services | L14: =IF(C14="",1,0) -> 0
A15: A0011 | B15: Rift Capital Limited | C15: Financial Services | D15: Priority | E15: Private company | F15: Nairobi | G15: U004 | H15: riftcapital | I15: =IF(COUNTIF($H$5:$H$336,H15)>1,1,0) -> 0 | J15: =INDEX($A$5:$A$336,MATCH(H15,$H$5:$H$336,0)) -> A0011 | K15: =IF(C15<>"",C15,IF(INDEX($C$5:$C$336,MATCH(J15,$A$5:$A$336,0))<>"",INDEX($C$5:$C$336,MATCH(J15,$A$5:$A$336,0)),"Unassigned")) -> Financial Services | L15: =IF(C15="",1,0) -> 0
A16: A0012 | B16: Safari Microfinance Limited | C16: Financial Services | D16: Priority | E16: NGO / development partner | F16: Nairobi | G16: U005 | H16: safarimicrofinance | I16: =IF(COUNTIF($H$5:$H$336,H16)>1,1,0) -> 0 | J16: =INDEX($A$5:$A$336,MATCH(H16,$H$5:$H$336,0)) -> A0012 | K16: =IF(C16<>"",C16,IF(INDEX($C$5:$C$336,MATCH(J16,$A$5:$A$336,0))<>"",INDEX($C$5:$C$336,MATCH(J16,$A$5:$A$336,0)),"Unassigned")) -> Financial Services | L16: =IF(C16="",1,0) -> 0
... A34: A0030 | B34: Nile Networks Limited | C34: Technology, Media & Telecom | D34: Priority | E34: Private company | F34: Nairobi | G34: U002 | H34: nilenetworks | I34: =IF(COUNTIF($H$5:$H$336,H34)>1,1,0) -> 0 | J34: =INDEX($A$5:$A$336,MATCH(H34,$H$5:$H$336,0)) -> A0030 | K34: =IF(C34<>"",C34,IF(INDEX($C$5:$C$336,MATCH(J34,$A$5:$A$336,0))<>"",INDEX($C$5:$C$336,MATCH(J34,$A$5:$A$336,0)),"Unassigned")) -> Technology, Media & Telecom | L34: =IF(C34="",1,0) -> 0
A35: A0031 | B35: Acacia Hospital Limited | D35: Priority | E35: Private company | F35: Mombasa | G35: U003 | H35: acaciahospital | I35: =IF(COUNTIF($H$5:$H$336,H35)>1,1,0) -> 1 | J35: =INDEX($A$5:$A$336,MATCH(H35,$H$5:$H$336,0)) -> A0031 | K35: =IF(C35<>"",C35,IF(INDEX($C$5:$C$336,MATCH(J35,$A$5:$A$336,0))<>"",INDEX($C$5:$C$336,MATCH(J35,$A$5:$A$336,0)),"Unassigned")) -> Unassigned | L35: =IF(C35="",1,0) -> 1
A36: A0032 | B36: Jambo Tea Estates Limited | C36: Agribusiness | D36: Priority | E36: Multinational subsidiary | F36: Nairobi | G36: U004 | H36: jamboteaestates | I36: =IF(COUNTIF($H$5:$H$336,H36)>1,1,0) -> 0 | J36: =INDEX($A$5:$A$336,MATCH(H36,$H$5:$H$336,0)) -> A0032 | K36: =IF(C36<>"",C36,IF(INDEX($C$5:$C$336,MATCH(J36,$A$5:$A$336,0))<>"",INDEX($C$5:$C$336,MATCH(J36,$A$5:$A$336,0)),"Unassigned")) -> Agribusiness | L36: =IF(C36="",1,0) -> 0
A37: A0033 | B37: Twiga Horticulture Limited | C37: Agribusiness | D37: Priority | E37: Private company | F37: Nairobi | G37: U005 | H37: twigahorticulture | I37: =IF(COUNTIF($H$5:$H$336,H37)>1,1,0) -> 0 | J37: =INDEX($A$5:$A$336,MATCH(H37,$H$5:$H$336,0)) -> A0033 | K37: =IF(C37<>"",C37,IF(INDEX($C$5:$C$336,MATCH(J37,$A$5:$A$336,0))<>"",INDEX($C$5:$C$336,MATCH(J37,$A$5:$A$336,0)),"Unassigned")) -> Agribusiness | L37: =IF(C37="",1,0) -> 0
A38: A0034 | B38: Harambee Capital Limited | C38: Financial Services | D38: Priority | E38: Private company | F38: Kisumu | G38: U006 | H38: harambeecapital | I38: =IF(COUNTIF($H$5:$H$336,H38)>1,1,0) -> 0 | J38: =INDEX($A$5:$A$336,MATCH(H38,$H$5:$H$336,0)) -> A0034 | K38: =IF(C38<>"",C38,IF(INDEX($C$5:$C$336,MATCH(J38,$A$5:$A$336,0))<>"",INDEX($C$5:$C$336,MATCH(J38,$A$5:$A$336,0)),"Unassigned")) -> Financial Services | L38: =IF(C38="",1,0) -> 0
A39: A0035 | B39: Kilimanjaro Media Limited | C39: Technology, Media & Telecom | D39: Priority | E39: Private company | F39: Nairobi | G39: U007 | H39: kilimanjaromedia | I39: =IF(COUNTIF($H$5:$H$336,H39)>1,1,0) -> 0 | J39: =INDEX($A$5:$A$336,MATCH(H39,$H$5:$H$336,0)) -> A0035 | K39: =IF(C39<>"",C39,IF(INDEX($C$5:$C$336,MATCH(J39,$A$5:$A$336,0))<>"",INDEX($C$5:$C$336,MATCH(J39,$A$5:$A$336,0)),"Unassigned")) -> Technology, Media & Telecom | L39: =IF(C39="",1,0) -> 0
A40: A0036 | B40: Amani Authority | C40: Public Sector & Development | D40: Priority | E40: NGO / development partner | F40: Nairobi | G40: U001 | H40: amaniauthority | I40: =IF(COUNTIF($H$5:$H$336,H40)>1,1,0) -> 0 | J40: =INDEX($A$5:$A$336,MATCH(H40,$H$5:$H$336,0)) -> A0036 | K40: =IF(C40<>"",C40,IF(INDEX($C$5:$C$336,MATCH(J40,$A$5:$A$336,0))<>"",INDEX($C$5:$C$336,MATCH(J40,$A$5:$A$336,0)),"Unassigned")) -> Public Sector & Development | L40: =IF(C40="",1,0) -> 0
A41: A0037 | B41: Zuri Hotels Limited | D41: Priority | E41: Private company | F41: Mombasa | G41: U002 | H41: zurihotels | I41: =IF(COUNTIF($H$5:$H$336,H41)>1,1,0) -> 0 | J41: =INDEX($A$5:$A$336,MATCH(H41,$H$5:$H$336,0)) -> A0037 | K41: =IF(C41<>"",C41,IF(INDEX($C$5:$C$336,MATCH(J41,$A$5:$A$336,0))<>"",INDEX($C$5:$C$336,MATCH(J41,$A$5:$A$336,0)),"Unassigned")) -> Unassigned | L41: =IF(C41="",1,0) -> 1
A42: A0038 | B42: Pwani Media Limited | C42: Technology, Media & Telecom | D42: Priority | E42: NGO / development partner | F42: Nairobi | G42: U003 | H42: pwanimedia | I42: =IF(COUNTIF($H$5:$H$336,H42)>1,1,0) -> 0 | J42: =INDEX($A$5:$A$336,MATCH(H42,$H$5:$H$336,0)) -> A0038 | K42: =IF(C42<>"",C42,IF(INDEX($C$5:$C$336,MATCH(J42,$A$5:$A$336,0))<>"",INDEX($C$5:$C$336,MATCH(J42,$A$5:$A$336,0)),"Unassigned")) -> Technology, Media & Telecom | L42: =IF(C42="",1,0) -> 0
A43: A0039 | B43: Baobab Power Limited | C43: Energy & Resources | D43: Priority | E43: Private company | F43: Kisumu | G43: U004 | H43: baobabpower | I43: =IF(COUNTIF($H$5:$H$336,H43)>1,1,0) -> 0 | J43: =INDEX($A$5:$A$336,MATCH(H43,$H$5:$H$336,0)) -> A0039 | K43: =IF(C43<>"",C43,IF(INDEX($C$5:$C$336,MATCH(J43,$A$5:$A$336,0))<>"",INDEX($C$5:$C$336,MATCH(J43,$A$5:$A$336,0)),"Unassigned")) -> Energy & Resources | L43: =IF(C43="",1,0) -> 0
A44: A0040 | B44: Amani Insurance Limited | C44: Financial Services | D44: Priority | E44: Private company | F44: Nairobi | G44: U005 | H44: amaniinsurance | I44: =IF(COUNTIF($H$5:$H$336,H44)>1,1,0) -> 0 | J44: =INDEX($A$5:$A$336,MATCH(H44,$H$5:$H$336,0)) -> A0040 | K44: =IF(C44<>"",C44,IF(INDEX($C$5:$C$336,MATCH(J44,$A$5:$A$336,0))<>"",INDEX($C$5:$C$336,MATCH(J44,$A$5:$A$336,0)),"Unassigned")) -> Financial Services | L44: =IF(C44="",1,0) -> 0
A45: A0041 | B45: Simba Foods Limited | C45: Consumer & Retail | D45: Key | E45: Private company | F45: Eldoret | G45: U024 | H45: simbafoods | I45: =IF(COUNTIF($H$5:$H$336,H45)>1,1,0) -> 0 | J45: =INDEX($A$5:$A$336,MATCH(H45,$H$5:$H$336,0)) -> A0041 | K45: =IF(C45<>"",C45,IF(INDEX($C$5:$C$336,MATCH(J45,$A$5:$A$336,0))<>"",INDEX($C$5:$C$336,MATCH(J45,$A$5:$A$336,0)),"Unassigned")) -> Consumer & Retail | L45: =IF(C45="",1,0) -> 0
A46: A0042 | B46: Amani Media Limited | C46: Technology, Media & Telecom | D46: Key | E46: Private company | F46: Nairobi | G46: U010 | H46: amanimedia | I46: =IF(COUNTIF($H$5:$H$336,H46)>1,1,0) -> 0 | J46: =INDEX($A$5:$A$336,MATCH(H46,$H$5:$H$336,0)) -> A0042 | K46: =IF(C46<>"",C46,IF(INDEX($C$5:$C$336,MATCH(J46,$A$5:$A$336,0))<>"",INDEX($C$5:$C$336,MATCH(J46,$A$5:$A$336,0)),"Unassigned")) -> Technology, Media & Telecom | L46: =IF(C46="",1,0) -> 0
A47: A0043 | B47: Zuri Power Limited | C47: Energy & Resources | D47: Key | E47: Multinational subsidiary | F47: Nairobi | G47: U012 | H47: zuripower | I47: =IF(COUNTIF($H$5:$H$336,H47)>1,1,0) -> 0 | J47: =INDEX($A$5:$A$336,MATCH(H47,$H$5:$H$336,0)) -> A0043 | K47: =IF(C47<>"",C47,IF(INDEX($C$5:$C$336,MATCH(J47,$A$5:$A$336,0))<>"",INDEX($C$5:$C$336,MATCH(J47,$A$5:$A$336,0)),"Unassigned")) -> Energy & Resources | L47: =IF(C47="",1,0) -> 0
A48: A0044 | B48: Harambee Commission | C48: Public Sector & Development | D48: Key | E48: Private company | F48: Eldoret | G48: U006 | H48: harambeecommission | I48: =IF(COUNTIF($H$5:$H$336,H48)>1,1,0) -> 0 | J48: =INDEX($A$5:$A$336,MATCH(H48,$H$5:$H$336,0)) -> A0044 | K48: =IF(C48<>"",C48,IF(INDEX($C$5:$C$336,MATCH(J48,$A$5:$A$336,0))<>"",INDEX($C$5:$C$336,MATCH(J48,$A$5:$A$336,0)),"Unassigned")) -> Public Sector & Development | L48: =IF(C48="",1,0) -> 0
A49: A0045 | B49: Acacia Infrastructure Limited | C49: Real Estate & Infrastructure | D49: Key | E49: Private company | F49: Nairobi | G49: U004 | H49: acaciainfrastructure | I49: =IF(COUNTIF($H$5:$H$336,H49)>1,1,0) -> 0 | J49: =INDEX($A$5:$A$336,MATCH(H49,$H$5:$H$336,0)) -> A0045 | K49: =IF(C49<>"",C49,IF(INDEX($C$5:$C$336,MATCH(J49,$A$5:$A$336,0))<>"",INDEX($C$5:$C$336,MATCH(J49,$A$5:$A$336,0)),"Unassigned")) -> Real Estate & Infrastructure | L49: =IF(C49="",1,0) -> 0
A50: A0046 | B50: Nyota Telecom Limited | C50: Technology, Media & Telecom | D50: Key | E50: NGO / development partner | F50: Nairobi | G50: U025 | H50: nyotatelecom | I50: =IF(COUNTIF($H$5:$H$336,H50)>1,1,0) -> 0 | J50: =INDEX($A$5:$A$336,MATCH(H50,$H$5:$H$336,0)) -> A0046 | K50: =IF(C50<>"",C50,IF(INDEX($C$5:$C$336,MATCH(J50,$A$5:$A$336,0))<>"",INDEX($C$5:$C$336,MATCH(J50,$A$5:$A$336,0)),"Unassigned")) -> Technology, Media & Telecom | L50: =IF(C50="",1,0) -> 0
A51: A0047 | B51: Acacia Properties Limited | C51: Real Estate & Infrastructure | D51: Key | E51: Private company | F51: Nairobi | G51: U002 | H51: acaciaproperties | I51: =IF(COUNTIF($H$5:$H$336,H51)>1,1,0) -> 0 | J51: =INDEX($A$5:$A$336,MATCH(H51,$H$5:$H$336,0)) -> A0047 | K51: =IF(C51<>"",C51,IF(INDEX($C$5:$C$336,MATCH(J51,$A$5:$A$336,0))<>"",INDEX($C$5:$C$336,MATCH(J51,$A$5:$A$336,0)),"Unassigned")) -> Real Estate & Infrastructure | L51: =IF(C51="",1,0) -> 0
A52: A0048 | B52: Safari Pharma Limited | C52: Health | D52: Key | E52: Listed company | F52: Nairobi | G52: U004 | H52: safaripharma | I52: =IF(COUNTIF($H$5:$H$336,H52)>1,1,0) -> 0 | J52: =INDEX($A$5:$A$336,MATCH(H52,$H$5:$H$336,0)) -> A0048 | K52: =IF(C52<>"",C52,IF(INDEX($C$5:$C$336,MATCH(J52,$A$5:$A$336,0))<>"",INDEX($C$5:$C$336,MATCH(J52,$A$5:$A$336,0)),"Unassigned")) -> Health | L52: =IF(C52="",1,0) -> 0
A53: A0049 | B53: Baobab Agri Limited | C53: Agribusiness | D53: Key | E53: Private company | F53: Nairobi | G53: U008 | H53: baobabagri | I53: =IF(COUNTIF($H$5:$H$336,H53)>1,1,0) -> 0 | J53: =INDEX($A$5:$A$336,MATCH(H53,$H$5:$H$336,0)) -> A0049 | K53: =IF(C53<>"",C53,IF(INDEX($C$5:$C$336,MATCH(J53,$A$5:$A$336,0))<>"",INDEX($C$5:$C$336,MATCH(J53,$A$5:$A$336,0)),"Unassigned")) -> Agribusiness | L53: =IF(C53="",1,0) -> 0
... A56: A0052 | B56: Highland Telecom Limited | C56: Technology, Media & Telecom | D56: Key | E56: Public sector | F56: Nairobi | G56: U026 | H56: highlandtelecom | I56: =IF(COUNTIF($H$5:$H$336,H56)>1,1,0) -> 0 | J56: =INDEX($A$5:$A$336,MATCH(H56,$H$5:$H$336,0)) -> A0052 | K56: =IF(C56<>"",C56,IF(INDEX($C$5:$C$336,MATCH(J56,$A$5:$A$336,0))<>"",INDEX($C$5:$C$336,MATCH(J56,$A$5:$A$336,0)),"Unassigned")) -> Technology, Media & Telecom | L56: =IF(C56="",1,0) -> 0
A57: A0053 | B57: Jambo Insurance Limited | D57: Key | E57: Public sector | F57: Nakuru | G57: U005 | H57: jamboinsurance | I57: =IF(COUNTIF($H$5:$H$336,H57)>1,1,0) -> 0 | J57: =INDEX($A$5:$A$336,MATCH(H57,$H$5:$H$336,0)) -> A0053 | K57: =IF(C57<>"",C57,IF(INDEX($C$5:$C$336,MATCH(J57,$A$5:$A$336,0))<>"",INDEX($C$5:$C$336,MATCH(J57,$A$5:$A$336,0)),"Unassigned")) -> Unassigned | L57: =IF(C57="",1,0) -> 1
A58: A0054 | B58: Equator Telecom Limited | C58: Technology, Media & Telecom | D58: Key | E58: Public sector | F58: Mombasa | G58: U011 | H58: equatortelecom | I58: =IF(COUNTIF($H$5:$H$336,H58)>1,1,0) -> 0 | J58: =INDEX($A$5:$A$336,MATCH(H58,$H$5:$H$336,0)) -> A0054 | K58: =IF(C58<>"",C58,IF(INDEX($C$5:$C$336,MATCH(J58,$A$5:$A$336,0))<>"",INDEX($C$5:$C$336,MATCH(J58,$A$5:$A$336,0)),"Unassigned")) -> Technology, Media & Telecom | L58: =IF(C58="",1,0) -> 0
A59: A0055 | B59: Kibo Commission | C59: Public Sector & Development | D59: Key | E59: Public sector | F59: Nairobi | G59: U025 | H59: kibocommission | I59: =IF(COUNTIF($H$5:$H$336,H59)>1,1,0) -> 0 | J59: =INDEX($A$5:$A$336,MATCH(H59,$H$5:$H$336,0)) -> A0055 | K59: =IF(C59<>"",C59,IF(INDEX($C$5:$C$336,MATCH(J59,$A$5:$A$336,0))<>"",INDEX($C$5:$C$336,MATCH(J59,$A$5:$A$336,0)),"Unassigned")) -> Public Sector & Development | L59: =IF(C59="",1,0) -> 0
A60: A0056 | B60: Amani Petroleum Limited | C60: Energy & Resources | D60: Key | E60: Listed company | F60: Nairobi | G60: U001 | H60: amanipetroleum | I60: =IF(COUNTIF($H$5:$H$336,H60)>1,1,0) -> 0 | J60: =INDEX($A$5:$A$336,MATCH(H60,$H$5:$H$336,0)) -> A0056 | K60: =IF(C60<>"",C60,IF(INDEX($C$5:$C$336,MATCH(J60,$A$5:$A$336,0))<>"",INDEX($C$5:$C$336,MATCH(J60,$A$5:$A$336,0)),"Unassigned")) -> Energy & Resources | L60: =IF(C60="",1,0) -> 0
A61: A0057 | B61: Mto Supermarkets Limited | C61: Consumer & Retail | D61: Key | E61: Listed company | F61: Kisumu | G61: U002 | H61: mtosupermarkets | I61: =IF(COUNTIF($H$5:$H$336,H61)>1,1,0) -> 0 | J61: =INDEX($A$5:$A$336,MATCH(H61,$H$5:$H$336,0)) -> A0057 | K61: =IF(C61<>"",C61,IF(INDEX($C$5:$C$336,MATCH(J61,$A$5:$A$336,0))<>"",INDEX($C$5:$C$336,MATCH(J61,$A$5:$A$336,0)),"Unassigned")) -> Consumer & Retail | L61: =IF(C61="",1,0) -> 0
A62: A0058 | B62: Rift Energy Limited | C62: Energy & Resources | D62: Key | E62: Public sector | F62: Nakuru | G62: U021 | H62: riftenergy | I62: =IF(COUNTIF($H$5:$H$336,H62)>1,1,0) -> 0 | J62: =INDEX($A$5:$A$336,MATCH(H62,$H$5:$H$336,0)) -> A0058 | K62: =IF(C62<>"",C62,IF(INDEX($C$5:$C$336,MATCH(J62,$A$5:$A$336,0))<>"",INDEX($C$5:$C$336,MATCH(J62,$A$5:$A$336,0)),"Unassigned")) -> Energy & Resources | L62: =IF(C62="",1,0) -> 0
A63: A0059 | B63: Nile Energy Limited | C63: Energy & Resources | D63: Key | E63: Private company | F63: Nakuru | G63: U019 | H63: nileenergy | I63: =IF(COUNTIF($H$5:$H$336,H63)>1,1,0) -> 0 | J63: =INDEX($A$5:$A$336,MATCH(H63,$H$5:$H$336,0)) -> A0059 | K63: =IF(C63<>"",C63,IF(INDEX($C$5:$C$336,MATCH(J63,$A$5:$A$336,0))<>"",INDEX($C$5:$C$336,MATCH(J63,$A$5:$A$336,0)),"Unassigned")) -> Energy & Resources | L63: =IF(C63="",1,0) -> 0
A64: A0060 | B64: Simba Development Fund | C64: Public Sector & Development | D64: Key | E64: Private company | F64: Nakuru | G64: U005 | H64: simbadevelopmentfund | I64: =IF(COUNTIF($H$5:$H$336,H64)>1,1,0) -> 0 | J64: =INDEX($A$5:$A$336,MATCH(H64,$H$5:$H$336,0)) -> A0060 | K64: =IF(C64<>"",C64,IF(INDEX($C$5:$C$336,MATCH(J64,$A$5:$A$336,0))<>"",INDEX($C$5:$C$336,MATCH(J64,$A$5:$A$336,0)),"Unassigned")) -> Public Sector & Development | L64: =IF(C64="",1,0) -> 0
A65: A0061 | B65: Mara Petroleum Limited | C65: Energy & Resources | D65: Key | E65: Private company | F65: Nairobi | G65: U019 | H65: marapetroleum | I65: =IF(COUNTIF($H$5:$H$336,H65)>1,1,0) -> 0 | J65: =INDEX($A$5:$A$336,MATCH(H65,$H$5:$H$336,0)) -> A0061 | K65: =IF(C65<>"",C65,IF(INDEX($C$5:$C$336,MATCH(J65,$A$5:$A$336,0))<>"",INDEX($C$5:$C$336,MATCH(J65,$A$5:$A$336,0)),"Unassigned")) -> Energy & Resources | L65: =IF(C65="",1,0) -> 0
A66: A0062 | B66: Safari Digital Limited | C66: Technology, Media & Telecom | D66: Key | E66: Multinational subsidiary | F66: Nairobi | G66: U021 | H66: safaridigital | I66: =IF(COUNTIF($H$5:$H$336,H66)>1,1,0) -> 0 | J66: =INDEX($A$5:$A$336,MATCH(H66,$H$5:$H$336,0)) -> A0062 | K66: =IF(C66<>"",C66,IF(INDEX($C$5:$C$336,MATCH(J66,$A$5:$A$336,0))<>"",INDEX($C$5:$C$336,MATCH(J66,$A$5:$A$336,0)),"Unassigned")) -> Technology, Media & Telecom | L66: =IF(C66="",1,0) -> 0
A67: A0063 | B67: Simba Supermarkets Limited | C67: Consumer & Retail | D67: Key | E67: Listed company | F67: Nakuru | G67: U018 | H67: simbasupermarkets | I67: =IF(COUNTIF($H$5:$H$336,H67)>1,1,0) -> 0 | J67: =INDEX($A$5:$A$336,MATCH(H67,$H$5:$H$336,0)) -> A0063 | K67: =IF(C67<>"",C67,IF(INDEX($C$5:$C$336,MATCH(J67,$A$5:$A$336,0))<>"",INDEX($C$5:$C$336,MATCH(J67,$A$5:$A$336,0)),"Unassigned")) -> Consumer & Retail | L67: =IF(C67="",1,0) -> 0
A68: A0064 | B68: Twiga Insurance Limited | C68: Financial Services | D68: Key | E68: Private company | F68: Nairobi | G68: U019 | H68: twigainsurance | I68: =IF(COUNTIF($H$5:$H$336,H68)>1,1,0) -> 0 | J68: =INDEX($A$5:$A$336,MATCH(H68,$H$5:$H$336,0)) -> A0064 | K68: =IF(C68<>"",C68,IF(INDEX($C$5:$C$336,MATCH(J68,$A$5:$A$336,0))<>"",INDEX($C$5:$C$336,MATCH(J68,$A$5:$A$336,0)),"Unassigned")) -> Financial Services | L68: =IF(C68="",1,0) -> 0
A69: A0065 | B69: Baobab Telecom Limited | C69: Technology, Media & Telecom | D69: Key | E69: NGO / development partner | F69: Nakuru | G69: U020 | H69: baobabtelecom | I69: =IF(COUNTIF($H$5:$H$336,H69)>1,1,0) -> 0 | J69: =INDEX($A$5:$A$336,MATCH(H69,$H$5:$H$336,0)) -> A0065 | K69: =IF(C69<>"",C69,IF(INDEX($C$5:$C$336,MATCH(J69,$A$5:$A$336,0))<>"",INDEX($C$5:$C$336,MATCH(J69,$A$5:$A$336,0)),"Unassigned")) -> Technology, Media & Telecom | L69: =IF(C69="",1,0) -> 0
... A83: A0079 | B83: Equator Sacco Limited | C83: Financial Services | D83: Key | E83: Multinational subsidiary | F83: Mombasa | G83: U019 | H83: equatorsacco | I83: =IF(COUNTIF($H$5:$H$336,H83)>1,1,0) -> 0 | J83: =INDEX($A$5:$A$336,MATCH(H83,$H$5:$H$336,0)) -> A0079 | K83: =IF(C83<>"",C83,IF(INDEX($C$5:$C$336,MATCH(J83,$A$5:$A$336,0))<>"",INDEX($C$5:$C$336,MATCH(J83,$A$5:$A$336,0)),"Unassigned")) -> Financial Services | L83: =IF(C83="",1,0) -> 0
A84: A0080 | B84: Harambee Cloud Limited | D84: Key | E84: Multinational subsidiary | F84: Nairobi | G84: U015 | H84: harambeecloud | I84: =IF(COUNTIF($H$5:$H$336,H84)>1,1,0) -> 0 | J84: =INDEX($A$5:$A$336,MATCH(H84,$H$5:$H$336,0)) -> A0080 | K84: =IF(C84<>"",C84,IF(INDEX($C$5:$C$336,MATCH(J84,$A$5:$A$336,0))<>"",INDEX($C$5:$C$336,MATCH(J84,$A$5:$A$336,0)),"Unassigned")) -> Unassigned | L84: =IF(C84="",1,0) -> 1
A85: A0081 | B85: Pwani Mining Limited | C85: Energy & Resources | D85: Key | E85: Private company | F85: Nairobi | G85: U027 | H85: pwanimining | I85: =IF(COUNTIF($H$5:$H$336,H85)>1,1,0) -> 0 | J85: =INDEX($A$5:$A$336,MATCH(H85,$H$5:$H$336,0)) -> A0081 | K85: =IF(C85<>"",C85,IF(INDEX($C$5:$C$336,MATCH(J85,$A$5:$A$336,0))<>"",INDEX($C$5:$C$336,MATCH(J85,$A$5:$A$336,0)),"Unassigned")) -> Energy & Resources | L85: =IF(C85="",1,0) -> 0
A86: A0082 | B86: Nile Beverages Limited | C86: Consumer & Retail | D86: Key | E86: Multinational subsidiary | F86: Mombasa | G86: U005 | H86: nilebeverages | I86: =IF(COUNTIF($H$5:$H$336,H86)>1,1,0) -> 0 | J86: =INDEX($A$5:$A$336,MATCH(H86,$H$5:$H$336,0)) -> A0082 | K86: =IF(C86<>"",C86,IF(INDEX($C$5:$C$336,MATCH(J86,$A$5:$A$336,0))<>"",INDEX($C$5:$C$336,MATCH(J86,$A$5:$A$336,0)),"Unassigned")) -> Consumer & Retail | L86: =IF(C86="",1,0) -> 0
A87: A0083 | B87: Lakeview Foods Limited | C87: Consumer & Retail | D87: Key | E87: Listed company | F87: Nairobi | G87: U020 | H87: lakeviewfoods | I87: =IF(COUNTIF($H$5:$H$336,H87)>1,1,0) -> 0 | J87: =INDEX($A$5:$A$336,MATCH(H87,$H$5:$H$336,0)) -> A0083 | K87: =IF(C87<>"",C87,IF(INDEX($C$5:$C$336,MATCH(J87,$A$5:$A$336,0))<>"",INDEX($C$5:$C$336,MATCH(J87,$A$5:$A$336,0)),"Unassigned")) -> Consumer & Retail | L87: =IF(C87="",1,0) -> 0
A88: A0084 | B88: Simba Digital Limited | C88: Technology, Media & Telecom | D88: Key | E88: Private company | F88: Nairobi | G88: U021 | H88: simbadigital | I88: =IF(COUNTIF($H$5:$H$336,H88)>1,1,0) -> 0 | J88: =INDEX($A$5:$A$336,MATCH(H88,$H$5:$H$336,0)) -> A0084 | K88: =IF(C88<>"",C88,IF(INDEX($C$5:$C$336,MATCH(J88,$A$5:$A$336,0))<>"",INDEX($C$5:$C$336,MATCH(J88,$A$5:$A$336,0)),"Unassigned")) -> Technology, Media & Telecom | L88: =IF(C88="",1,0) -> 0
A89: A0085 | B89: Acacia Microfinance Limited | D89: Key | E89: Private company | F89: Nairobi | G89: U003 | H89: acaciamicrofinance | I89: =IF(COUNTIF($H$5:$H$336,H89)>1,1,0) -> 1 | J89: =INDEX($A$5:$A$336,MATCH(H89,$H$5:$H$336,0)) -> A0085 | K89: =IF(C89<>"",C89,IF(INDEX($C$5:$C$336,MATCH(J89,$A$5:$A$336,0))<>"",INDEX($C$5:$C$336,MATCH(J89,$A$5:$A$336,0)),"Unassigned")) -> Unassigned | L89: =IF(C89="",1,0) -> 1
A90: A0086 | B90: Zuri Infrastructure Limited | C90: Real Estate & Infrastructure | D90: Key | E90: Listed company | F90: Nairobi | G90: U026 | H90: zuriinfrastructure | I90: =IF(COUNTIF($H$5:$H$336,H90)>1,1,0) -> 0 | J90: =INDEX($A$5:$A$336,MATCH(H90,$H$5:$H$336,0)) -> A0086 | K90: =IF(C90<>"",C90,IF(INDEX($C$5:$C$336,MATCH(J90,$A$5:$A$336,0))<>"",INDEX($C$5:$C$336,MATCH(J90,$A$5:$A$336,0)),"Unassigned")) -> Real Estate & Infrastructure | L90: =IF(C90="",1,0) -> 0
A91: A0087 | B91: Harambee Authority | C91: Public Sector & Development | D91: Key | E91: Listed company | F91: Nairobi | G91: U011 | H91: harambeeauthority | I91: =IF(COUNTIF($H$5:$H$336,H91)>1,1,0) -> 0 | J91: =INDEX($A$5:$A$336,MATCH(H91,$H$5:$H$336,0)) -> A0087 | K91: =IF(C91<>"",C91,IF(INDEX($C$5:$C$336,MATCH(J91,$A$5:$A$336,0))<>"",INDEX($C$5:$C$336,MATCH(J91,$A$5:$A$336,0)),"Unassigned")) -> Public Sector & Development | L91: =IF(C91="",1,0) -> 0
A92: A0088 | B92: Savanna Development Fund | C92: Public Sector & Development | D92: Key | E92: Public sector | F92: Nairobi | G92: U004 | H92: savannadevelopmentfund | I92: =IF(COUNTIF($H$5:$H$336,H92)>1,1,0) -> 0 | J92: =INDEX($A$5:$A$336,MATCH(H92,$H$5:$H$336,0)) -> A0088 | K92: =IF(C92<>"",C92,IF(INDEX($C$5:$C$336,MATCH(J92,$A$5:$A$336,0))<>"",INDEX($C$5:$C$336,MATCH(J92,$A$5:$A$336,0)),"Unassigned")) -> Public Sector & Development | L92: =IF(C92="",1,0) -> 0
A93: A0089 | B93: Harambee Supermarkets Limited | C93: Consumer & Retail | D93: Key | E93: Multinational subsidiary | F93: Kisumu | G93: U027 | H93: harambeesupermarkets | I93: =IF(COUNTIF($H$5:$H$336,H93)>1,1,0) -> 0 | J93: =INDEX($A$5:$A$336,MATCH(H93,$H$5:$H$336,0)) -> A0089 | K93: =IF(C93<>"",C93,IF(INDEX($C$5:$C$336,MATCH(J93,$A$5:$A$336,0))<>"",INDEX($C$5:$C$336,MATCH(J93,$A$5:$A$336,0)),"Unassigned")) -> Consumer & Retail | L93: =IF(C93="",1,0) -> 0
A94: A0090 | B94: Lakeview Agri Limited | C94: Agribusiness | D94: Key | E94: Listed company | F94: Mombasa | G94: U025 | H94: lakeviewagri | I94: =IF(COUNTIF($H$5:$H$336,H94)>1,1,0) -> 0 | J94: =INDEX($A$5:$A$336,MATCH(H94,$H$5:$H$336,0)) -> A0090 | K94: =IF(C94<>"",C94,IF(INDEX($C$5:$C$336,MATCH(J94,$A$5:$A$336,0))<>"",INDEX($C$5:$C$336,MATCH(J94,$A$5:$A$336,0)),"Unassigned")) -> Agribusiness | L94: =IF(C94="",1,0) -> 0
A95: A0091 | B95: Lakeview County Government | C95: Public Sector & Development | D95: Key | E95: Multinational subsidiary | F95: Nairobi | G95: U024 | H95: lakeviewcountygovernment | I95: =IF(COUNTIF($H$5:$H$336,H95)>1,1,0) -> 0 | J95: =INDEX($A$5:$A$336,MATCH(H95,$H$5:$H$336,0)) -> A0091 | K95: =IF(C95<>"",C95,IF(INDEX($C$5:$C$336,MATCH(J95,$A$5:$A$336,0))<>"",INDEX($C$5:$C$336,MATCH(J95,$A$5:$A$336,0)),"Unassigned")) -> Public Sector & Development | L95: =IF(C95="",1,0) -> 0
A96: A0092 | B96: Mara Hotels Limited | C96: Consumer & Retail | D96: Key | E96: Public sector | F96: Nairobi | G96: U012 | H96: marahotels | I96: =IF(COUNTIF($H$5:$H$336,H96)>1,1,0) -> 0 | J96: =INDEX($A$5:$A$336,MATCH(H96,$H$5:$H$336,0)) -> A0092 | K96: =IF(C96<>"",C96,IF(INDEX($C$5:$C$336,MATCH(J96,$A$5:$A$336,0))<>"",INDEX($C$5:$C$336,MATCH(J96,$A$5:$A$336,0)),"Unassigned")) -> Consumer & Retail | L96: =IF(C96="",1,0) -> 0
A97: A0093 | B97: Baobab County Government | C97: Public Sector & Development | D97: Key | E97: Public sector | F97: Nairobi | G97: U026 | H97: baobabcountygovernment | I97: =IF(COUNTIF($H$5:$H$336,H97)>1,1,0) -> 0 | J97: =INDEX($A$5:$A$336,MATCH(H97,$H$5:$H$336,0)) -> A0093 | K97: =IF(C97<>"",C97,IF(INDEX($C$5:$C$336,MATCH(J97,$A$5:$A$336,0))<>"",INDEX($C$5:$C$336,MATCH(J97,$A$5:$A$336,0)),"Unassigned")) -> Public Sector & Development | L97: =IF(C97="",1,0) -> 0
A98: A0094 | B98: Harambee Development Fund | C98: Public Sector & Development | D98: Key | E98: Multinational subsidiary | F98: Nairobi | G98: U015 | H98: harambeedevelopmentfund | I98: =IF(COUNTIF($H$5:$H$336,H98)>1,1,0) -> 0 | J98: =INDEX($A$5:$A$336,MATCH(H98,$H$5:$H$336,0)) -> A0094 | K98: =IF(C98<>"",C98,IF(INDEX($C$5:$C$336,MATCH(J98,$A$5:$A$336,0))<>"",INDEX($C$5:$C$336,MATCH(J98,$A$5:$A$336,0)),"Unassigned")) -> Public Sector & Development | L98: =IF(C98="",1,0) -> 0
A99: A0095 | B99: Equator Supermarkets Limited | C99: Consumer & Retail | D99: Key | E99: Multinational subsidiary | F99: Nairobi | G99: U005 | H99: equatorsupermarkets | I99: =IF(COUNTIF($H$5:$H$336,H99)>1,1,0) -> 0 | J99: =INDEX($A$5:$A$336,MATCH(H99,$H$5:$H$336,0)) -> A0095 | K99: =IF(C99<>"",C99,IF(INDEX($C$5:$C$336,MATCH(J99,$A$5:$A$336,0))<>"",INDEX($C$5:$C$336,MATCH(J99,$A$5:$A$336,0)),"Unassigned")) -> Consumer & Retail | L99: =IF(C99="",1,0) -> 0
A100: A0096 | B100: Equator Energy Limited | C100: Energy & Resources | D100: Key | E100: Public sector | F100: Nakuru | G100: U015 | H100: equatorenergy | I100: =IF(COUNTIF($H$5:$H$336,H100)>1,1,0) -> 0 | J100: =INDEX($A$5:$A$336,MATCH(H100,$H$5:$H$336,0)) -> A0096 | K100: =IF(C100<>"",C100,IF(INDEX($C$5:$C$336,MATCH(J100,$A$5:$A$336,0))<>"",INDEX($C$5:$C$336,MATCH(J100,$A$5:$A$336,0)),"Unassigned")) -> Energy & Resources | L100: =IF(C100="",1,0) -> 0
A101: A0097 | B101: Savanna Telecom Limited | C101: Technology, Media & Telecom | D101: Key | E101: NGO / development partner | F101: Nairobi | G101: U019 | H101: savannatelecom | I101: =IF(COUNTIF($H$5:$H$336,H101)>1,1,0) -> 0 | J101: =INDEX($A$5:$A$336,MATCH(H101,$H$5:$H$336,0)) -> A0097 | K101: =IF(C101<>"",C101,IF(INDEX($C$5:$C$336,MATCH(J101,$A$5:$A$336,0))<>"",INDEX($C$5:$C$336,MATCH(J101,$A$5:$A$336,0)),"Unassigned")) -> Technology, Media & Telecom | L101: =IF(C101="",1,0) -> 0
... A104: A0100 | B104: Mara Networks Limited | C104: Technology, Media & Telecom | D104: Key | E104: Private company | F104: Nairobi | G104: U028 | H104: maranetworks | I104: =IF(COUNTIF($H$5:$H$336,H104)>1,1,0) -> 1 | J104: =INDEX($A$5:$A$336,MATCH(H104,$H$5:$H$336,0)) -> A0100 | K104: =IF(C104<>"",C104,IF(INDEX($C$5:$C$336,MATCH(J104,$A$5:$A$336,0))<>"",INDEX($C$5:$C$336,MATCH(J104,$A$5:$A$336,0)),"Unassigned")) -> Technology, Media & Telecom | L104: =IF(C104="",1,0) -> 0
A105: A0101 | B105: Kibo Pharma Limited | D105: Key | E105: Private company | F105: Nairobi | G105: U023 | H105: kibopharma | I105: =IF(COUNTIF($H$5:$H$336,H105)>1,1,0) -> 0 | J105: =INDEX($A$5:$A$336,MATCH(H105,$H$5:$H$336,0)) -> A0101 | K105: =IF(C105<>"",C105,IF(INDEX($C$5:$C$336,MATCH(J105,$A$5:$A$336,0))<>"",INDEX($C$5:$C$336,MATCH(J105,$A$5:$A$336,0)),"Unassigned")) -> Unassigned | L105: =IF(C105="",1,0) -> 1
